Workbook

Sheet 2026
B1: 46023 | C1: 46054 | D1: 46082 | E1: 46113 | F1: 46143 | G1: 46174 | H1: 46204 | I1: 46235 | J1: 46266 | K1: 46296 | L1: 46327 | M1: 46357 | N1: TOTAL
A2: Usuários | B2: =Dados!B1 -> 10 | C2: =ROUNDDOWN(Dados!$B$1+(B2-(B2*Dados!$B$3)),0) -> 19 | D2: =ROUNDDOWN(Dados!$B$1+(C2-(C2*Dados!$B$3)),0) -> 28 | E2: =ROUNDDOWN(Dados!$B$1+(D2-(D2*Dados!$B$3)),0) -> 37 | F2: =ROUNDDOWN(Dados!$B$1+(E2-(E2*Dados!$B$3)),0) -> 46 | G2: =ROUNDDOWN(Dados!$B$1+(F2-(F2*Dados!$B$3)),0) -> 55 | H2: =ROUNDDOWN(Dados!$B$1+(G2-(G2*Dados!$B$3)),0) -> 63 | I2: =ROUNDDOWN(Dados!$B$1+(H2-(H2*Dados!$B$3)),0) -> 71 | J2: =ROUNDDOWN(Dados!$B$1+(I2-(I2*Dados!$B$3)),0) -> 79 | ... M2: =ROUNDDOWN(Dados!$B$1+(L2-(L2*Dados!$B$3)),0) -> 103 | N2: =M2 -> 103
A4: Receita Total | B4: =ROUND(B5+B6,2) -> 8358 | C4: =ROUND(C5+C6,2) -> 15880.2 | D4: =ROUND(D5+D6,2) -> 23402.4 | E4: =ROUND(E5+E6,2) -> 30924.6 | F4: =ROUND(F5+F6,2) -> 38446.8 | G4: =ROUND(G5+G6,2) -> 45969 | H4: =ROUND(H5+H6,2) -> 52655.4 | I4: =ROUND(I5+I6,2) -> 59341.8 | ... M4: =ROUND(M5+M6,2) -> 86087.4 | N4: =ROUND(SUM(B4:M4),2) -> 579209.4
A5: Receita Fixa - Mensalidade | B5: =ROUND(B2*Dados!$B$5,0) -> 5970 | C5: =ROUND(C2*Dados!$B$5,0) -> 11343 | D5: =ROUND(D2*Dados!$B$5,0) -> 16716 | E5: =ROUND(E2*Dados!$B$5,0) -> 22089 | F5: =ROUND(F2*Dados!$B$5,0) -> 27462 | G5: =ROUND(G2*Dados!$B$5,0) -> 32835 | H5: =ROUND(H2*Dados!$B$5,0) -> 37611 | I5: =ROUND(I2*Dados!$B$5,0) -> 42387 | ... M5: =ROUND(M2*Dados!$B$5,0) -> 61491 | N5: =ROUND(SUM(B5:M5),2) -> 413721
A6: Receita Variável - Comissão sobre Vendas Recuperadas | B6: =IF(Dados!$B$9>0,Dados!$B$9*B2,ROUND(B2*(Dados!$B$11*Dados!$B$7),2)) -> 2388 | C6: =IF(Dados!$B$9>0,Dados!$B$9*C2,ROUND(C2*(Dados!$B$11*Dados!$B$7),2)) -> 4537.2 | D6: =IF(Dados!$B$9>0,Dados!$B$9*D2,ROUND(D2*(Dados!$B$11*Dados!$B$7),2)) -> 6686.4 | E6: =IF(Dados!$B$9>0,Dados!$B$9*E2,ROUND(E2*(Dados!$B$11*Dados!$B$7),2)) -> 8835.6 | F6: =IF(Dados!$B$9>0,Dados!$B$9*F2,ROUND(F2*(Dados!$B$11*Dados!$B$7),2)) -> 10984.8 | G6: =IF(Dados!$B$9>0,Dados!$B$9*G2,ROUND(G2*(Dados!$B$11*Dados!$B$7),2)) -> 13134 | H6: =IF(Dados!$B$9>0,Dados!$B$9*H2,ROUND(H2*(Dados!$B$11*Dados!$B$7),2)) -> 15044.4 | I6: =IF(Dados!$B$9>0,Dados!$B$9*I2,ROUND(I2*(Dados!$B$11*Dados!$B$7),2)) -> 16954.8 | ... M6: =IF(Dados!$B$9>0,Dados!$B$9*M2,ROUND(M2*(Dados!$B$11*Dados!$B$7),2)) -> 24596.4 | N6: =ROUND(SUM(B6:M6),2) -> 165488.4
A7: Impostos | B7: =B4*Dados!$E$2 -> 1337.28 | C7: =C4*Dados!$E$2 -> 2540.832 | D7: =D4*Dados!$E$2 -> 3744.384 | E7: =E4*Dados!$E$2 -> 4947.936 | F7: =F4*Dados!$E$2 -> 6151.488 | G7: =G4*Dados!$E$2 -> 7355.04 | H7: =H4*Dados!$E$2 -> 8424.864 | I7: =I4*Dados!$E$2 -> 9494.688 | ... M7: =M4*Dados!$E$2 -> 13773.984 | N7: =ROUND(SUM(B7:M7),2) -> 92673.5
A8: Receita Líquida | B8: =B4-B7 -> 7020.72 | C8: =C4-C7 -> 13339.368 | D8: =D4-D7 -> 19658.016 | E8: =E4-E7 -> 25976.664 | F8: =F4-F7 -> 32295.312 | G8: =G4-G7 -> 38613.96 | H8: =H4-H7 -> 44230.536 | I8: =I4-I7 -> 49847.112 | ... M8: =M4-M7 -> 72313.416 | N8: =ROUND(SUM(B8:M8),2) -> 486535.9
A9: Resultado Bruto | B9: =ROUND(B8-B14-B15-B16-B17-B18,2) -> 4222.22 | C9: =ROUND(C8-C14-C15-C16-C17-C18,2) -> 8022.22 | D9: =ROUND(D8-D14-D15-D16-D17-D18,2) -> 11822.22 | E9: =ROUND(E8-E14-E15-E16-E17-E18,2) -> 15622.21 | F9: =ROUND(F8-F14-F15-F16-F17-F18,2) -> 19422.21 | G9: =ROUND(G8-G14-G15-G16-G17-G18,2) -> 23222.21 | H9: =ROUND(H8-H14-H15-H16-H17-H18,2) -> 26599.99 | I9: =ROUND(I8-I14-I15-I16-I17-I18,2) -> 29977.76 | ... M9: =ROUND(M8-M14-M15-M16-M17-M18,2) -> 43488.87 | N9: =ROUND(SUM(B9:M9),2) -> 292599.85
A10: Margem Bruta % | B10: =IFERROR(ROUND(B9/B4,2),0) -> 0.51 | C10: =IFERROR(ROUND(C9/C4,2),0) -> 0.51 | D10: =IFERROR(ROUND(D9/D4,2),0) -> 0.51 | E10: =IFERROR(ROUND(E9/E4,2),0) -> 0.51 | F10: =IFERROR(ROUND(F9/F4,2),0) -> 0.51 | G10: =IFERROR(ROUND(G9/G4,2),0) -> 0.51 | H10: =IFERROR(ROUND(H9/H4,2),0) -> 0.51 | I10: =IFERROR(ROUND(I9/I4,2),0) -> 0.51 | ... N10: =IFERROR(ROUND(N9/N4,2),0) -> 0.51
A12: Despesa Total | B12: =ROUND(SUM(B13,B19),2) -> 42546.5 | C12: =ROUND(SUM(C13,C19),2) -> 45097.15 | D12: =ROUND(SUM(D13,D19),2) -> 47615.8 | E12: =ROUND(SUM(E13,E19),2) -> 50134.45 | F12: =ROUND(SUM(F13,F19),2) -> 52653.1 | G12: =ROUND(SUM(G13,G19),2) -> 55171.75 | H12: =ROUND(SUM(H13,H19),2) -> 57410.55 | I12: =ROUND(SUM(I13,I19),2) -> 59649.35 | ... M12: =ROUND(SUM(M13,M19),2) -> 68604.55 | N12: =ROUND(SUM(B12:M12),2) -> 671264.05 | O12: =N12-N8 -> 184728.15
A13: Despesas Variáveis | B13: =B14+B15+B16+B17+B18 -> 2798.5 | C13: =C14+C15+C16+C17+C18 -> 5317.15 | D13: =D14+D15+D16+D17+D18 -> 7835.8 | E13: =E14+E15+E16+E17+E18 -> 10354.45 | F13: =F14+F15+F16+F17+F18 -> 12873.1 | G13: =G14+G15+G16+G17+G18 -> 15391.75 | H13: =H14+H15+H16+H17+H18 -> 17630.55 | I13: =I14+I15+I16+I17+I18 -> 19869.35 | ... M13: =M14+M15+M16+M17+M18 -> 28824.55 | N13: =ROUND(SUM(B13:M13),2) -> 193936.05
A14: Taxas de Checkout e Plataformas | B14: =B5*Dados!$E$1 -> 298.5 | C14: =C5*Dados!$E$1 -> 567.15 | D14: =D5*Dados!$E$1 -> 835.8 | E14: =E5*Dados!$E$1 -> 1104.45 | F14: =F5*Dados!$E$1 -> 1373.1 | G14: =G5*Dados!$E$1 -> 1641.75 | H14: =H5*Dados!$E$1 -> 1880.55 | I14: =I5*Dados!$E$1 -> 2119.35 | ... M14: =M5*Dados!$E$1 -> 3074.55 | N14: =ROUND(SUM(B14:M14),2) -> 20686.05
A15: Servidor | B15: =10*B2 -> 100 | C15: =10*C2 -> 190 | D15: =10*D2 -> 280 | E15: =10*E2 -> 370 | F15: =10*F2 -> 460 | G15: =10*G2 -> 550 | H15: =10*H2 -> 630 | I15: =10*I2 -> 710 | ... M15: =10*M2 -> 1030 | N15: =ROUND(SUM(B15:M15),2) -> 6930
A16: API Oficial Whatsapp | B16: =200*B2 -> 2000 | C16: =200*C2 -> 3800 | D16: =200*D2 -> 5600 | E16: =200*E2 -> 7400 | F16: =200*F2 -> 9200 | G16: =200*G2 -> 11000 | H16: =200*H2 -> 12600 | I16: =200*I2 -> 14200 | ... M16: =200*M2 -> 20600 | N16: =ROUND(SUM(B16:M16),2) -> 138600
A17: Tokens GPT | B17: =10*B2 -> 100 | C17: =10*C2 -> 190 | D17: =10*D2 -> 280 | E17: =10*E2 -> 370 | F17: =10*F2 -> 460 | G17: =10*G2 -> 550 | H17: =10*H2 -> 630 | I17: =10*I2 -> 710 | ... M17: =10*M2 -> 1030 | N17: =ROUND(SUM(B17:M17),2) -> 6930
A18: Telefone | B18: =30*B2 -> 300 | C18: =30*C2 -> 570 | D18: =30*D2 -> 840 | E18: =30*E2 -> 1110 | F18: =30*F2 -> 1380 | G18: =30*G2 -> 1650 | H18: =30*H2 -> 1890 | I18: =30*I2 -> 2130 | ... M18: =30*M2 -> 3090 | N18: =ROUND(SUM(B18:M18),2) -> 20790
A19: Despesas Fixas | B19: =SUM(B20:B40) -> 39748 | C19: =SUM(C20:C40) -> 39780 | D19: =SUM(D20:D40) -> 39780 | E19: =SUM(E20:E40) -> 39780 | F19: =SUM(F20:F40) -> 39780 | G19: =SUM(G20:G40) -> 39780 | H19: =SUM(H20:H40) -> 39780 | I19: =SUM(I20:I40) -> 39780 | ... M19: =SUM(M20:M40) -> 39780 | N19: =ROUND(SUM(B19:M19),2) -> 477328
A20: Pro Labore - CEO | B20: 4440 | C20: 4440 | D20: 4440 | E20: 4440 | F20: 4440 | G20: 4440 | H20: 4440 | I20: 4440 | J20: 4440 | K20: 4440 | L20: 4440 | M20: 4440 | N20: =ROUND(SUM(B20:M20),2) -> 53280
A21: Pro Labore - Operacional | B21: 2220 | C21: 2220 | D21: 2220 | E21: 2220 | F21: 2220 | G21: 2220 | H21: 2220 | I21: 2220 | J21: 2220 | K21: 2220 | L21: 2220 | M21: 2220 | N21: =ROUND(SUM(B21:M21),2) -> 26640
A22: Pro Labore - Operacional | B22: 2220 | C22: 2220 | D22: 2220 | E22: 2220 | F22: 2220 | G22: 2220 | H22: 2220 | I22: 2220 | J22: 2220 | K22: 2220 | L22: 2220 | M22: 2220 | N22: =ROUND(SUM(B22:M22),2) -> 26640
A23: Pro Labore - Operacional | B23: 2220 | C23: 2220 | D23: 2220 | E23: 2220 | F23: 2220 | G23: 2220 | H23: 2220 | I23: 2220 | J23: 2220 | K23: 2220 | L23: 2220 | M23: 2220 | N23: =ROUND(SUM(B23:M23),2) -> 26640
A24: Auxiliar de Serviços Gerais | B24: =Dados!$E$4*Dados!$F$4 -> 1000 | C24: =Dados!$E$4*Dados!$F$4 -> 1000 | D24: =Dados!$E$4*Dados!$F$4 -> 1000 | E24: =Dados!$E$4*Dados!$F$4 -> 1000 | F24: =Dados!$E$4*Dados!$F$4 -> 1000 | G24: =Dados!$E$4*Dados!$F$4 -> 1000 | H24: =Dados!$E$4*Dados!$F$4 -> 1000 | I24: =Dados!$E$4*Dados!$F$4 -> 1000 | ... M24: =Dados!$E$4*Dados!$F$4 -> 1000 | N24: =ROUND(SUM(B24:M24),2) -> 12000
A25: Desenvolvedor | B25: =Dados!$E$5*Dados!$F$5 -> 2000 | C25: =Dados!$E$5*Dados!$F$5 -> 2000 | D25: =Dados!$E$5*Dados!$F$5 -> 2000 | E25: =Dados!$E$5*Dados!$F$5 -> 2000 | F25: =Dados!$E$5*Dados!$F$5 -> 2000 | G25: =Dados!$E$5*Dados!$F$5 -> 2000 | H25: =Dados!$E$5*Dados!$F$5 -> 2000 | I25: =Dados!$E$5*Dados!$F$5 -> 2000 | ... M25: =Dados!$E$5*Dados!$F$5 -> 2000 | N25: =ROUND(SUM(B25:M25),2) -> 24000
A26: Gestor de Tráfego | B26: =Dados!$E$6*Dados!$F$6 -> 2000 | C26: =Dados!$E$6*Dados!$F$6 -> 2000 | D26: =Dados!$E$6*Dados!$F$6 -> 2000 | E26: =Dados!$E$6*Dados!$F$6 -> 2000 | F26: =Dados!$E$6*Dados!$F$6 -> 2000 | G26: =Dados!$E$6*Dados!$F$6 -> 2000 | H26: =Dados!$E$6*Dados!$F$6 -> 2000 | I26: =Dados!$E$6*Dados!$F$6 -> 2000 | ... M26: =Dados!$E$6*Dados!$F$6 -> 2000 | N26: =ROUND(SUM(B26:M26),2) -> 24000
A27: Designer / Editor de Vídeo / Tecnologia | B27: =Dados!$E$7*Dados!$F$7 -> 2000 | C27: =Dados!$E$7*Dados!$F$7 -> 2000 | D27: =Dados!$E$7*Dados!$F$7 -> 2000 | E27: =Dados!$E$7*Dados!$F$7 -> 2000 | F27: =Dados!$E$7*Dados!$F$7 -> 2000 | G27: =Dados!$E$7*Dados!$F$7 -> 2000 | H27: =Dados!$E$7*Dados!$F$7 -> 2000 | I27: =Dados!$E$7*Dados!$F$7 -> 2000 | ... M27: =Dados!$E$7*Dados!$F$7 -> 2000 | N27: =ROUND(SUM(B27:M27),2) -> 24000
A28: Customer Success | B28: =Dados!$E$8*Dados!$F$8 -> 3000 | C28: =Dados!$E$8*Dados!$F$8 -> 3000 | D28: =Dados!$E$8*Dados!$F$8 -> 3000 | E28: =Dados!$E$8*Dados!$F$8 -> 3000 | F28: =Dados!$E$8*Dados!$F$8 -> 3000 | G28: =Dados!$E$8*Dados!$F$8 -> 3000 | H28: =Dados!$E$8*Dados!$F$8 -> 3000 | I28: =Dados!$E$8*Dados!$F$8 -> 3000 | ... M28: =Dados!$E$8*Dados!$F$8 -> 3000 | N28: =ROUND(SUM(B28:M28),2) -> 36000
A29: Vendedores | B29: =Dados!$E$9*Dados!$F$9 -> 0 | C29: 0 | D29: 0 | E29: 0 | F29: 0 | G29: 0 | H29: 0 | I29: 0 | J29: 0 | K29: 0 | L29: 0 | M29: 0 | N29: =ROUND(SUM(B29:M29),2) -> 0
A30: CRM | B30: =Dados!$E$10*Dados!$F$10 -> 300 | C30: 396 | D30: 396 | E30: 396 | F30: 396 | G30: 396 | H30: 396 | I30: 396 | J30: 396 | K30: 396 | L30: 396 | M30: 396 | N30: =ROUND(SUM(B30:M30),2) -> 4656
A31: Internet / Telefonia | B31: 500 | C31: 500 | D31: 500 | E31: 500 | F31: 500 | G31: 500 | H31: 500 | I31: 500 | J31: 500 | K31: 500 | L31: 500 | M31: 500 | N31: =ROUND(SUM(B31:M31),2) -> 6000
A32: Contabilidade | B32: 1000 | C32: 1000 | D32: 1000 | E32: 1000 | F32: 1000 | G32: 1000 | H32: 1000 | I32: 1000 | J32: 1000 | K32: 1000 | L32: 1000 | M32: 1000 | N32: =ROUND(SUM(B32:M32),2) -> 12000
A33: Condominio | B33: 500 | C33: 500 | D33: 500 | E33: 500 | F33: 500 | G33: 500 | H33: 500 | I33: 500 | J33: 500 | K33: 500 | L33: 500 | M33: 500 | N33: =ROUND(SUM(B33:M33),2) -> 6000
A34: Energia Elétrica | B34: 500 | C34: 500 | D34: 500 | E34: 500 | F34: 500 | G34: 500 | H34: 500 | I34: 500 | J34: 500 | K34: 500 | L34: 500 | M34: 500 | N34: =ROUND(SUM(B34:M34),2) -> 6000
A35: Aluguel | B35: 2000 | C35: 2000 | D35: 2000 | E35: 2000 | F35: 2000 | G35: 2000 | H35: 2000 | I35: 2000 | J35: 2000 | K35: 2000 | L35: 2000 | M35: 2000 | N35: =ROUND(SUM(B35:M35),2) -> 24000
A36: Google Workspace | B36: =Dados!$E$11*Dados!$F$11 -> 600 | C36: 686 | D36: 686 | E36: 686 | F36: 686 | G36: 686 | H36: 686 | I36: 686 | J36: 686 | K36: 686 | L36: 686 | M36: 686 | N36: =ROUND(SUM(B36:M36),2) -> 8146
A37: Notion | B37: =Dados!$E$12*Dados!$F$12 -> 1200 | C37: 1050 | D37: 1050 | E37: 1050 | F37: 1050 | G37: 1050 | H37: 1050 | I37: 1050 | J37: 1050 | K37: 1050 | L37: 1050 | M37: 1050 | N37: =ROUND(SUM(B37:M37),2) -> 12750
A38: Treinamentos Udemy | B38: 48 | C38: 48 | D38: 48 | E38: 48 | F38: 48 | G38: 48 | H38: 48 | I38: 48 | J38: 48 | K38: 48 | L38: 48 | M38: 48 | N38: =ROUND(SUM(B38:M38),2) -> 576
A39: Jurídico | B39: 2000 | C39: 2000 | D39: 2000 | E39: 2000 | F39: 2000 | G39: 2000 | H39: 2000 | I39: 2000 | J39: 2000 | K39: 2000 | L39: 2000 | M39: 2000 | N39: =ROUND(SUM(B39:M39),2) -> 24000
A40: Anúncios Online | B40: =Dados!$E$3 -> 10000 | C40: =Dados!$E$3 -> 10000 | D40: =Dados!$E$3 -> 10000 | E40: =Dados!$E$3 -> 10000 | F40: =Dados!$E$3 -> 10000 | G40: =Dados!$E$3 -> 10000 | H40: =Dados!$E$3 -> 10000 | I40: =Dados!$E$3 -> 10000 | ... M40: =Dados!$E$3 -> 10000 | N40: =ROUND(SUM(B40:M40),2) -> 120000
A41: EBITDA = Lucro Líquido | B41: =ROUND(B9-B19,2) -> -35525.78 | C41: =ROUND(C9-C19,2) -> -31757.78 | D41: =ROUND(D9-D19,2) -> -27957.78 | E41: =ROUND(E9-E19,2) -> -24157.79 | F41: =ROUND(F9-F19,2) -> -20357.79 | G41: =ROUND(G9-G19,2) -> -16557.79 | H41: =ROUND(H9-H19,2) -> -13180.01 | I41: =ROUND(I9-I19,2) -> -9802.24 | ... M41: =ROUND(M9-M19,2) -> 3708.87 | N41: =ROUND(SUM(B41:M41),2) -> -184728.15
A42: Margem Líquida % | B42: =B41/B8 -> -5.0601334 | C42: =C41/C8 -> -2.380756 | D42: =D41/D8 -> -1.4222076 | E42: =E41/E8 -> -0.92998046 | F42: =F41/F8 -> -0.63036363 | G42: =G41/G8 -> -0.42880321 | H42: =H41/H8 -> -0.29798441 | I42: =I41/I8 -> -0.1966461 | ... M42: =M41/M8 -> 0.051288823 | N42: =AVERAGE(B42:M42) -> -0.95469448

Sheet 2027
B1: 46388 | C1: 46419 | D1: 46447 | E1: 46478 | F1: 46508 | G1: 46539 | H1: 46569 | I1: 46600 | J1: 46631 | K1: 46661 | L1: 46692 | M1: 46722 | N1: TOTAL
A2: Usuários | B2: =ROUNDDOWN(Dados!$B$1+('2026'!M2-('2026'!M2*Dados!$B$3)),0) -> 110 | C2: =ROUNDDOWN(Dados!$B$1+(B2-(B2*Dados!$B$3)),0) -> 117 | D2: =ROUNDDOWN(Dados!$B$1+(C2-(C2*Dados!$B$3)),0) -> 124 | E2: =ROUNDDOWN(Dados!$B$1+(D2-(D2*Dados!$B$3)),0) -> 131 | F2: =ROUNDDOWN(Dados!$B$1+(E2-(E2*Dados!$B$3)),0) -> 138 | G2: =ROUNDDOWN(Dados!$B$1+(F2-(F2*Dados!$B$3)),0) -> 145 | H2: =ROUNDDOWN(Dados!$B$1+(G2-(G2*Dados!$B$3)),0) -> 152 | I2: =ROUNDDOWN(Dados!$B$1+(H2-(H2*Dados!$B$3)),0) -> 158 | J2: =ROUNDDOWN(Dados!$B$1+(I2-(I2*Dados!$B$3)),0) -> 164 | ... M2: =ROUNDDOWN(Dados!$B$1+(L2-(L2*Dados!$B$3)),0) -> 182 | N2: =M2 -> 182
A4: Receita Total | B4: =ROUND(B5+B6,2) -> 91938 | C4: =ROUND(C5+C6,2) -> 97788.6 | D4: =ROUND(D5+D6,2) -> 103639.2 | E4: =ROUND(E5+E6,2) -> 109489.8 | F4: =ROUND(F5+F6,2) -> 115340.4 | G4: =ROUND(G5+G6,2) -> 121191 | H4: =ROUND(H5+H6,2) -> 127041.6 | I4: =ROUND(I5+I6,2) -> 132056.4 | ... M4: =ROUND(M5+M6,2) -> 152115.6 | N4: =ROUND(SUM(B4:M4),2) -> 1476858.6
A5: Receita Fixa - Mensalidade | B5: =ROUND(B2*Dados!$B$5,0) -> 65670 | C5: =ROUND(C2*Dados!$B$5,0) -> 69849 | D5: =ROUND(D2*Dados!$B$5,0) -> 74028 | E5: =ROUND(E2*Dados!$B$5,0) -> 78207 | F5: =ROUND(F2*Dados!$B$5,0) -> 82386 | G5: =ROUND(G2*Dados!$B$5,0) -> 86565 | H5: =ROUND(H2*Dados!$B$5,0) -> 90744 | I5: =ROUND(I2*Dados!$B$5,0) -> 94326 | ... M5: =ROUND(M2*Dados!$B$5,0) -> 108654 | N5: =ROUND(SUM(B5:M5),2) -> 1054899
A6: Receita Variável - Comissão sobre Vendas Recuperadas | B6: =IF(Dados!$B$9>0,Dados!$B$9*B2,ROUND(B2*(Dados!$B$11*Dados!$B$7),2)) -> 26268 | C6: =IF(Dados!$B$9>0,Dados!$B$9*C2,ROUND(C2*(Dados!$B$11*Dados!$B$7),2)) -> 27939.6 | D6: =IF(Dados!$B$9>0,Dados!$B$9*D2,ROUND(D2*(Dados!$B$11*Dados!$B$7),2)) -> 29611.2 | E6: =IF(Dados!$B$9>0,Dados!$B$9*E2,ROUND(E2*(Dados!$B$11*Dados!$B$7),2)) -> 31282.8 | F6: =IF(Dados!$B$9>0,Dados!$B$9*F2,ROUND(F2*(Dados!$B$11*Dados!$B$7),2)) -> 32954.4 | G6: =IF(Dados!$B$9>0,Dados!$B$9*G2,ROUND(G2*(Dados!$B$11*Dados!$B$7),2)) -> 34626 | H6: =IF(Dados!$B$9>0,Dados!$B$9*H2,ROUND(H2*(Dados!$B$11*Dados!$B$7),2)) -> 36297.6 | I6: =IF(Dados!$B$9>0,Dados!$B$9*I2,ROUND(I2*(Dados!$B$11*Dados!$B$7),2)) -> 37730.4 | ... M6: =IF(Dados!$B$9>0,Dados!$B$9*M2,ROUND(M2*(Dados!$B$11*Dados!$B$7),2)) -> 43461.6 | N6: =ROUND(SUM(B6:M6),2) -> 421959.6
A7: Impostos | B7: =B4*Dados!$E$2 -> 14710.08 | C7: =C4*Dados!$E$2 -> 15646.176 | D7: =D4*Dados!$E$2 -> 16582.272 | E7: =E4*Dados!$E$2 -> 17518.368 | F7: =F4*Dados!$E$2 -> 18454.464 | G7: =G4*Dados!$E$2 -> 19390.56 | H7: =H4*Dados!$E$2 -> 20326.656 | I7: =I4*Dados!$E$2 -> 21129.024 | ... M7: =M4*Dados!$E$2 -> 24338.496 | N7: =ROUND(SUM(B7:M7),2) -> 236297.38
A8: Receita Líquida | B8: =B4-B7 -> 77227.92 | C8: =C4-C7 -> 82142.424 | D8: =D4-D7 -> 87056.928 | E8: =E4-E7 -> 91971.432 | F8: =F4-F7 -> 96885.936 | G8: =G4-G7 -> 101800.44 | H8: =H4-H7 -> 106714.94 | I8: =I4-I7 -> 110927.38 | ... M8: =M4-M7 -> 127777.1 | N8: =ROUND(SUM(B8:M8),2) -> 1240561.2
A9: Receita Bruta | B9: =ROUND(B8-B14-B15-B16-B17-B18,2) -> 46444.42 | C9: =ROUND(C8-C14-C15-C16-C17-C18,2) -> 49399.97 | D9: =ROUND(D8-D14-D15-D16-D17-D18,2) -> 52355.53 | E9: =ROUND(E8-E14-E15-E16-E17-E18,2) -> 55311.08 | F9: =ROUND(F8-F14-F15-F16-F17-F18,2) -> 58266.64 | G9: =ROUND(G8-G14-G15-G16-G17-G18,2) -> 61222.19 | H9: =ROUND(H8-H14-H15-H16-H17-H18,2) -> 64177.74 | I9: =ROUND(I8-I14-I15-I16-I17-I18,2) -> 66711.08 | ... M9: =ROUND(M8-M14-M15-M16-M17-M18,2) -> 76844.4 | N9: =ROUND(SUM(B9:M9),2) -> 746066.27
A10: Margem Bruta % | B10: =IFERROR(ROUND(B9/B4,2),0) -> 0.51 | C10: =IFERROR(ROUND(C9/C4,2),0) -> 0.51 | D10: =IFERROR(ROUND(D9/D4,2),0) -> 0.51 | E10: =IFERROR(ROUND(E9/E4,2),0) -> 0.51 | F10: =IFERROR(ROUND(F9/F4,2),0) -> 0.51 | G10: =IFERROR(ROUND(G9/G4,2),0) -> 0.51 | H10: =IFERROR(ROUND(H9/H4,2),0) -> 0.51 | I10: =IFERROR(ROUND(I9/I4,2),0) -> 0.51 | ... N10: =IFERROR(ROUND(N9/N4,2),0) -> 0.51
A12: Despesa Total | B12: =ROUND(SUM(B13,B19),2) -> 77746.5 | C12: =ROUND(SUM(C13,C19),2) -> 79737.45 | D12: =ROUND(SUM(D13,D19),2) -> 81696.4 | E12: =ROUND(SUM(E13,E19),2) -> 83655.35 | F12: =ROUND(SUM(F13,F19),2) -> 85614.3 | G12: =ROUND(SUM(G13,G19),2) -> 87573.25 | H12: =ROUND(SUM(H13,H19),2) -> 89532.2 | I12: =ROUND(SUM(I13,I19),2) -> 91211.3 | ... M12: =ROUND(SUM(M13,M19),2) -> 97927.7 | N12: =ROUND(SUM(B12:M12),2) -> 1058402.9
A13: Despesas Variáveis | B13: =B14+B15+B16+B17+B18 -> 30783.5 | C13: =C14+C15+C16+C17+C18 -> 32742.45 | D13: =D14+D15+D16+D17+D18 -> 34701.4 | E13: =E14+E15+E16+E17+E18 -> 36660.35 | F13: =F14+F15+F16+F17+F18 -> 38619.3 | G13: =G14+G15+G16+G17+G18 -> 40578.25 | H13: =H14+H15+H16+H17+H18 -> 42537.2 | I13: =I14+I15+I16+I17+I18 -> 44216.3 | ... M13: =M14+M15+M16+M17+M18 -> 50932.7 | N13: =ROUND(SUM(B13:M13),2) -> 494494.95
A14: Taxas de Checkout e Plataformas | B14: =B5*Dados!$E$1 -> 3283.5 | C14: =C5*Dados!$E$1 -> 3492.45 | D14: =D5*Dados!$E$1 -> 3701.4 | E14: =E5*Dados!$E$1 -> 3910.35 | F14: =F5*Dados!$E$1 -> 4119.3 | G14: =G5*Dados!$E$1 -> 4328.25 | H14: =H5*Dados!$E$1 -> 4537.2 | I14: =I5*Dados!$E$1 -> 4716.3 | ... M14: =M5*Dados!$E$1 -> 5432.7 | N14: =ROUND(SUM(B14:M14),2) -> 52744.95
A15: Servidor | B15: =10*B2 -> 1100 | C15: =10*C2 -> 1170 | D15: =10*D2 -> 1240 | E15: =10*E2 -> 1310 | F15: =10*F2 -> 1380 | G15: =10*G2 -> 1450 | H15: =10*H2 -> 1520 | I15: =10*I2 -> 1580 | ... M15: =10*M2 -> 1820 | N15: =ROUND(SUM(B15:M15),2) -> 17670
A16: API Oficial Whatsapp | B16: =200*B2 -> 22000 | C16: =200*C2 -> 23400 | D16: =200*D2 -> 24800 | E16: =200*E2 -> 26200 | F16: =200*F2 -> 27600 | G16: =200*G2 -> 29000 | H16: =200*H2 -> 30400 | I16: =200*I2 -> 31600 | ... M16: =200*M2 -> 36400 | N16: =ROUND(SUM(B16:M16),2) -> 353400
A17: Tokens GPT | B17: =10*B2 -> 1100 | C17: =10*C2 -> 1170 | D17: =10*D2 -> 1240 | E17: =10*E2 -> 1310 | F17: =10*F2 -> 1380 | G17: =10*G2 -> 1450 | H17: =10*H2 -> 1520 | I17: =10*I2 -> 1580 | ... M17: =10*M2 -> 1820 | N17: =ROUND(SUM(B17:M17),2) -> 17670
A18: Telefone | B18: =30*B2 -> 3300 | C18: =30*C2 -> 3510 | D18: =30*D2 -> 3720 | E18: =30*E2 -> 3930 | F18: =30*F2 -> 4140 | G18: =30*G2 -> 4350 | H18: =30*H2 -> 4560 | I18: =30*I2 -> 4740 | ... M18: =30*M2 -> 5460 | N18: =ROUND(SUM(B18:M18),2) -> 53010
A19: Despesas Fixas | B19: =SUM(B20:B40) -> 46963 | C19: =SUM(C20:C40) -> 46995 | D19: =SUM(D20:D40) -> 46995 | E19: =SUM(E20:E40) -> 46995 | F19: =SUM(F20:F40) -> 46995 | G19: =SUM(G20:G40) -> 46995 | H19: =SUM(H20:H40) -> 46995 | I19: =SUM(I20:I40) -> 46995 | ... M19: =SUM(M20:M40) -> 46995 | N19: =ROUND(SUM(B19:M19),2) -> 563908
A20: Pro Labore - CEO | B20: 6660 | C20: 6660 | D20: 6660 | E20: 6660 | F20: 6660 | G20: 6660 | H20: 6660 | I20: 6660 | J20: 6660 | K20: 6660 | L20: 6660 | M20: 6660 | N20: =ROUND(SUM(B20:M20),2) -> 79920
A21: Pro Labore - Operacional | B21: 3885 | C21: 3885 | D21: 3885 | E21: 3885 | F21: 3885 | G21: 3885 | H21: 3885 | I21: 3885 | J21: 3885 | K21: 3885 | L21: 3885 | M21: 3885 | N21: =ROUND(SUM(B21:M21),2) -> 46620
A22: Pro Labore - Operacional | B22: 3885 | C22: 3885 | D22: 3885 | E22: 3885 | F22: 3885 | G22: 3885 | H22: 3885 | I22: 3885 | J22: 3885 | K22: 3885 | L22: 3885 | M22: 3885 | N22: =ROUND(SUM(B22:M22),2) -> 46620
A23: Pro Labore - Operacional | B23: 3885 | C23: 3885 | D23: 3885 | E23: 3885 | F23: 3885 | G23: 3885 | H23: 3885 | I23: 3885 | J23: 3885 | K23: 3885 | L23: 3885 | M23: 3885 | N23: =ROUND(SUM(B23:M23),2) -> 46620
A24: Auxiliar de Serviços Gerais | B24: =Dados!$E$4*Dados!$F$4 -> 1000 | C24: =Dados!$E$4*Dados!$F$4 -> 1000 | D24: =Dados!$E$4*Dados!$F$4 -> 1000 | E24: =Dados!$E$4*Dados!$F$4 -> 1000 | F24: =Dados!$E$4*Dados!$F$4 -> 1000 | G24: =Dados!$E$4*Dados!$F$4 -> 1000 | H24: =Dados!$E$4*Dados!$F$4 -> 1000 | I24: =Dados!$E$4*Dados!$F$4 -> 1000 | ... M24: =Dados!$E$4*Dados!$F$4 -> 1000 | N24: =ROUND(SUM(B24:M24),2) -> 12000
A25: Desenvolvedor | B25: =Dados!$E$5*Dados!$F$5 -> 2000 | C25: =Dados!$E$5*Dados!$F$5 -> 2000 | D25: =Dados!$E$5*Dados!$F$5 -> 2000 | E25: =Dados!$E$5*Dados!$F$5 -> 2000 | F25: =Dados!$E$5*Dados!$F$5 -> 2000 | G25: =Dados!$E$5*Dados!$F$5 -> 2000 | H25: =Dados!$E$5*Dados!$F$5 -> 2000 | I25: =Dados!$E$5*Dados!$F$5 -> 2000 | ... M25: =Dados!$E$5*Dados!$F$5 -> 2000 | N25: =ROUND(SUM(B25:M25),2) -> 24000
A26: Gestor de Tráfego | B26: =Dados!$E$6*Dados!$F$6 -> 2000 | C26: =Dados!$E$6*Dados!$F$6 -> 2000 | D26: =Dados!$E$6*Dados!$F$6 -> 2000 | E26: =Dados!$E$6*Dados!$F$6 -> 2000 | F26: =Dados!$E$6*Dados!$F$6 -> 2000 | G26: =Dados!$E$6*Dados!$F$6 -> 2000 | H26: =Dados!$E$6*Dados!$F$6 -> 2000 | I26: =Dados!$E$6*Dados!$F$6 -> 2000 | ... M26: =Dados!$E$6*Dados!$F$6 -> 2000 | N26: =ROUND(SUM(B26:M26),2) -> 24000
A27: Designer / Editor de Vídeo / Tecnologia | B27: =Dados!$E$7*Dados!$F$7 -> 2000 | C27: =Dados!$E$7*Dados!$F$7 -> 2000 | D27: =Dados!$E$7*Dados!$F$7 -> 2000 | E27: =Dados!$E$7*Dados!$F$7 -> 2000 | F27: =Dados!$E$7*Dados!$F$7 -> 2000 | G27: =Dados!$E$7*Dados!$F$7 -> 2000 | H27: =Dados!$E$7*Dados!$F$7 -> 2000 | I27: =Dados!$E$7*Dados!$F$7 -> 2000 | ... M27: =Dados!$E$7*Dados!$F$7 -> 2000 | N27: =ROUND(SUM(B27:M27),2) -> 24000
A28: Customer Success | B28: =Dados!$E$8*Dados!$F$8 -> 3000 | C28: =Dados!$E$8*Dados!$F$8 -> 3000 | D28: =Dados!$E$8*Dados!$F$8 -> 3000 | E28: =Dados!$E$8*Dados!$F$8 -> 3000 | F28: =Dados!$E$8*Dados!$F$8 -> 3000 | G28: =Dados!$E$8*Dados!$F$8 -> 3000 | H28: =Dados!$E$8*Dados!$F$8 -> 3000 | I28: =Dados!$E$8*Dados!$F$8 -> 3000 | ... M28: =Dados!$E$8*Dados!$F$8 -> 3000 | N28: =ROUND(SUM(B28:M28),2) -> 36000
A29: Vendedores | B29: =Dados!$E$9*Dados!$F$9 -> 0 | C29: 0 | D29: 0 | E29: 0 | F29: 0 | G29: 0 | H29: 0 | I29: 0 | J29: 0 | K29: 0 | L29: 0 | M29: 0 | N29: =ROUND(SUM(B29:M29),2) -> 0
A30: CRM | B30: =Dados!$E$10*Dados!$F$10 -> 300 | C30: 396 | D30: 396 | E30: 396 | F30: 396 | G30: 396 | H30: 396 | I30: 396 | J30: 396 | K30: 396 | L30: 396 | M30: 396 | N30: =ROUND(SUM(B30:M30),2) -> 4656
A31: Internet / Telefonia | B31: 500 | C31: 500 | D31: 500 | E31: 500 | F31: 500 | G31: 500 | H31: 500 | I31: 500 | J31: 500 | K31: 500 | L31: 500 | M31: 500 | N31: =ROUND(SUM(B31:M31),2) -> 6000
A32: Contabilidade | B32: 1000 | C32: 1000 | D32: 1000 | E32: 1000 | F32: 1000 | G32: 1000 | H32: 1000 | I32: 1000 | J32: 1000 | K32: 1000 | L32: 1000 | M32: 1000 | N32: =ROUND(SUM(B32:M32),2) -> 12000
A33: Condominio | B33: 500 | C33: 500 | D33: 500 | E33: 500 | F33: 500 | G33: 500 | H33: 500 | I33: 500 | J33: 500 | K33: 500 | L33: 500 | M33: 500 | N33: =ROUND(SUM(B33:M33),2) -> 6000
A34: Energia Elétrica | B34: 500 | C34: 500 | D34: 500 | E34: 500 | F34: 500 | G34: 500 | H34: 500 | I34: 500 | J34: 500 | K34: 500 | L34: 500 | M34: 500 | N34: =ROUND(SUM(B34:M34),2) -> 6000
A35: Aluguel | B35: 2000 | C35: 2000 | D35: 2000 | E35: 2000 | F35: 2000 | G35: 2000 | H35: 2000 | I35: 2000 | J35: 2000 | K35: 2000 | L35: 2000 | M35: 2000 | N35: =ROUND(SUM(B35:M35),2) -> 24000
A36: Google Workspace | B36: =Dados!$E$11*Dados!$F$11 -> 600 | C36: 686 | D36: 686 | E36: 686 | F36: 686 | G36: 686 | H36: 686 | I36: 686 | J36: 686 | K36: 686 | L36: 686 | M36: 686 | N36: =ROUND(SUM(B36:M36),2) -> 8146
A37: Notion | B37: =Dados!$E$12*Dados!$F$12 -> 1200 | C37: 1050 | D37: 1050 | E37: 1050 | F37: 1050 | G37: 1050 | H37: 1050 | I37: 1050 | J37: 1050 | K37: 1050 | L37: 1050 | M37: 1050 | N37: =ROUND(SUM(B37:M37),2) -> 12750
A38: Treinamentos Udemy | B38: 48 | C38: 48 | D38: 48 | E38: 48 | F38: 48 | G38: 48 | H38: 48 | I38: 48 | J38: 48 | K38: 48 | L38: 48 | M38: 48 | N38: =ROUND(SUM(B38:M38),2) -> 576
A39: Jurídico | B39: 2000 | C39: 2000 | D39: 2000 | E39: 2000 | F39: 2000 | G39: 2000 | H39: 2000 | I39: 2000 | J39: 2000 | K39: 2000 | L39: 2000 | M39: 2000 | N39: =ROUND(SUM(B39:M39),2) -> 24000
A40: Anúncios Online | B40: =Dados!$E$3 -> 10000 | C40: =Dados!$E$3 -> 10000 | D40: =Dados!$E$3 -> 10000 | E40: =Dados!$E$3 -> 10000 | F40: =Dados!$E$3 -> 10000 | G40: =Dados!$E$3 -> 10000 | H40: =Dados!$E$3 -> 10000 | I40: =Dados!$E$3 -> 10000 | ... M40: =Dados!$E$3 -> 10000 | N40: =ROUND(SUM(B40:M40),2) -> 120000
A41: EBITDA = Lucro Líquido | B41: =ROUND(B9-B19,2) -> -518.58 | C41: =ROUND(C9-C19,2) -> 2404.97 | D41: =ROUND(D9-D19,2) -> 5360.53 | E41: =ROUND(E9-E19,2) -> 8316.08 | F41: =ROUND(F9-F19,2) -> 11271.64 | G41: =ROUND(G9-G19,2) -> 14227.19 | H41: =ROUND(H9-H19,2) -> 17182.74 | I41: =ROUND(I9-I19,2) -> 19716.08 | ... M41: =ROUND(M9-M19,2) -> 29849.4 | N41: =ROUND(SUM(B41:M41),2) -> 182158.27
A42: Margem Líquida % | B42: =B41/B8 -> -0.006714929 | C42: =C41/C8 -> 0.02927805 | D42: =D41/D8 -> 0.061574996 | E42: =E41/E8 -> 0.090420251 | F42: =F41/F8 -> 0.11633928 | G42: =G41/G8 -> 0.13975568 | H42: =H41/H8 -> 0.16101531 | I42: =I41/I8 -> 0.17773863 | ... M42: =M41/M8 -> 0.23360523 | N42: =AVERAGE(B42:M42) -> 0.13541345

Sheet 2028
B1: 46753 | C1: 46784 | D1: 46813 | E1: 46844 | F1: 46874 | G1: 46905 | H1: 46935 | I1: 46966 | J1: 46997 | K1: 47027 | L1: 47058 | M1: 47088 | N1: TOTAL
A2: Usuários | B2: =ROUNDDOWN(Dados!$B$1+('2027'!M2-('2027'!M2*Dados!$B$3)),0) -> 188 | C2: =ROUNDDOWN(Dados!$B$1+(B2-(B2*Dados!$B$3)),0) -> 194 | D2: =ROUNDDOWN(Dados!$B$1+(C2-(C2*Dados!$B$3)),0) -> 200 | E2: =ROUNDDOWN(Dados!$B$1+(D2-(D2*Dados!$B$3)),0) -> 206 | F2: =ROUNDDOWN(Dados!$B$1+(E2-(E2*Dados!$B$3)),0) -> 211 | G2: =ROUNDDOWN(Dados!$B$1+(F2-(F2*Dados!$B$3)),0) -> 216 | H2: =ROUNDDOWN(Dados!$B$1+(G2-(G2*Dados!$B$3)),0) -> 221 | I2: =ROUNDDOWN(Dados!$B$1+(H2-(H2*Dados!$B$3)),0) -> 226 | J2: =ROUNDDOWN(Dados!$B$1+(I2-(I2*Dados!$B$3)),0) -> 231 | ... M2: =ROUNDDOWN(Dados!$B$1+(L2-(L2*Dados!$B$3)),0) -> 246 | N2: =M2 -> 246
A4: Receita Total | B4: =ROUND(B5+B6,2) -> 157130.4 | C4: =ROUND(C5+C6,2) -> 162145.2 | D4: =ROUND(D5+D6,2) -> 167160 | E4: =ROUND(E5+E6,2) -> 172174.8 | F4: =ROUND(F5+F6,2) -> 176353.8 | G4: =ROUND(G5+G6,2) -> 180532.8 | H4: =ROUND(H5+H6,2) -> 184711.8 | I4: =ROUND(I5+I6,2) -> 188890.8 | ... M4: =ROUND(M5+M6,2) -> 205606.8 | N4: =ROUND(SUM(B4:M4),2) -> 2186452.8
A5: Receita Fixa - Mensalidade | B5: =ROUND(B2*Dados!$B$5,0) -> 112236 | C5: =ROUND(C2*Dados!$B$5,0) -> 115818 | D5: =ROUND(D2*Dados!$B$5,0) -> 119400 | E5: =ROUND(E2*Dados!$B$5,0) -> 122982 | F5: =ROUND(F2*Dados!$B$5,0) -> 125967 | G5: =ROUND(G2*Dados!$B$5,0) -> 128952 | H5: =ROUND(H2*Dados!$B$5,0) -> 131937 | I5: =ROUND(I2*Dados!$B$5,0) -> 134922 | ... M5: =ROUND(M2*Dados!$B$5,0) -> 146862 | N5: =ROUND(SUM(B5:M5),2) -> 1561752
A6: Receita Variável - Comissão sobre Vendas Recuperadas | B6: =IF(Dados!$B$9>0,Dados!$B$9*B2,ROUND(B2*(Dados!$B$11*Dados!$B$7),2)) -> 44894.4 | C6: =IF(Dados!$B$9>0,Dados!$B$9*C2,ROUND(C2*(Dados!$B$11*Dados!$B$7),2)) -> 46327.2 | D6: =IF(Dados!$B$9>0,Dados!$B$9*D2,ROUND(D2*(Dados!$B$11*Dados!$B$7),2)) -> 47760 | E6: =IF(Dados!$B$9>0,Dados!$B$9*E2,ROUND(E2*(Dados!$B$11*Dados!$B$7),2)) -> 49192.8 | F6: =IF(Dados!$B$9>0,Dados!$B$9*F2,ROUND(F2*(Dados!$B$11*Dados!$B$7),2)) -> 50386.8 | G6: =IF(Dados!$B$9>0,Dados!$B$9*G2,ROUND(G2*(Dados!$B$11*Dados!$B$7),2)) -> 51580.8 | H6: =IF(Dados!$B$9>0,Dados!$B$9*H2,ROUND(H2*(Dados!$B$11*Dados!$B$7),2)) -> 52774.8 | I6: =IF(Dados!$B$9>0,Dados!$B$9*I2,ROUND(I2*(Dados!$B$11*Dados!$B$7),2)) -> 53968.8 | ... M6: =IF(Dados!$B$9>0,Dados!$B$9*M2,ROUND(M2*(Dados!$B$11*Dados!$B$7),2)) -> 58744.8 | N6: =ROUND(SUM(B6:M6),2) -> 624700.8
A7: Impostos | B7: =B4*Dados!$E$2 -> 25140.864 | C7: =C4*Dados!$E$2 -> 25943.232 | D7: =D4*Dados!$E$2 -> 26745.6 | E7: =E4*Dados!$E$2 -> 27547.968 | F7: =F4*Dados!$E$2 -> 28216.608 | G7: =G4*Dados!$E$2 -> 28885.248 | H7: =H4*Dados!$E$2 -> 29553.888 | I7: =I4*Dados!$E$2 -> 30222.528 | ... M7: =M4*Dados!$E$2 -> 32897.088 | N7: =ROUND(SUM(B7:M7),2) -> 349832.45
A8: Receita Líquida | B8: =B4-B7 -> 131989.54 | C8: =C4-C7 -> 136201.97 | D8: =D4-D7 -> 140414.4 | E8: =E4-E7 -> 144626.83 | F8: =F4-F7 -> 148137.19 | G8: =G4-G7 -> 151647.55 | H8: =H4-H7 -> 155157.91 | I8: =I4-I7 -> 158668.27 | ... M8: =M4-M7 -> 172709.71 | N8: =ROUND(SUM(B8:M8),2) -> 1836620.4
A9: Receita Bruta | B9: =ROUND(B8-B14-B15-B16-B17-B18,2) -> 79377.74 | C9: =ROUND(C8-C14-C15-C16-C17-C18,2) -> 81911.07 | D9: =ROUND(D8-D14-D15-D16-D17-D18,2) -> 84444.4 | E9: =ROUND(E8-E14-E15-E16-E17-E18,2) -> 86977.73 | F9: =ROUND(F8-F14-F15-F16-F17-F18,2) -> 89088.84 | G9: =ROUND(G8-G14-G15-G16-G17-G18,2) -> 91199.95 | H9: =ROUND(H8-H14-H15-H16-H17-H18,2) -> 93311.06 | I9: =ROUND(I8-I14-I15-I16-I17-I18,2) -> 95422.17 | ... M9: =ROUND(M8-M14-M15-M16-M17-M18,2) -> 103866.61 | N9: =ROUND(SUM(B9:M9),2) -> 1104532.7
A10: Margem Bruta % | B10: =IFERROR(ROUND(B9/B4,2),0) -> 0.51 | C10: =IFERROR(ROUND(C9/C4,2),0) -> 0.51 | D10: =IFERROR(ROUND(D9/D4,2),0) -> 0.51 | E10: =IFERROR(ROUND(E9/E4,2),0) -> 0.51 | F10: =IFERROR(ROUND(F9/F4,2),0) -> 0.51 | G10: =IFERROR(ROUND(G9/G4,2),0) -> 0.51 | H10: =IFERROR(ROUND(H9/H4,2),0) -> 0.51 | I10: =IFERROR(ROUND(I9/I4,2),0) -> 0.51 | ... N10: =IFERROR(ROUND(N9/N4,2),0) -> 0.51
A12: Despesa Total | B12: =ROUND(SUM(B13,B19),2) -> 106789.8 | C12: =ROUND(SUM(C13,C19),2) -> 108468.9 | D12: =ROUND(SUM(D13,D19),2) -> 110148 | E12: =ROUND(SUM(E13,E19),2) -> 111827.1 | F12: =ROUND(SUM(F13,F19),2) -> 113226.35 | G12: =ROUND(SUM(G13,G19),2) -> 114625.6 | H12: =ROUND(SUM(H13,H19),2) -> 116024.85 | I12: =ROUND(SUM(I13,I19),2) -> 117424.1 | ... M12: =ROUND(SUM(M13,M19),2) -> 123021.1 | N12: =ROUND(SUM(B12:M12),2) -> 1382223.6
A13: Despesas Variáveis | B13: =B14+B15+B16+B17+B18 -> 52611.8 | C13: =C14+C15+C16+C17+C18 -> 54290.9 | D13: =D14+D15+D16+D17+D18 -> 55970 | E13: =E14+E15+E16+E17+E18 -> 57649.1 | F13: =F14+F15+F16+F17+F18 -> 59048.35 | G13: =G14+G15+G16+G17+G18 -> 60447.6 | H13: =H14+H15+H16+H17+H18 -> 61846.85 | I13: =I14+I15+I16+I17+I18 -> 63246.1 | ... M13: =M14+M15+M16+M17+M18 -> 68843.1 | N13: =ROUND(SUM(B13:M13),2) -> 732087.6
A14: Taxas de Checkout e Plataformas | B14: =B5*Dados!$E$1 -> 5611.8 | C14: =C5*Dados!$E$1 -> 5790.9 | D14: =D5*Dados!$E$1 -> 5970 | E14: =E5*Dados!$E$1 -> 6149.1 | F14: =F5*Dados!$E$1 -> 6298.35 | G14: =G5*Dados!$E$1 -> 6447.6 | H14: =H5*Dados!$E$1 -> 6596.85 | I14: =I5*Dados!$E$1 -> 6746.1 | ... M14: =M5*Dados!$E$1 -> 7343.1 | N14: =ROUND(SUM(B14:M14),2) -> 78087.6
A15: Servidor | B15: =10*B2 -> 1880 | C15: =10*C2 -> 1940 | D15: =10*D2 -> 2000 | E15: =10*E2 -> 2060 | F15: =10*F2 -> 2110 | G15: =10*G2 -> 2160 | H15: =10*H2 -> 2210 | I15: =10*I2 -> 2260 | ... M15: =10*M2 -> 2460 | N15: =ROUND(SUM(B15:M15),2) -> 26160
A16: API Oficial Whatsapp | B16: =200*B2 -> 37600 | C16: =200*C2 -> 38800 | D16: =200*D2 -> 40000 | E16: =200*E2 -> 41200 | F16: =200*F2 -> 42200 | G16: =200*G2 -> 43200 | H16: =200*H2 -> 44200 | I16: =200*I2 -> 45200 | ... M16: =200*M2 -> 49200 | N16: =ROUND(SUM(B16:M16),2) -> 523200
A17: Tokens GPT | B17: =10*B2 -> 1880 | C17: =10*C2 -> 1940 | D17: =10*D2 -> 2000 | E17: =10*E2 -> 2060 | F17: =10*F2 -> 2110 | G17: =10*G2 -> 2160 | H17: =10*H2 -> 2210 | I17: =10*I2 -> 2260 | ... M17: =10*M2 -> 2460 | N17: =ROUND(SUM(B17:M17),2) -> 26160
A18: Telefone | B18: =30*B2 -> 5640 | C18: =30*C2 -> 5820 | D18: =30*D2 -> 6000 | E18: =30*E2 -> 6180 | F18: =30*F2 -> 6330 | G18: =30*G2 -> 6480 | H18: =30*H2 -> 6630 | I18: =30*I2 -> 6780 | ... M18: =30*M2 -> 7380 | N18: =ROUND(SUM(B18:M18),2) -> 78480
A19: Despesas Fixas | B19: =SUM(B20:B40) -> 54178 | C19: =SUM(C20:C40) -> 54178 | D19: =SUM(D20:D40) -> 54178 | E19: =SUM(E20:E40) -> 54178 | F19: =SUM(F20:F40) -> 54178 | G19: =SUM(G20:G40) -> 54178 | H19: =SUM(H20:H40) -> 54178 | I19: =SUM(I20:I40) -> 54178 | ... M19: =SUM(M20:M40) -> 54178 | N19: =ROUND(SUM(B19:M19),2) -> 650136
A20: Pro Labore - CEO | B20: 8880 | C20: 8880 | D20: 8880 | E20: 8880 | F20: 8880 | G20: 8880 | H20: 8880 | I20: 8880 | J20: 8880 | K20: 8880 | L20: 8880 | M20: 8880 | N20: =ROUND(SUM(B20:M20),2) -> 106560
A21: Pro Labore - Operacional | B21: 5550 | C21: 5550 | D21: 5550 | E21: 5550 | F21: 5550 | G21: 5550 | H21: 5550 | I21: 5550 | J21: 5550 | K21: 5550 | L21: 5550 | M21: 5550 | N21: =ROUND(SUM(B21:M21),2) -> 66600
A22: Pro Labore - Operacional | B22: 5550 | C22: 5550 | D22: 5550 | E22: 5550 | F22: 5550 | G22: 5550 | H22: 5550 | I22: 5550 | J22: 5550 | K22: 5550 | L22: 5550 | M22: 5550 | N22: =ROUND(SUM(B22:M22),2) -> 66600
A23: Pro Labore - Operacional | B23: 5550 | C23: 5550 | D23: 5550 | E23: 5550 | F23: 5550 | G23: 5550 | H23: 5550 | I23: 5550 | J23: 5550 | K23: 5550 | L23: 5550 | M23: 5550 | N23: =ROUND(SUM(B23:M23),2) -> 66600
A24: Auxiliar de Serviços Gerais | B24: =Dados!$E$4*Dados!$F$4 -> 1000 | C24: =Dados!$E$4*Dados!$F$4 -> 1000 | D24: =Dados!$E$4*Dados!$F$4 -> 1000 | E24: =Dados!$E$4*Dados!$F$4 -> 1000 | F24: =Dados!$E$4*Dados!$F$4 -> 1000 | G24: =Dados!$E$4*Dados!$F$4 -> 1000 | H24: =Dados!$E$4*Dados!$F$4 -> 1000 | I24: =Dados!$E$4*Dados!$F$4 -> 1000 | ... M24: =Dados!$E$4*Dados!$F$4 -> 1000 | N24: =ROUND(SUM(B24:M24),2) -> 12000
A25: Desenvolvedor | B25: =Dados!$E$5*Dados!$F$5 -> 2000 | C25: =Dados!$E$5*Dados!$F$5 -> 2000 | D25: =Dados!$E$5*Dados!$F$5 -> 2000 | E25: =Dados!$E$5*Dados!$F$5 -> 2000 | F25: =Dados!$E$5*Dados!$F$5 -> 2000 | G25: =Dados!$E$5*Dados!$F$5 -> 2000 | H25: =Dados!$E$5*Dados!$F$5 -> 2000 | I25: =Dados!$E$5*Dados!$F$5 -> 2000 | ... M25: =Dados!$E$5*Dados!$F$5 -> 2000 | N25: =ROUND(SUM(B25:M25),2) -> 24000
A26: Gestor de Tráfego | B26: =Dados!$E$6*Dados!$F$6 -> 2000 | C26: =Dados!$E$6*Dados!$F$6 -> 2000 | D26: =Dados!$E$6*Dados!$F$6 -> 2000 | E26: =Dados!$E$6*Dados!$F$6 -> 2000 | F26: =Dados!$E$6*Dados!$F$6 -> 2000 | G26: =Dados!$E$6*Dados!$F$6 -> 2000 | H26: =Dados!$E$6*Dados!$F$6 -> 2000 | I26: =Dados!$E$6*Dados!$F$6 -> 2000 | ... M26: =Dados!$E$6*Dados!$F$6 -> 2000 | N26: =ROUND(SUM(B26:M26),2) -> 24000
A27: Designer / Editor de Vídeo / Tecnologia | B27: =Dados!$E$7*Dados!$F$7 -> 2000 | C27: =Dados!$E$7*Dados!$F$7 -> 2000 | D27: =Dados!$E$7*Dados!$F$7 -> 2000 | E27: =Dados!$E$7*Dados!$F$7 -> 2000 | F27: =Dados!$E$7*Dados!$F$7 -> 2000 | G27: =Dados!$E$7*Dados!$F$7 -> 2000 | H27: =Dados!$E$7*Dados!$F$7 -> 2000 | I27: =Dados!$E$7*Dados!$F$7 -> 2000 | ... M27: =Dados!$E$7*Dados!$F$7 -> 2000 | N27: =ROUND(SUM(B27:M27),2) -> 24000
A28: Customer Success | B28: =Dados!$E$8*Dados!$F$8 -> 3000 | C28: =Dados!$E$8*Dados!$F$8 -> 3000 | D28: =Dados!$E$8*Dados!$F$8 -> 3000 | E28: =Dados!$E$8*Dados!$F$8 -> 3000 | F28: =Dados!$E$8*Dados!$F$8 -> 3000 | G28: =Dados!$E$8*Dados!$F$8 -> 3000 | H28: =Dados!$E$8*Dados!$F$8 -> 3000 | I28: =Dados!$E$8*Dados!$F$8 -> 3000 | ... M28: =Dados!$E$8*Dados!$F$8 -> 3000 | N28: =ROUND(SUM(B28:M28),2) -> 36000
A29: Vendedores | B29: =Dados!$E$9*Dados!$F$9 -> 0 | C29: =Dados!$E$9*Dados!$F$9 -> 0 | D29: =Dados!$E$9*Dados!$F$9 -> 0 | E29: =Dados!$E$9*Dados!$F$9 -> 0 | F29: =Dados!$E$9*Dados!$F$9 -> 0 | G29: =Dados!$E$9*Dados!$F$9 -> 0 | H29: =Dados!$E$9*Dados!$F$9 -> 0 | I29: =Dados!$E$9*Dados!$F$9 -> 0 | ... M29: =Dados!$E$9*Dados!$F$9 -> 0 | N29: =ROUND(SUM(B29:M29),2) -> 0
A30: CRM | B30: =Dados!$E$10*Dados!$F$10 -> 300 | C30: =Dados!$E$10*Dados!$F$10 -> 300 | D30: =Dados!$E$10*Dados!$F$10 -> 300 | E30: =Dados!$E$10*Dados!$F$10 -> 300 | F30: =Dados!$E$10*Dados!$F$10 -> 300 | G30: =Dados!$E$10*Dados!$F$10 -> 300 | H30: =Dados!$E$10*Dados!$F$10 -> 300 | I30: =Dados!$E$10*Dados!$F$10 -> 300 | ... M30: =Dados!$E$10*Dados!$F$10 -> 300 | N30: =ROUND(SUM(B30:M30),2) -> 3600
A31: Internet / Telefonia | B31: 500 | C31: 500 | D31: 500 | E31: 500 | F31: 500 | G31: 500 | H31: 500 | I31: 500 | J31: 500 | K31: 500 | L31: 500 | M31: 500 | N31: =ROUND(SUM(B31:M31),2) -> 6000
A32: Contabilidade | B32: 1000 | C32: 1000 | D32: 1000 | E32: 1000 | F32: 1000 | G32: 1000 | H32: 1000 | I32: 1000 | J32: 1000 | K32: 1000 | L32: 1000 | M32: 1000 | N32: =ROUND(SUM(B32:M32),2) -> 12000
A33: Condominio | B33: 500 | C33: 500 | D33: 500 | E33: 500 | F33: 500 | G33: 500 | H33: 500 | I33: 500 | J33: 500 | K33: 500 | L33: 500 | M33: 500 | N33: =ROUND(SUM(B33:M33),2) -> 6000
A34: Energia Elétrica | B34: 500 | C34: 500 | D34: 500 | E34: 500 | F34: 500 | G34: 500 | H34: 500 | I34: 500 | J34: 500 | K34: 500 | L34: 500 | M34: 500 | N34: =ROUND(SUM(B34:M34),2) -> 6000
A35: Aluguel | B35: 2000 | C35: 2000 | D35: 2000 | E35: 2000 | F35: 2000 | G35: 2000 | H35: 2000 | I35: 2000 | J35: 2000 | K35: 2000 | L35: 2000 | M35: 2000 | N35: =ROUND(SUM(B35:M35),2) -> 24000
A36: Google Workspace | B36: =Dados!$E$11*Dados!$F$11 -> 600 | C36: =Dados!$E$11*Dados!$F$11 -> 600 | D36: =Dados!$E$11*Dados!$F$11 -> 600 | E36: =Dados!$E$11*Dados!$F$11 -> 600 | F36: =Dados!$E$11*Dados!$F$11 -> 600 | G36: =Dados!$E$11*Dados!$F$11 -> 600 | H36: =Dados!$E$11*Dados!$F$11 -> 600 | I36: =Dados!$E$11*Dados!$F$11 -> 600 | ... M36: =Dados!$E$11*Dados!$F$11 -> 600 | N36: =ROUND(SUM(B36:M36),2) -> 7200
A37: Notion | B37: =Dados!$E$12*Dados!$F$12 -> 1200 | C37: =Dados!$E$12*Dados!$F$12 -> 1200 | D37: =Dados!$E$12*Dados!$F$12 -> 1200 | E37: =Dados!$E$12*Dados!$F$12 -> 1200 | F37: =Dados!$E$12*Dados!$F$12 -> 1200 | G37: =Dados!$E$12*Dados!$F$12 -> 1200 | H37: =Dados!$E$12*Dados!$F$12 -> 1200 | I37: =Dados!$E$12*Dados!$F$12 -> 1200 | ... M37: =Dados!$E$12*Dados!$F$12 -> 1200 | N37: =ROUND(SUM(B37:M37),2) -> 14400
A38: Treinamentos Udemy | B38: 48 | C38: 48 | D38: 48 | E38: 48 | F38: 48 | G38: 48 | H38: 48 | I38: 48 | J38: 48 | K38: 48 | L38: 48 | M38: 48 | N38: =ROUND(SUM(B38:M38),2) -> 576
A39: Jurídico | B39: 2000 | C39: 2000 | D39: 2000 | E39: 2000 | F39: 2000 | G39: 2000 | H39: 2000 | I39: 2000 | J39: 2000 | K39: 2000 | L39: 2000 | M39: 2000 | N39: =ROUND(SUM(B39:M39),2) -> 24000
A40: Anúncios Online | B40: =Dados!$E$3 -> 10000 | C40: =Dados!$E$3 -> 10000 | D40: =Dados!$E$3 -> 10000 | E40: =Dados!$E$3 -> 10000 | F40: =Dados!$E$3 -> 10000 | G40: =Dados!$E$3 -> 10000 | H40: =Dados!$E$3 -> 10000 | I40: =Dados!$E$3 -> 10000 | ... M40: =Dados!$E$3 -> 10000 | N40: =ROUND(SUM(B40:M40),2) -> 120000
A41: EBITDA = Lucro Líquido | B41: =ROUND(B9-B19,2) -> 25199.74 | C41: =ROUND(C9-C19,2) -> 27733.07 | D41: =ROUND(D9-D19,2) -> 30266.4 | E41: =ROUND(E9-E19,2) -> 32799.73 | F41: =ROUND(F9-F19,2) -> 34910.84 | G41: =ROUND(G9-G19,2) -> 37021.95 | H41: =ROUND(H9-H19,2) -> 39133.06 | I41: =ROUND(I9-I19,2) -> 41244.17 | ... M41: =ROUND(M9-M19,2) -> 49688.61 | N41: =ROUND(SUM(B41:M41),2) -> 454396.74
A42: Margem Líquida % | B42: =B41/B8 -> 0.19092226 | C42: =C41/C8 -> 0.20361725 | D42: =D41/D8 -> 0.21555054 | E42: =E41/E8 -> 0.22678869 | F42: =F41/F8 -> 0.2356656 | G42: =G41/G8 -> 0.24413154 | H42: =H41/H8 -> 0.2522144 | I42: =I41/I8 -> 0.25993962 | ... M42: =M41/M8 -> 0.28770015 | N42: =AVERAGE(B42:M42) -> 0.24495504

Sheet 2029
B1: 47119 | C1: 47150 | D1: 47178 | E1: 47209 | F1: 47239 | G1: 47270 | H1: 47300 | I1: 47331 | J1: 47362 | K1: 47392 | L1: 47423 | M1: 47453 | N1: TOTAL
A2: Usuários | B2: =ROUNDDOWN(Dados!$B$1+('2028'!M2-('2028'!M2*Dados!$B$3)),0) -> 251 | C2: =ROUNDDOWN(Dados!$B$1+(B2-(B2*Dados!$B$3)),0) -> 255 | D2: =ROUNDDOWN(Dados!$B$1+(C2-(C2*Dados!$B$3)),0) -> 259 | E2: =ROUNDDOWN(Dados!$B$1+(D2-(D2*Dados!$B$3)),0) -> 263 | F2: =ROUNDDOWN(Dados!$B$1+(E2-(E2*Dados!$B$3)),0) -> 267 | G2: =ROUNDDOWN(Dados!$B$1+(F2-(F2*Dados!$B$3)),0) -> 271 | H2: =ROUNDDOWN(Dados!$B$1+(G2-(G2*Dados!$B$3)),0) -> 275 | I2: =ROUNDDOWN(Dados!$B$1+(H2-(H2*Dados!$B$3)),0) -> 279 | J2: =ROUNDDOWN(Dados!$B$1+(I2-(I2*Dados!$B$3)),0) -> 283 | ... M2: =ROUNDDOWN(Dados!$B$1+(L2-(L2*Dados!$B$3)),0) -> 295 | N2: =M2 -> 295
A4: Receita Total | B4: =ROUND(B5+B6,2) -> 209785.8 | C4: =ROUND(C5+C6,2) -> 213129 | D4: =ROUND(D5+D6,2) -> 216472.2 | E4: =ROUND(E5+E6,2) -> 219815.4 | F4: =ROUND(F5+F6,2) -> 223158.6 | G4: =ROUND(G5+G6,2) -> 226501.8 | H4: =ROUND(H5+H6,2) -> 229845 | I4: =ROUND(I5+I6,2) -> 233188.2 | ... M4: =ROUND(M5+M6,2) -> 246561 | N4: =ROUND(SUM(B4:M4),2) -> 2738080.8
A5: Receita Fixa - Mensalidade | B5: =ROUND(B2*Dados!$B$5,0) -> 149847 | C5: =ROUND(C2*Dados!$B$5,0) -> 152235 | D5: =ROUND(D2*Dados!$B$5,0) -> 154623 | E5: =ROUND(E2*Dados!$B$5,0) -> 157011 | F5: =ROUND(F2*Dados!$B$5,0) -> 159399 | G5: =ROUND(G2*Dados!$B$5,0) -> 161787 | H5: =ROUND(H2*Dados!$B$5,0) -> 164175 | I5: =ROUND(I2*Dados!$B$5,0) -> 166563 | ... M5: =ROUND(M2*Dados!$B$5,0) -> 176115 | N5: =ROUND(SUM(B5:M5),2) -> 1955772
A6: Receita Variável - Comissão sobre Vendas Recuperadas | B6: =IF(Dados!$B$9>0,Dados!$B$9*B2,ROUND(B2*(Dados!$B$11*Dados!$B$7),2)) -> 59938.8 | C6: =IF(Dados!$B$9>0,Dados!$B$9*C2,ROUND(C2*(Dados!$B$11*Dados!$B$7),2)) -> 60894 | D6: =IF(Dados!$B$9>0,Dados!$B$9*D2,ROUND(D2*(Dados!$B$11*Dados!$B$7),2)) -> 61849.2 | E6: =IF(Dados!$B$9>0,Dados!$B$9*E2,ROUND(E2*(Dados!$B$11*Dados!$B$7),2)) -> 62804.4 | F6: =IF(Dados!$B$9>0,Dados!$B$9*F2,ROUND(F2*(Dados!$B$11*Dados!$B$7),2)) -> 63759.6 | G6: =IF(Dados!$B$9>0,Dados!$B$9*G2,ROUND(G2*(Dados!$B$11*Dados!$B$7),2)) -> 64714.8 | H6: =IF(Dados!$B$9>0,Dados!$B$9*H2,ROUND(H2*(Dados!$B$11*Dados!$B$7),2)) -> 65670 | I6: =IF(Dados!$B$9>0,Dados!$B$9*I2,ROUND(I2*(Dados!$B$11*Dados!$B$7),2)) -> 66625.2 | ... M6: =IF(Dados!$B$9>0,Dados!$B$9*M2,ROUND(M2*(Dados!$B$11*Dados!$B$7),2)) -> 70446 | N6: =ROUND(SUM(B6:M6),2) -> 782308.8
A7: Impostos | B7: =B4*Dados!$E$2 -> 33565.728 | C7: =C4*Dados!$E$2 -> 34100.64 | D7: =D4*Dados!$E$2 -> 34635.552 | E7: =E4*Dados!$E$2 -> 35170.464 | F7: =F4*Dados!$E$2 -> 35705.376 | G7: =G4*Dados!$E$2 -> 36240.288 | H7: =H4*Dados!$E$2 -> 36775.2 | I7: =I4*Dados!$E$2 -> 37310.112 | ... M7: =M4*Dados!$E$2 -> 39449.76 | N7: =ROUND(SUM(B7:M7),2) -> 438092.93
A8: Receita Líquida | B8: =B4-B7 -> 176220.07 | C8: =C4-C7 -> 179028.36 | D8: =D4-D7 -> 181836.65 | E8: =E4-E7 -> 184644.94 | F8: =F4-F7 -> 187453.22 | G8: =G4-G7 -> 190261.51 | H8: =H4-H7 -> 193069.8 | I8: =I4-I7 -> 195878.09 | ... M8: =M4-M7 -> 207111.24 | N8: =ROUND(SUM(B8:M8),2) -> 2299987.9
A9: Receita Bruta | B9: =ROUND(B8-B14-B15-B16-B17-B18,2) -> 105977.72 | C9: =ROUND(C8-C14-C15-C16-C17-C18,2) -> 107666.61 | D9: =ROUND(D8-D14-D15-D16-D17-D18,2) -> 109355.5 | E9: =ROUND(E8-E14-E15-E16-E17-E18,2) -> 111044.39 | F9: =ROUND(F8-F14-F15-F16-F17-F18,2) -> 112733.27 | G9: =ROUND(G8-G14-G15-G16-G17-G18,2) -> 114422.16 | H9: =ROUND(H8-H14-H15-H16-H17-H18,2) -> 116111.05 | I9: =ROUND(I8-I14-I15-I16-I17-I18,2) -> 117799.94 | ... M9: =ROUND(M8-M14-M15-M16-M17-M18,2) -> 124555.49 | N9: =ROUND(SUM(B9:M9),2) -> 1383199.3
A10: Margem Bruta % | B10: =IFERROR(ROUND(B9/B4,2),0) -> 0.51 | C10: =IFERROR(ROUND(C9/C4,2),0) -> 0.51 | D10: =IFERROR(ROUND(D9/D4,2),0) -> 0.51 | E10: =IFERROR(ROUND(E9/E4,2),0) -> 0.51 | F10: =IFERROR(ROUND(F9/F4,2),0) -> 0.51 | G10: =IFERROR(ROUND(G9/G4,2),0) -> 0.51 | H10: =IFERROR(ROUND(H9/H4,2),0) -> 0.51 | I10: =IFERROR(ROUND(I9/I4,2),0) -> 0.51 | ... N10: =IFERROR(ROUND(N9/N4,2),0) -> 0.51
A12: Despesa Total | B12: =ROUND(SUM(B13,B19),2) -> 131635.35 | C12: =ROUND(SUM(C13,C19),2) -> 132754.75 | D12: =ROUND(SUM(D13,D19),2) -> 133874.15 | E12: =ROUND(SUM(E13,E19),2) -> 134993.55 | F12: =ROUND(SUM(F13,F19),2) -> 136112.95 | G12: =ROUND(SUM(G13,G19),2) -> 137232.35 | H12: =ROUND(SUM(H13,H19),2) -> 138351.75 | I12: =ROUND(SUM(I13,I19),2) -> 139471.15 | ... M12: =ROUND(SUM(M13,M19),2) -> 143948.75 | N12: =ROUND(SUM(B12:M12),2) -> 1653504.6
A13: Despesas Variáveis | B13: =B14+B15+B16+B17+B18 -> 70242.35 | C13: =C14+C15+C16+C17+C18 -> 71361.75 | D13: =D14+D15+D16+D17+D18 -> 72481.15 | E13: =E14+E15+E16+E17+E18 -> 73600.55 | F13: =F14+F15+F16+F17+F18 -> 74719.95 | G13: =G14+G15+G16+G17+G18 -> 75839.35 | H13: =H14+H15+H16+H17+H18 -> 76958.75 | I13: =I14+I15+I16+I17+I18 -> 78078.15 | ... M13: =M14+M15+M16+M17+M18 -> 82555.75 | N13: =ROUND(SUM(B13:M13),2) -> 916788.6
A14: Taxas de Checkout e Plataformas | B14: =B5*Dados!$E$1 -> 7492.35 | C14: =C5*Dados!$E$1 -> 7611.75 | D14: =D5*Dados!$E$1 -> 7731.15 | E14: =E5*Dados!$E$1 -> 7850.55 | F14: =F5*Dados!$E$1 -> 7969.95 | G14: =G5*Dados!$E$1 -> 8089.35 | H14: =H5*Dados!$E$1 -> 8208.75 | I14: =I5*Dados!$E$1 -> 8328.15 | ... M14: =M5*Dados!$E$1 -> 8805.75 | N14: =ROUND(SUM(B14:M14),2) -> 97788.6
A15: Servidor | B15: =10*B2 -> 2510 | C15: =10*C2 -> 2550 | D15: =10*D2 -> 2590 | E15: =10*E2 -> 2630 | F15: =10*F2 -> 2670 | G15: =10*G2 -> 2710 | H15: =10*H2 -> 2750 | I15: =10*I2 -> 2790 | ... M15: =10*M2 -> 2950 | N15: =ROUND(SUM(B15:M15),2) -> 32760
A16: API Oficial Whatsapp | B16: =200*B2 -> 50200 | C16: =200*C2 -> 51000 | D16: =200*D2 -> 51800 | E16: =200*E2 -> 52600 | F16: =200*F2 -> 53400 | G16: =200*G2 -> 54200 | H16: =200*H2 -> 55000 | I16: =200*I2 -> 55800 | ... M16: =200*M2 -> 59000 | N16: =ROUND(SUM(B16:M16),2) -> 655200
A17: Tokens GPT | B17: =10*B2 -> 2510 | C17: =10*C2 -> 2550 | D17: =10*D2 -> 2590 | E17: =10*E2 -> 2630 | F17: =10*F2 -> 2670 | G17: =10*G2 -> 2710 | H17: =10*H2 -> 2750 | I17: =10*I2 -> 2790 | ... M17: =10*M2 -> 2950 | N17: =ROUND(SUM(B17:M17),2) -> 32760
A18: Telefone | B18: =30*B2 -> 7530 | C18: =30*C2 -> 7650 | D18: =30*D2 -> 7770 | E18: =30*E2 -> 7890 | F18: =30*F2 -> 8010 | G18: =30*G2 -> 8130 | H18: =30*H2 -> 8250 | I18: =30*I2 -> 8370 | ... M18: =30*M2 -> 8850 | N18: =ROUND(SUM(B18:M18),2) -> 98280
A19: Despesas Fixas | B19: =SUM(B20:B40) -> 61393 | C19: =SUM(C20:C40) -> 61393 | D19: =SUM(D20:D40) -> 61393 | E19: =SUM(E20:E40) -> 61393 | F19: =SUM(F20:F40) -> 61393 | G19: =SUM(G20:G40) -> 61393 | H19: =SUM(H20:H40) -> 61393 | I19: =SUM(I20:I40) -> 61393 | ... M19: =SUM(M20:M40) -> 61393 | N19: =ROUND(SUM(B19:M19),2) -> 736716
A20: Pro Labore - CEO | B20: 11100 | C20: 11100 | D20: 11100 | E20: 11100 | F20: 11100 | G20: 11100 | H20: 11100 | I20: 11100 | J20: 11100 | K20: 11100 | L20: 11100 | M20: 11100 | N20: =ROUND(SUM(B20:M20),2) -> 133200
A21: Pro Labore - Operacional | B21: 7215 | C21: 7215 | D21: 7215 | E21: 7215 | F21: 7215 | G21: 7215 | H21: 7215 | I21: 7215 | J21: 7215 | K21: 7215 | L21: 7215 | M21: 7215 | N21: =ROUND(SUM(B21:M21),2) -> 86580
A22: Pro Labore - Operacional | B22: 7215 | C22: 7215 | D22: 7215 | E22: 7215 | F22: 7215 | G22: 7215 | H22: 7215 | I22: 7215 | J22: 7215 | K22: 7215 | L22: 7215 | M22: 7215 | N22: =ROUND(SUM(B22:M22),2) -> 86580
A23: Pro Labore - Operacional | B23: 7215 | C23: 7215 | D23: 7215 | E23: 7215 | F23: 7215 | G23: 7215 | H23: 7215 | I23: 7215 | J23: 7215 | K23: 7215 | L23: 7215 | M23: 7215 | N23: =ROUND(SUM(B23:M23),2) -> 86580
A24: Auxiliar de Serviços Gerais | B24: =Dados!$E$4*Dados!$F$4 -> 1000 | C24: =Dados!$E$4*Dados!$F$4 -> 1000 | D24: =Dados!$E$4*Dados!$F$4 -> 1000 | E24: =Dados!$E$4*Dados!$F$4 -> 1000 | F24: =Dados!$E$4*Dados!$F$4 -> 1000 | G24: =Dados!$E$4*Dados!$F$4 -> 1000 | H24: =Dados!$E$4*Dados!$F$4 -> 1000 | I24: =Dados!$E$4*Dados!$F$4 -> 1000 | ... M24: =Dados!$E$4*Dados!$F$4 -> 1000 | N24: =ROUND(SUM(B24:M24),2) -> 12000
A25: Desenvolvedor | B25: =Dados!$E$5*Dados!$F$5 -> 2000 | C25: =Dados!$E$5*Dados!$F$5 -> 2000 | D25: =Dados!$E$5*Dados!$F$5 -> 2000 | E25: =Dados!$E$5*Dados!$F$5 -> 2000 | F25: =Dados!$E$5*Dados!$F$5 -> 2000 | G25: =Dados!$E$5*Dados!$F$5 -> 2000 | H25: =Dados!$E$5*Dados!$F$5 -> 2000 | I25: =Dados!$E$5*Dados!$F$5 -> 2000 | ... M25: =Dados!$E$5*Dados!$F$5 -> 2000 | N25: =ROUND(SUM(B25:M25),2) -> 24000
A26: Gestor de Tráfego | B26: =Dados!$E$6*Dados!$F$6 -> 2000 | C26: =Dados!$E$6*Dados!$F$6 -> 2000 | D26: =Dados!$E$6*Dados!$F$6 -> 2000 | E26: =Dados!$E$6*Dados!$F$6 -> 2000 | F26: =Dados!$E$6*Dados!$F$6 -> 2000 | G26: =Dados!$E$6*Dados!$F$6 -> 2000 | H26: =Dados!$E$6*Dados!$F$6 -> 2000 | I26: =Dados!$E$6*Dados!$F$6 -> 2000 | ... M26: =Dados!$E$6*Dados!$F$6 -> 2000 | N26: =ROUND(SUM(B26:M26),2) -> 24000
A27: Designer / Editor de Vídeo / Tecnologia | B27: =Dados!$E$7*Dados!$F$7 -> 2000 | C27: =Dados!$E$7*Dados!$F$7 -> 2000 | D27: =Dados!$E$7*Dados!$F$7 -> 2000 | E27: =Dados!$E$7*Dados!$F$7 -> 2000 | F27: =Dados!$E$7*Dados!$F$7 -> 2000 | G27: =Dados!$E$7*Dados!$F$7 -> 2000 | H27: =Dados!$E$7*Dados!$F$7 -> 2000 | I27: =Dados!$E$7*Dados!$F$7 -> 2000 | ... M27: =Dados!$E$7*Dados!$F$7 -> 2000 | N27: =ROUND(SUM(B27:M27),2) -> 24000
A28: Customer Success | B28: =Dados!$E$8*Dados!$F$8 -> 3000 | C28: =Dados!$E$8*Dados!$F$8 -> 3000 | D28: =Dados!$E$8*Dados!$F$8 -> 3000 | E28: =Dados!$E$8*Dados!$F$8 -> 3000 | F28: =Dados!$E$8*Dados!$F$8 -> 3000 | G28: =Dados!$E$8*Dados!$F$8 -> 3000 | H28: =Dados!$E$8*Dados!$F$8 -> 3000 | I28: =Dados!$E$8*Dados!$F$8 -> 3000 | ... M28: =Dados!$E$8*Dados!$F$8 -> 3000 | N28: =ROUND(SUM(B28:M28),2) -> 36000
A29: Vendedores | B29: =Dados!$E$9*Dados!$F$9 -> 0 | C29: =Dados!$E$9*Dados!$F$9 -> 0 | D29: =Dados!$E$9*Dados!$F$9 -> 0 | E29: =Dados!$E$9*Dados!$F$9 -> 0 | F29: =Dados!$E$9*Dados!$F$9 -> 0 | G29: =Dados!$E$9*Dados!$F$9 -> 0 | H29: =Dados!$E$9*Dados!$F$9 -> 0 | I29: =Dados!$E$9*Dados!$F$9 -> 0 | ... M29: =Dados!$E$9*Dados!$F$9 -> 0 | N29: =ROUND(SUM(B29:M29),2) -> 0
A30: CRM | B30: =Dados!$E$10*Dados!$F$10 -> 300 | C30: =Dados!$E$10*Dados!$F$10 -> 300 | D30: =Dados!$E$10*Dados!$F$10 -> 300 | E30: =Dados!$E$10*Dados!$F$10 -> 300 | F30: =Dados!$E$10*Dados!$F$10 -> 300 | G30: =Dados!$E$10*Dados!$F$10 -> 300 | H30: =Dados!$E$10*Dados!$F$10 -> 300 | I30: =Dados!$E$10*Dados!$F$10 -> 300 | ... M30: =Dados!$E$10*Dados!$F$10 -> 300 | N30: =ROUND(SUM(B30:M30),2) -> 3600
A31: Internet / Telefonia | B31: 500 | C31: 500 | D31: 500 | E31: 500 | F31: 500 | G31: 500 | H31: 500 | I31: 500 | J31: 500 | K31: 500 | L31: 500 | M31: 500 | N31: =ROUND(SUM(B31:M31),2) -> 6000
A32: Contabilidade | B32: 1000 | C32: 1000 | D32: 1000 | E32: 1000 | F32: 1000 | G32: 1000 | H32: 1000 | I32: 1000 | J32: 1000 | K32: 1000 | L32: 1000 | M32: 1000 | N32: =ROUND(SUM(B32:M32),2) -> 12000
A33: Condominio | B33: 500 | C33: 500 | D33: 500 | E33: 500 | F33: 500 | G33: 500 | H33: 500 | I33: 500 | J33: 500 | K33: 500 | L33: 500 | M33: 500 | N33: =ROUND(SUM(B33:M33),2) -> 6000
A34: Energia Elétrica | B34: 500 | C34: 500 | D34: 500 | E34: 500 | F34: 500 | G34: 500 | H34: 500 | I34: 500 | J34: 500 | K34: 500 | L34: 500 | M34: 500 | N34: =ROUND(SUM(B34:M34),2) -> 6000
A35: Aluguel | B35: 2000 | C35: 2000 | D35: 2000 | E35: 2000 | F35: 2000 | G35: 2000 | H35: 2000 | I35: 2000 | J35: 2000 | K35: 2000 | L35: 2000 | M35: 2000 | N35: =ROUND(SUM(B35:M35),2) -> 24000
A36: Google Workspace | B36: =Dados!$E$11*Dados!$F$11 -> 600 | C36: =Dados!$E$11*Dados!$F$11 -> 600 | D36: =Dados!$E$11*Dados!$F$11 -> 600 | E36: =Dados!$E$11*Dados!$F$11 -> 600 | F36: =Dados!$E$11*Dados!$F$11 -> 600 | G36: =Dados!$E$11*Dados!$F$11 -> 600 | H36: =Dados!$E$11*Dados!$F$11 -> 600 | I36: =Dados!$E$11*Dados!$F$11 -> 600 | ... M36: =Dados!$E$11*Dados!$F$11 -> 600 | N36: =ROUND(SUM(B36:M36),2) -> 7200
A37: Notion | B37: =Dados!$E$12*Dados!$F$12 -> 1200 | C37: =Dados!$E$12*Dados!$F$12 -> 1200 | D37: =Dados!$E$12*Dados!$F$12 -> 1200 | E37: =Dados!$E$12*Dados!$F$12 -> 1200 | F37: =Dados!$E$12*Dados!$F$12 -> 1200 | G37: =Dados!$E$12*Dados!$F$12 -> 1200 | H37: =Dados!$E$12*Dados!$F$12 -> 1200 | I37: =Dados!$E$12*Dados!$F$12 -> 1200 | ... M37: =Dados!$E$12*Dados!$F$12 -> 1200 | N37: =ROUND(SUM(B37:M37),2) -> 14400
A38: Treinamentos Udemy | B38: 48 | C38: 48 | D38: 48 | E38: 48 | F38: 48 | G38: 48 | H38: 48 | I38: 48 | J38: 48 | K38: 48 | L38: 48 | M38: 48 | N38: =ROUND(SUM(B38:M38),2) -> 576
A39: Jurídico | B39: 2000 | C39: 2000 | D39: 2000 | E39: 2000 | F39: 2000 | G39: 2000 | H39: 2000 | I39: 2000 | J39: 2000 | K39: 2000 | L39: 2000 | M39: 2000 | N39: =ROUND(SUM(B39:M39),2) -> 24000
A40: Anúncios Online | B40: =Dados!$E$3 -> 10000 | C40: =Dados!$E$3 -> 10000 | D40: =Dados!$E$3 -> 10000 | E40: =Dados!$E$3 -> 10000 | F40: =Dados!$E$3 -> 10000 | G40: =Dados!$E$3 -> 10000 | H40: =Dados!$E$3 -> 10000 | I40: =Dados!$E$3 -> 10000 | ... M40: =Dados!$E$3 -> 10000 | N40: =ROUND(SUM(B40:M40),2) -> 120000
A41: EBITDA = Lucro Líquido | B41: =ROUND(B9-B19,2) -> 44584.72 | C41: =ROUND(C9-C19,2) -> 46273.61 | D41: =ROUND(D9-D19,2) -> 47962.5 | E41: =ROUND(E9-E19,2) -> 49651.39 | F41: =ROUND(F9-F19,2) -> 51340.27 | G41: =ROUND(G9-G19,2) -> 53029.16 | H41: =ROUND(H9-H19,2) -> 54718.05 | I41: =ROUND(I9-I19,2) -> 56406.94 | ... M41: =ROUND(M9-M19,2) -> 63162.49 | N41: =ROUND(SUM(B41:M41),2) -> 646483.27
A42: Margem Líquida % | B42: =B41/B8 -> 0.25300591 | C42: =C41/C8 -> 0.25847084 | D42: =D41/D8 -> 0.26376696 | E42: =E41/E8 -> 0.26890199 | F42: =F41/F8 -> 0.2738831 | G42: =G41/G8 -> 0.27871722 | H42: =H41/H8 -> 0.28341071 | I42: =I41/I8 -> 0.28796963 | ... M42: =M41/M8 -> 0.30496891 | N42: =AVERAGE(B42:M42) -> 0.28025795

Sheet 2030
B1: 47484 | C1: 47515 | D1: 47543 | E1: 47574 | F1: 47604 | G1: 47635 | H1: 47665 | I1: 47696 | J1: 47727 | K1: 47757 | L1: 47788 | M1: 47818 | N1: TOTAL
A2: Usuários | B2: =ROUNDDOWN(Dados!$B$1+('2029'!M2-('2029'!M2*Dados!$B$3)),0) -> 299 | C2: =ROUNDDOWN(Dados!$B$1+(B2-(B2*Dados!$B$3)),0) -> 303 | D2: =ROUNDDOWN(Dados!$B$1+(C2-(C2*Dados!$B$3)),0) -> 306 | E2: =ROUNDDOWN(Dados!$B$1+(D2-(D2*Dados!$B$3)),0) -> 309 | F2: =ROUNDDOWN(Dados!$B$1+(E2-(E2*Dados!$B$3)),0) -> 312 | G2: =ROUNDDOWN(Dados!$B$1+(F2-(F2*Dados!$B$3)),0) -> 315 | H2: =ROUNDDOWN(Dados!$B$1+(G2-(G2*Dados!$B$3)),0) -> 318 | I2: =ROUNDDOWN(Dados!$B$1+(H2-(H2*Dados!$B$3)),0) -> 321 | J2: =ROUNDDOWN(Dados!$B$1+(I2-(I2*Dados!$B$3)),0) -> 324 | ... M2: =ROUNDDOWN(Dados!$B$1+(L2-(L2*Dados!$B$3)),0) -> 333 | N2: =M2 -> 333
A4: Receita Total | B4: =ROUND(B5+B6,2) -> 249904.2 | C4: =ROUND(C5+C6,2) -> 253247.4 | D4: =ROUND(D5+D6,2) -> 255754.8 | E4: =ROUND(E5+E6,2) -> 258262.2 | F4: =ROUND(F5+F6,2) -> 260769.6 | G4: =ROUND(G5+G6,2) -> 263277 | H4: =ROUND(H5+H6,2) -> 265784.4 | I4: =ROUND(I5+I6,2) -> 268291.8 | ... M4: =ROUND(M5+M6,2) -> 278321.4 | N4: =ROUND(SUM(B4:M4),2) -> 3173532.6
A5: Receita Fixa - Mensalidade | B5: =ROUND(B2*Dados!$B$5,0) -> 178503 | C5: =ROUND(C2*Dados!$B$5,0) -> 180891 | D5: =ROUND(D2*Dados!$B$5,0) -> 182682 | E5: =ROUND(E2*Dados!$B$5,0) -> 184473 | F5: =ROUND(F2*Dados!$B$5,0) -> 186264 | G5: =ROUND(G2*Dados!$B$5,0) -> 188055 | H5: =ROUND(H2*Dados!$B$5,0) -> 189846 | I5: =ROUND(I2*Dados!$B$5,0) -> 191637 | ... M5: =ROUND(M2*Dados!$B$5,0) -> 198801 | N5: =ROUND(SUM(B5:M5),2) -> 2266809
A6: Receita Variável - Comissão sobre Vendas Recuperadas | B6: =IF(Dados!$B$9>0,Dados!$B$9*B2,ROUND(B2*(Dados!$B$11*Dados!$B$7),2)) -> 71401.2 | C6: =IF(Dados!$B$9>0,Dados!$B$9*C2,ROUND(C2*(Dados!$B$11*Dados!$B$7),2)) -> 72356.4 | D6: =IF(Dados!$B$9>0,Dados!$B$9*D2,ROUND(D2*(Dados!$B$11*Dados!$B$7),2)) -> 73072.8 | E6: =IF(Dados!$B$9>0,Dados!$B$9*E2,ROUND(E2*(Dados!$B$11*Dados!$B$7),2)) -> 73789.2 | F6: =IF(Dados!$B$9>0,Dados!$B$9*F2,ROUND(F2*(Dados!$B$11*Dados!$B$7),2)) -> 74505.6 | G6: =IF(Dados!$B$9>0,Dados!$B$9*G2,ROUND(G2*(Dados!$B$11*Dados!$B$7),2)) -> 75222 | H6: =IF(Dados!$B$9>0,Dados!$B$9*H2,ROUND(H2*(Dados!$B$11*Dados!$B$7),2)) -> 75938.4 | I6: =IF(Dados!$B$9>0,Dados!$B$9*I2,ROUND(I2*(Dados!$B$11*Dados!$B$7),2)) -> 76654.8 | ... M6: =IF(Dados!$B$9>0,Dados!$B$9*M2,ROUND(M2*(Dados!$B$11*Dados!$B$7),2)) -> 79520.4 | N6: =ROUND(SUM(B6:M6),2) -> 906723.6
A7: Impostos | B7: =B4*Dados!$E$2 -> 39984.672 | C7: =C4*Dados!$E$2 -> 40519.584 | D7: =D4*Dados!$E$2 -> 40920.768 | E7: =E4*Dados!$E$2 -> 41321.952 | F7: =F4*Dados!$E$2 -> 41723.136 | G7: =G4*Dados!$E$2 -> 42124.32 | H7: =H4*Dados!$E$2 -> 42525.504 | I7: =I4*Dados!$E$2 -> 42926.688 | ... M7: =M4*Dados!$E$2 -> 44531.424 | N7: =ROUND(SUM(B7:M7),2) -> 507765.22
A8: Receita Líquida | B8: =B4-B7 -> 209919.53 | C8: =C4-C7 -> 212727.82 | D8: =D4-D7 -> 214834.03 | E8: =E4-E7 -> 216940.25 | F8: =F4-F7 -> 219046.46 | G8: =G4-G7 -> 221152.68 | H8: =H4-H7 -> 223258.9 | I8: =I4-I7 -> 225365.11 | ... M8: =M4-M7 -> 233789.98 | N8: =ROUND(SUM(B8:M8),2) -> 2665767.4
A9: Receita Bruta | B9: =ROUND(B8-B14-B15-B16-B17-B18,2) -> 126244.38 | C9: =ROUND(C8-C14-C15-C16-C17-C18,2) -> 127933.27 | D9: =ROUND(D8-D14-D15-D16-D17-D18,2) -> 129199.93 | E9: =ROUND(E8-E14-E15-E16-E17-E18,2) -> 130466.6 | F9: =ROUND(F8-F14-F15-F16-F17-F18,2) -> 131733.26 | G9: =ROUND(G8-G14-G15-G16-G17-G18,2) -> 132999.93 | H9: =ROUND(H8-H14-H15-H16-H17-H18,2) -> 134266.6 | I9: =ROUND(I8-I14-I15-I16-I17-I18,2) -> 135533.26 | ... M9: =ROUND(M8-M14-M15-M16-M17-M18,2) -> 140599.93 | N9: =ROUND(SUM(B9:M9),2) -> 1603176.9
A10: Margem Bruta % | B10: =IFERROR(ROUND(B9/B4,2),0) -> 0.51 | C10: =IFERROR(ROUND(C9/C4,2),0) -> 0.51 | D10: =IFERROR(ROUND(D9/D4,2),0) -> 0.51 | E10: =IFERROR(ROUND(E9/E4,2),0) -> 0.51 | F10: =IFERROR(ROUND(F9/F4,2),0) -> 0.51 | G10: =IFERROR(ROUND(G9/G4,2),0) -> 0.51 | H10: =IFERROR(ROUND(H9/H4,2),0) -> 0.51 | I10: =IFERROR(ROUND(I9/I4,2),0) -> 0.51 | ... N10: =IFERROR(ROUND(N9/N4,2),0) -> 0.51
A12: Despesa Total | B12: =ROUND(SUM(B13,B19),2) -> 152283.15 | C12: =ROUND(SUM(C13,C19),2) -> 153402.55 | D12: =ROUND(SUM(D13,D19),2) -> 154242.1 | E12: =ROUND(SUM(E13,E19),2) -> 155081.65 | F12: =ROUND(SUM(F13,F19),2) -> 155921.2 | G12: =ROUND(SUM(G13,G19),2) -> 156760.75 | H12: =ROUND(SUM(H13,H19),2) -> 157600.3 | I12: =ROUND(SUM(I13,I19),2) -> 158439.85 | ... M12: =ROUND(SUM(M13,M19),2) -> 161798.05 | N12: =ROUND(SUM(B12:M12),2) -> 1885886.4
A13: Despesas Variáveis | B13: =B14+B15+B16+B17+B18 -> 83675.15 | C13: =C14+C15+C16+C17+C18 -> 84794.55 | D13: =D14+D15+D16+D17+D18 -> 85634.1 | E13: =E14+E15+E16+E17+E18 -> 86473.65 | F13: =F14+F15+F16+F17+F18 -> 87313.2 | G13: =G14+G15+G16+G17+G18 -> 88152.75 | H13: =H14+H15+H16+H17+H18 -> 88992.3 | I13: =I14+I15+I16+I17+I18 -> 89831.85 | ... M13: =M14+M15+M16+M17+M18 -> 93190.05 | N13: =ROUND(SUM(B13:M13),2) -> 1062590.4
A14: Taxas de Checkout e Plataformas | B14: =B5*Dados!$E$1 -> 8925.15 | C14: =C5*Dados!$E$1 -> 9044.55 | D14: =D5*Dados!$E$1 -> 9134.1 | E14: =E5*Dados!$E$1 -> 9223.65 | F14: =F5*Dados!$E$1 -> 9313.2 | G14: =G5*Dados!$E$1 -> 9402.75 | H14: =H5*Dados!$E$1 -> 9492.3 | I14: =I5*Dados!$E$1 -> 9581.85 | ... M14: =M5*Dados!$E$1 -> 9940.05 | N14: =ROUND(SUM(B14:M14),2) -> 113340.45
A15: Servidor | B15: =10*B2 -> 2990 | C15: =10*C2 -> 3030 | D15: =10*D2 -> 3060 | E15: =10*E2 -> 3090 | F15: =10*F2 -> 3120 | G15: =10*G2 -> 3150 | H15: =10*H2 -> 3180 | I15: =10*I2 -> 3210 | ... M15: =10*M2 -> 3330 | N15: =ROUND(SUM(B15:M15),2) -> 37970
A16: API Oficial Whatsapp | B16: =200*B2 -> 59800 | C16: =200*C2 -> 60600 | D16: =200*D2 -> 61200 | E16: =200*E2 -> 61800 | F16: =200*F2 -> 62400 | G16: =200*G2 -> 63000 | H16: =200*H2 -> 63600 | I16: =200*I2 -> 64200 | ... M16: =200*M2 -> 66600 | N16: =ROUND(SUM(B16:M16),2) -> 759400
A17: Tokens GPT | B17: =10*B2 -> 2990 | C17: =10*C2 -> 3030 | D17: =10*D2 -> 3060 | E17: =10*E2 -> 3090 | F17: =10*F2 -> 3120 | G17: =10*G2 -> 3150 | H17: =10*H2 -> 3180 | I17: =10*I2 -> 3210 | ... M17: =10*M2 -> 3330 | N17: =ROUND(SUM(B17:M17),2) -> 37970
A18: Telefone | B18: =30*B2 -> 8970 | C18: =30*C2 -> 9090 | D18: =30*D2 -> 9180 | E18: =30*E2 -> 9270 | F18: =30*F2 -> 9360 | G18: =30*G2 -> 9450 | H18: =30*H2 -> 9540 | I18: =30*I2 -> 9630 | ... M18: =30*M2 -> 9990 | N18: =ROUND(SUM(B18:M18),2) -> 113910
A19: Despesas Fixas | B19: =SUM(B20:B40) -> 68608 | C19: =SUM(C20:C40) -> 68608 | D19: =SUM(D20:D40) -> 68608 | E19: =SUM(E20:E40) -> 68608 | F19: =SUM(F20:F40) -> 68608 | G19: =SUM(G20:G40) -> 68608 | H19: =SUM(H20:H40) -> 68608 | I19: =SUM(I20:I40) -> 68608 | ... M19: =SUM(M20:M40) -> 68608 | N19: =ROUND(SUM(B19:M19),2) -> 823296
A20: Pro Labore - CEO | B20: 13320 | C20: 13320 | D20: 13320 | E20: 13320 | F20: 13320 | G20: 13320 | H20: 13320 | I20: 13320 | J20: 13320 | K20: 13320 | L20: 13320 | M20: 13320 | N20: =ROUND(SUM(B20:M20),2) -> 159840
A21: Pro Labore - Operacional | B21: 8880 | C21: 8880 | D21: 8880 | E21: 8880 | F21: 8880 | G21: 8880 | H21: 8880 | I21: 8880 | J21: 8880 | K21: 8880 | L21: 8880 | M21: 8880 | N21: =ROUND(SUM(B21:M21),2) -> 106560
A22: Pro Labore - Operacional | B22: 8880 | C22: 8880 | D22: 8880 | E22: 8880 | F22: 8880 | G22: 8880 | H22: 8880 | I22: 8880 | J22: 8880 | K22: 8880 | L22: 8880 | M22: 8880 | N22: =ROUND(SUM(B22:M22),2) -> 106560
A23: Pro Labore - Operacional | B23: 8880 | C23: 8880 | D23: 8880 | E23: 8880 | F23: 8880 | G23: 8880 | H23: 8880 | I23: 8880 | J23: 8880 | K23: 8880 | L23: 8880 | M23: 8880 | N23: =ROUND(SUM(B23:M23),2) -> 106560
A24: Auxiliar de Serviços Gerais | B24: =Dados!$E$4*Dados!$F$4 -> 1000 | C24: =Dados!$E$4*Dados!$F$4 -> 1000 | D24: =Dados!$E$4*Dados!$F$4 -> 1000 | E24: =Dados!$E$4*Dados!$F$4 -> 1000 | F24: =Dados!$E$4*Dados!$F$4 -> 1000 | G24: =Dados!$E$4*Dados!$F$4 -> 1000 | H24: =Dados!$E$4*Dados!$F$4 -> 1000 | I24: =Dados!$E$4*Dados!$F$4 -> 1000 | ... M24: =Dados!$E$4*Dados!$F$4 -> 1000 | N24: =ROUND(SUM(B24:M24),2) -> 12000
A25: Desenvolvedor | B25: =Dados!$E$5*Dados!$F$5 -> 2000 | C25: =Dados!$E$5*Dados!$F$5 -> 2000 | D25: =Dados!$E$5*Dados!$F$5 -> 2000 | E25: =Dados!$E$5*Dados!$F$5 -> 2000 | F25: =Dados!$E$5*Dados!$F$5 -> 2000 | G25: =Dados!$E$5*Dados!$F$5 -> 2000 | H25: =Dados!$E$5*Dados!$F$5 -> 2000 | I25: =Dados!$E$5*Dados!$F$5 -> 2000 | ... M25: =Dados!$E$5*Dados!$F$5 -> 2000 | N25: =ROUND(SUM(B25:M25),2) -> 24000
A26: Gestor de Tráfego | B26: =Dados!$E$6*Dados!$F$6 -> 2000 | C26: =Dados!$E$6*Dados!$F$6 -> 2000 | D26: =Dados!$E$6*Dados!$F$6 -> 2000 | E26: =Dados!$E$6*Dados!$F$6 -> 2000 | F26: =Dados!$E$6*Dados!$F$6 -> 2000 | G26: =Dados!$E$6*Dados!$F$6 -> 2000 | H26: =Dados!$E$6*Dados!$F$6 -> 2000 | I26: =Dados!$E$6*Dados!$F$6 -> 2000 | ... M26: =Dados!$E$6*Dados!$F$6 -> 2000 | N26: =ROUND(SUM(B26:M26),2) -> 24000
A27: Designer / Editor de Vídeo / Tecnologia | B27: =Dados!$E$7*Dados!$F$7 -> 2000 | C27: =Dados!$E$7*Dados!$F$7 -> 2000 | D27: =Dados!$E$7*Dados!$F$7 -> 2000 | E27: =Dados!$E$7*Dados!$F$7 -> 2000 | F27: =Dados!$E$7*Dados!$F$7 -> 2000 | G27: =Dados!$E$7*Dados!$F$7 -> 2000 | H27: =Dados!$E$7*Dados!$F$7 -> 2000 | I27: =Dados!$E$7*Dados!$F$7 -> 2000 | ... M27: =Dados!$E$7*Dados!$F$7 -> 2000 | N27: =ROUND(SUM(B27:M27),2) -> 24000
A28: Customer Success | B28: =Dados!$E$8*Dados!$F$8 -> 3000 | C28: =Dados!$E$8*Dados!$F$8 -> 3000 | D28: =Dados!$E$8*Dados!$F$8 -> 3000 | E28: =Dados!$E$8*Dados!$F$8 -> 3000 | F28: =Dados!$E$8*Dados!$F$8 -> 3000 | G28: =Dados!$E$8*Dados!$F$8 -> 3000 | H28: =Dados!$E$8*Dados!$F$8 -> 3000 | I28: =Dados!$E$8*Dados!$F$8 -> 3000 | ... M28: =Dados!$E$8*Dados!$F$8 -> 3000 | N28: =ROUND(SUM(B28:M28),2) -> 36000
A29: Vendedores | B29: =Dados!$E$9*Dados!$F$9 -> 0 | C29: =Dados!$E$9*Dados!$F$9 -> 0 | D29: =Dados!$E$9*Dados!$F$9 -> 0 | E29: =Dados!$E$9*Dados!$F$9 -> 0 | F29: =Dados!$E$9*Dados!$F$9 -> 0 | G29: =Dados!$E$9*Dados!$F$9 -> 0 | H29: =Dados!$E$9*Dados!$F$9 -> 0 | I29: =Dados!$E$9*Dados!$F$9 -> 0 | ... M29: =Dados!$E$9*Dados!$F$9 -> 0 | N29: =ROUND(SUM(B29:M29),2) -> 0
A30: CRM | B30: =Dados!$E$10*Dados!$F$10 -> 300 | C30: =Dados!$E$10*Dados!$F$10 -> 300 | D30: =Dados!$E$10*Dados!$F$10 -> 300 | E30: =Dados!$E$10*Dados!$F$10 -> 300 | F30: =Dados!$E$10*Dados!$F$10 -> 300 | G30: =Dados!$E$10*Dados!$F$10 -> 300 | H30: =Dados!$E$10*Dados!$F$10 -> 300 | I30: =Dados!$E$10*Dados!$F$10 -> 300 | ... M30: =Dados!$E$10*Dados!$F$10 -> 300 | N30: =ROUND(SUM(B30:M30),2) -> 3600
A31: Internet / Telefonia | B31: 500 | C31: 500 | D31: 500 | E31: 500 | F31: 500 | G31: 500 | H31: 500 | I31: 500 | J31: 500 | K31: 500 | L31: 500 | M31: 500 | N31: =ROUND(SUM(B31:M31),2) -> 6000
A32: Contabilidade | B32: 1000 | C32: 1000 | D32: 1000 | E32: 1000 | F32: 1000 | G32: 1000 | H32: 1000 | I32: 1000 | J32: 1000 | K32: 1000 | L32: 1000 | M32: 1000 | N32: =ROUND(SUM(B32:M32),2) -> 12000
A33: Condominio | B33: 500 | C33: 500 | D33: 500 | E33: 500 | F33: 500 | G33: 500 | H33: 500 | I33: 500 | J33: 500 | K33: 500 | L33: 500 | M33: 500 | N33: =ROUND(SUM(B33:M33),2) -> 6000
A34: Energia Elétrica | B34: 500 | C34: 500 | D34: 500 | E34: 500 | F34: 500 | G34: 500 | H34: 500 | I34: 500 | J34: 500 | K34: 500 | L34: 500 | M34: 500 | N34: =ROUND(SUM(B34:M34),2) -> 6000
A35: Aluguel | B35: 2000 | C35: 2000 | D35: 2000 | E35: 2000 | F35: 2000 | G35: 2000 | H35: 2000 | I35: 2000 | J35: 2000 | K35: 2000 | L35: 2000 | M35: 2000 | N35: =ROUND(SUM(B35:M35),2) -> 24000
A36: Google Workspace | B36: =Dados!$E$11*Dados!$F$11 -> 600 | C36: =Dados!$E$11*Dados!$F$11 -> 600 | D36: =Dados!$E$11*Dados!$F$11 -> 600 | E36: =Dados!$E$11*Dados!$F$11 -> 600 | F36: =Dados!$E$11*Dados!$F$11 -> 600 | G36: =Dados!$E$11*Dados!$F$11 -> 600 | H36: =Dados!$E$11*Dados!$F$11 -> 600 | I36: =Dados!$E$11*Dados!$F$11 -> 600 | ... M36: =Dados!$E$11*Dados!$F$11 -> 600 | N36: =ROUND(SUM(B36:M36),2) -> 7200
A37: Notion | B37: =Dados!$E$12*Dados!$F$12 -> 1200 | C37: =Dados!$E$12*Dados!$F$12 -> 1200 | D37: =Dados!$E$12*Dados!$F$12 -> 1200 | E37: =Dados!$E$12*Dados!$F$12 -> 1200 | F37: =Dados!$E$12*Dados!$F$12 -> 1200 | G37: =Dados!$E$12*Dados!$F$12 -> 1200 | H37: =Dados!$E$12*Dados!$F$12 -> 1200 | I37: =Dados!$E$12*Dados!$F$12 -> 1200 | ... M37: =Dados!$E$12*Dados!$F$12 -> 1200 | N37: =ROUND(SUM(B37:M37),2) -> 14400
A38: Treinamentos Udemy | B38: 48 | C38: 48 | D38: 48 | E38: 48 | F38: 48 | G38: 48 | H38: 48 | I38: 48 | J38: 48 | K38: 48 | L38: 48 | M38: 48 | N38: =ROUND(SUM(B38:M38),2) -> 576
A39: Jurídico | B39: 2000 | C39: 2000 | D39: 2000 | E39: 2000 | F39: 2000 | G39: 2000 | H39: 2000 | I39: 2000 | J39: 2000 | K39: 2000 | L39: 2000 | M39: 2000 | N39: =ROUND(SUM(B39:M39),2) -> 24000
A40: Anúncios Online | B40: =Dados!$E$3 -> 10000 | C40: =Dados!$E$3 -> 10000 | D40: =Dados!$E$3 -> 10000 | E40: =Dados!$E$3 -> 10000 | F40: =Dados!$E$3 -> 10000 | G40: =Dados!$E$3 -> 10000 | H40: =Dados!$E$3 -> 10000 | I40: =Dados!$E$3 -> 10000 | ... M40: =Dados!$E$3 -> 10000 | N40: =ROUND(SUM(B40:M40),2) -> 120000
A41: EBITDA = Lucro Líquido | B41: =ROUND(B9-B19,2) -> 57636.38 | C41: =ROUND(C9-C19,2) -> 59325.27 | D41: =ROUND(D9-D19,2) -> 60591.93 | E41: =ROUND(E9-E19,2) -> 61858.6 | F41: =ROUND(F9-F19,2) -> 63125.26 | G41: =ROUND(G9-G19,2) -> 64391.93 | H41: =ROUND(H9-H19,2) -> 65658.6 | I41: =ROUND(I9-I19,2) -> 66925.26 | ... M41: =ROUND(M9-M19,2) -> 71991.93 | N41: =ROUND(SUM(B41:M41),2) -> 779880.94
A42: Margem Líquida % | B42: =B41/B8 -> 0.27456417 | C42: =C41/C8 -> 0.27887876 | D42: =D41/D8 -> 0.28204065 | E42: =E41/E8 -> 0.28514119 | F42: =F41/F8 -> 0.28818205 | G42: =G41/G8 -> 0.29116504 | H42: =H41/H8 -> 0.29409175 | I42: =I41/I8 -> 0.29696371 | ... M42: =M41/M8 -> 0.3079342 | N42: =AVERAGE(B42:M42) -> 0.29221333

Sheet Total
B1: 2026 | C1: 2027 | D1: 2028 | E1: 2029 | F1: 2030 | G1: TOTAL
A2: Usuários | B2: ='2026'!N2 -> 103 | C2: ='2027'!N2 -> 182 | D2: ='2028'!N2 -> 246 | E2: ='2029'!N2 -> 295 | F2: ='2030'!N2 -> 333 | G2: =SUM(B2:F2) -> 1159
A4: Receita Total | B4: ='2026'!N4 -> 579209.4 | C4: ='2027'!N4 -> 1476858.6 | D4: ='2028'!N4 -> 2186452.8 | E4: ='2029'!N4 -> 2738080.8 | F4: ='2030'!N4 -> 3173532.6 | G4: =SUM(B4:F4) -> 10154134
A5: Receita Fixa - Mensalidade | B5: ='2026'!N5 -> 413721 | C5: ='2027'!N5 -> 1054899 | D5: ='2028'!N5 -> 1561752 | E5: ='2029'!N5 -> 1955772 | F5: ='2030'!N5 -> 2266809 | G5: =SUM(B5:F5) -> 7252953
A6: Receita Variável - Comissão sobre Vendas Recuperadas | B6: ='2026'!N6 -> 165488.4 | C6: ='2027'!N6 -> 421959.6 | D6: ='2028'!N6 -> 624700.8 | E6: ='2029'!N6 -> 782308.8 | F6: ='2030'!N6 -> 906723.6 | G6: =SUM(B6:F6) -> 2901181.2
A7: Impostos | B7: ='2026'!N7 -> 92673.5 | C7: ='2027'!N7 -> 236297.38 | D7: ='2028'!N7 -> 349832.45 | E7: ='2029'!N7 -> 438092.93 | F7: ='2030'!N7 -> 507765.22 | G7: =SUM(B7:F7) -> 1624661.5
A8: Receita Líquida | B8: ='2026'!N8 -> 486535.9 | C8: ='2027'!N8 -> 1240561.2 | D8: ='2028'!N8 -> 1836620.4 | E8: ='2029'!N8 -> 2299987.9 | F8: ='2030'!N8 -> 2665767.4 | G8: =SUM(B8:F8) -> 8529472.7
A9: Receita Bruta | B9: ='2026'!N9 -> 292599.85 | C9: ='2027'!N9 -> 746066.27 | D9: ='2028'!N9 -> 1104532.7 | E9: ='2029'!N9 -> 1383199.3 | F9: ='2030'!N9 -> 1603176.9 | G9: =SUM(B9:F9) -> 5129575.1
A10: Margem Bruta % | B10: ='2026'!N10 -> 0.51 | C10: ='2027'!N10 -> 0.51 | D10: ='2028'!N10 -> 0.51 | E10: ='2029'!N10 -> 0.51 | F10: ='2030'!N10 -> 0.51 | G10: =AVERAGE(B10:F10) -> 0.51
B11: ='2026'!N11 -> 0 | C11: ='2027'!N11 -> 0 | D11: ='2028'!N11 -> 0 | E11: ='2029'!N11 -> 0 | F11: ='2030'!N11 -> 0 | G11: =F11 -> 0
A12: Despesa Total | B12: ='2026'!N12 -> 671264.05 | C12: ='2027'!N12 -> 1058402.9 | D12: ='2028'!N12 -> 1382223.6 | E12: ='2029'!N12 -> 1653504.6 | F12: ='2030'!N12 -> 1885886.4 | G12: =SUM(B12:F12) -> 6651281.7
A13: Despesas Variáveis | B13: ='2026'!N13 -> 193936.05 | C13: ='2027'!N13 -> 494494.95 | D13: ='2028'!N13 -> 732087.6 | E13: ='2029'!N13 -> 916788.6 | F13: ='2030'!N13 -> 1062590.4 | G13: =SUM(B13:F13) -> 3399897.7
A14: Taxas de Checkout e Plataformas | B14: ='2026'!N14 -> 20686.05 | C14: ='2027'!N14 -> 52744.95 | D14: ='2028'!N14 -> 78087.6 | E14: ='2029'!N14 -> 97788.6 | F14: ='2030'!N14 -> 113340.45 | G14: =SUM(B14:F14) -> 362647.65
A15: Servidor | B15: ='2026'!N15 -> 6930 | C15: ='2027'!N15 -> 17670 | D15: ='2028'!N15 -> 26160 | E15: ='2029'!N15 -> 32760 | F15: ='2030'!N15 -> 37970 | G15: =SUM(B15:F15) -> 121490
A16: API Oficial Whatsapp | B16: ='2026'!N16 -> 138600 | C16: ='2027'!N16 -> 353400 | D16: ='2028'!N16 -> 523200 | E16: ='2029'!N16 -> 655200 | F16: ='2030'!N16 -> 759400 | G16: =SUM(B16:F16) -> 2429800
A17: Tokens GPT | B17: ='2026'!N17 -> 6930 | C17: ='2027'!N17 -> 17670 | D17: ='2028'!N17 -> 26160 | E17: ='2029'!N17 -> 32760 | F17: ='2030'!N17 -> 37970 | G17: =SUM(B17:F17) -> 121490
A18: Telefone | B18: ='2026'!N18 -> 20790 | C18: ='2027'!N18 -> 53010 | D18: ='2028'!N18 -> 78480 | E18: ='2029'!N18 -> 98280 | F18: ='2030'!N18 -> 113910 | G18: =SUM(B18:F18) -> 364470
A19: Despesas Fixas | B19: ='2026'!N19 -> 477328 | C19: ='2027'!N19 -> 563908 | D19: ='2028'!N19 -> 650136 | E19: ='2029'!N19 -> 736716 | F19: ='2030'!N19 -> 823296 | G19: =SUM(B19:F19) -> 3251384
A20: Pro Labore - CEO | B20: ='2026'!N20 -> 53280 | C20: ='2027'!N20 -> 79920 | D20: ='2028'!N20 -> 106560 | E20: ='2029'!N20 -> 133200 | F20: ='2030'!N20 -> 159840 | G20: =SUM(B20:F20) -> 532800
A21: Pro Labore - Operacional | B21: ='2026'!N21 -> 26640 | C21: ='2027'!N21 -> 46620 | D21: ='2028'!N21 -> 66600 | E21: ='2029'!N21 -> 86580 | F21: ='2030'!N21 -> 106560 | G21: =SUM(B21:F21) -> 333000
A22: Pro Labore - Operacional | B22: ='2026'!N22 -> 26640 | C22: ='2027'!N22 -> 46620 | D22: ='2028'!N22 -> 66600 | E22: ='2029'!N22 -> 86580 | F22: ='2030'!N22 -> 106560 | G22: =SUM(B22:F22) -> 333000
A23: Pro Labore - Operacional | B23: ='2026'!N23 -> 26640 | C23: ='2027'!N23 -> 46620 | D23: ='2028'!N23 -> 66600 | E23: ='2029'!N23 -> 86580 | F23: ='2030'!N23 -> 106560 | G23: =SUM(B23:F23) -> 333000
... A41: EBITDA = Lucro Líquido | B41: ='2026'!N41 -> -184728.15 | C41: ='2027'!N41 -> 182158.27 | D41: ='2028'!N41 -> 454396.74 | E41: ='2029'!N41 -> 646483.27 | F41: ='2030'!N41 -> 779880.94 | G41: =SUM(B41:F41) -> 1878191.1
A42: Margem Líquida % | B42: ='2026'!N42 -> -0.95469448 | C42: ='2027'!N42 -> 0.13541345 | D42: ='2028'!N42 -> 0.24495504 | E42: ='2029'!N42 -> 0.28025795 | F42: ='2030'!N42 -> 0.29221333 | G42: =AVERAGE(B42:F42) -> -0.00037094189

Sheet Dados
A1: Meta de Usuários Mensal | B1: 10 | D1: Taxa de Checkout | E1: 0.05
D2: Impostos | E2: 0.16
A3: Churn Mensal | B3: 0.02 | D3: Anúncios Online | E3: 10000
D4: Auxiliar de Serviços Gerais | E4: 1 | F4: 1000
A5: Mensalidade | B5: 597 | D5: Desenvolvedor | E5: 1 | F5: 2000
D6: Gestor de Tráfego | E6: 1 | F6: 2000
A7: Comissão - Suposição Média por Cliente em (%) | B7: 0.2 | D7: Designer / Editor de Vídeo / Tecnologia | E7: 1 | F7: 2000
D8: Customer Success | E8: 1 | F8: 3000
A9: Comissão - Suposição Média por Cliente em (R$) | D9: Vendedores | E9: 0 | F9: 3750
D10: CRM | E10: =E9+E8+2 -> 3 | F10: 100
A11: Garantia Minima Mensal | B11: =((B5*3)*2)/3 -> 1194 | D11: Google Workspace | E11: =4+E5+E8+E9 -> 6 | F11: 100
D12: Notion | E12: =E9+E8+E7+E6+E5+4 -> 8 | F12: 150

Sheet Simulador Tributario
A1: Mês | B1: Faturamento | C1: Pró-labore | D1: Salários CLT | E1: Custo total CLT (c/ encargos) | F1: RBT12 | G1: Folha12 | H1: Fator R | I1: Anexo Simples | J1: Alíquota Simples | K1: Imposto Simples | L1: Receita Líq Simples | M1: Alíquota Lucro Presumido | N1: Imposto Lucro Presumido | O1: Receita Líq Presumido | P1: Alíquota Lucro Real | Q1: Imposto Lucro Real | R1: Receita Líq Lucro Real | S1: Regime Mais Econômico
A2: Jan '26 | B2: 9695.28 | C2: 11000 | D2: 0 | E2: =D2*1.288 -> 0 | F2: =IF(ROW()-1<13,SUM($B$2:B2),SUM(INDEX($B:$B,ROW()-11):B2)) -> 9695.28 | G2: =IF(ROW()-1<13,SUM($C$2:C2)+SUM($D$2:D2),SUM(INDEX($C:$C,ROW()-11):C2)+SUM(INDEX($D:$D,ROW()-11):D2)) -> 11000 | H2: =IF(F2=0,0,G2/F2) -> 1.1345727 | I2: =IF(H2>=0.28,"III","V") -> III | J2: =IF(I2="III",IF(F2<=180000,0.06,IF(F2<=360000,(F2*0.112-9360)/F2,IF(F2<=720000,(F2*0.135-17640)/F2,IF(F2<=1800000,(F2*0.16-35640)/F2,IF(F2<=3600000,(F2*0.21-125640)/F2,IF(F2<=4800000,(F2*0.33-648000)/F2,0)))))),IF(F2<=180000,0.155,IF(F2<=360000,(F2*0.18-4500)/F2,IF(F2<=720000,(F2*0.195-9900)/F2,IF(F2<=1800000,(F2*0.205-17100)/F2,IF(F2<=3600000,(F2*0.23-62100)/F2,IF(F2<=4800000,(F2*0.305-540000)/F2,0))))))) -> 0.06 | K2: =B2*J2 -> 581.7168 | L2: =B2-K2 -> 9113.5632 | M2: =N2/B2 -> 0.1133 | N2: =(B2*0.32*0.15)+(MAX(0,(B2*0.32)-20000)*0.1)+(B2*0.32*0.09)+(B2*0.0365) -> 1098.4752 | O2: =B2-N2 -> 8596.8048 | P2: =Q2/B2 -> 0.0925 | Q2: =MAX(0,(B2-C2-E2))*0.15+MAX(0,(B2-C2-E2-20000))*0.1+MAX(0,(B2-C2-E2))*0.09+(B2*0.0925) -> 896.8134 | R2: =B2-Q2 -> 8798.4666 | S2: =IF(L2>=MAX(L2,O2,R2),"SIMPLES",IF(O2>=MAX(L2,O2,R2),"LUCRO PRESUMIDO","LUCRO REAL")) -> SIMPLES
A3: Feb '26 | B3: 18421.032 | C3: 11000 | D3: 0 | E3: =D3*1.288 -> 0 | F3: =IF(ROW()-1<13,SUM($B$2:B3),SUM(INDEX($B:$B,ROW()-11):B3)) -> 28116.312 | G3: =IF(ROW()-1<13,SUM($C$2:C3)+SUM($D$2:D3),SUM(INDEX($C:$C,ROW()-11):C3)+SUM(INDEX($D:$D,ROW()-11):D3)) -> 22000 | H3: =IF(F3=0,0,G3/F3) -> 0.78246393 | I3: =IF(H3>=0.28,"III","V") -> III | J3: =IF(I3="III",IF(F3<=180000,0.06,IF(F3<=360000,(F3*0.112-9360)/F3,IF(F3<=720000,(F3*0.135-17640)/F3,IF(F3<=1800000,(F3*0.16-35640)/F3,IF(F3<=3600000,(F3*0.21-125640)/F3,IF(F3<=4800000,(F3*0.33-648000)/F3,0)))))),IF(F3<=180000,0.155,IF(F3<=360000,(F3*0.18-4500)/F3,IF(F3<=720000,(F3*0.195-9900)/F3,IF(F3<=1800000,(F3*0.205-17100)/F3,IF(F3<=3600000,(F3*0.23-62100)/F3,IF(F3<=4800000,(F3*0.305-540000)/F3,0))))))) -> 0.06 | K3: =B3*J3 -> 1105.2619 | L3: =B3-K3 -> 17315.77 | M3: =N3/B3 -> 0.1133 | N3: =(B3*0.32*0.15)+(MAX(0,(B3*0.32)-20000)*0.1)+(B3*0.32*0.09)+(B3*0.0365) -> 2087.1029 | O3: =B3-N3 -> 16333.929 | P3: =Q3/B3 -> 0.18918555 | Q3: =MAX(0,(B3-C3-E3))*0.15+MAX(0,(B3-C3-E3-20000))*0.1+MAX(0,(B3-C3-E3))*0.09+(B3*0.0925) -> 3484.9931 | R3: =B3-Q3 -> 14936.039 | S3: =IF(L3>=MAX(L3,O3,R3),"SIMPLES",IF(O3>=MAX(L3,O3,R3),"LUCRO PRESUMIDO","LUCRO REAL")) -> SIMPLES
A4: Mar '26 | B4: 27146.784 | C4: 11000 | D4: 0 | E4: =D4*1.288 -> 0 | F4: =IF(ROW()-1<13,SUM($B$2:B4),SUM(INDEX($B:$B,ROW()-11):B4)) -> 55263.096 | G4: =IF(ROW()-1<13,SUM($C$2:C4)+SUM($D$2:D4),SUM(INDEX($C:$C,ROW()-11):C4)+SUM(INDEX($D:$D,ROW()-11):D4)) -> 33000 | H4: =IF(F4=0,0,G4/F4) -> 0.59714353 | I4: =IF(H4>=0.28,"III","V") -> III | J4: =IF(I4="III",IF(F4<=180000,0.06,IF(F4<=360000,(F4*0.112-9360)/F4,IF(F4<=720000,(F4*0.135-17640)/F4,IF(F4<=1800000,(F4*0.16-35640)/F4,IF(F4<=3600000,(F4*0.21-125640)/F4,IF(F4<=4800000,(F4*0.33-648000)/F4,0)))))),IF(F4<=180000,0.155,IF(F4<=360000,(F4*0.18-4500)/F4,IF(F4<=720000,(F4*0.195-9900)/F4,IF(F4<=1800000,(F4*0.205-17100)/F4,IF(F4<=3600000,(F4*0.23-62100)/F4,IF(F4<=4800000,(F4*0.305-540000)/F4,0))))))) -> 0.06 | K4: =B4*J4 -> 1628.807 | L4: =B4-K4 -> 25517.977 | M4: =N4/B4 -> 0.1133 | N4: =(B4*0.32*0.15)+(MAX(0,(B4*0.32)-20000)*0.1)+(B4*0.32*0.09)+(B4*0.0365) -> 3075.7306 | O4: =B4-N4 -> 24071.053 | P4: =Q4/B4 -> 0.23525091 | Q4: =MAX(0,(B4-C4-E4))*0.15+MAX(0,(B4-C4-E4-20000))*0.1+MAX(0,(B4-C4-E4))*0.09+(B4*0.0925) -> 6386.3057 | R4: =B4-Q4 -> 20760.478 | S4: =IF(L4>=MAX(L4,O4,R4),"SIMPLES",IF(O4>=MAX(L4,O4,R4),"LUCRO PRESUMIDO","LUCRO REAL")) -> SIMPLES
A5: Apr '26 | B5: 35872.536 | C5: 11000 | D5: 0 | E5: =D5*1.288 -> 0 | F5: =IF(ROW()-1<13,SUM($B$2:B5),SUM(INDEX($B:$B,ROW()-11):B5)) -> 91135.632 | G5: =IF(ROW()-1<13,SUM($C$2:C5)+SUM($D$2:D5),SUM(INDEX($C:$C,ROW()-11):C5)+SUM(INDEX($D:$D,ROW()-11):D5)) -> 44000 | H5: =IF(F5=0,0,G5/F5) -> 0.48279689 | I5: =IF(H5>=0.28,"III","V") -> III | J5: =IF(I5="III",IF(F5<=180000,0.06,IF(F5<=360000,(F5*0.112-9360)/F5,IF(F5<=720000,(F5*0.135-17640)/F5,IF(F5<=1800000,(F5*0.16-35640)/F5,IF(F5<=3600000,(F5*0.21-125640)/F5,IF(F5<=4800000,(F5*0.33-648000)/F5,0)))))),IF(F5<=180000,0.155,IF(F5<=360000,(F5*0.18-4500)/F5,IF(F5<=720000,(F5*0.195-9900)/F5,IF(F5<=1800000,(F5*0.205-17100)/F5,IF(F5<=3600000,(F5*0.23-62100)/F5,IF(F5<=4800000,(F5*0.305-540000)/F5,0))))))) -> 0.06 | K5: =B5*J5 -> 2152.3522 | L5: =B5-K5 -> 33720.184 | M5: =N5/B5 -> 0.1133 | N5: =(B5*0.32*0.15)+(MAX(0,(B5*0.32)-20000)*0.1)+(B5*0.32*0.09)+(B5*0.0365) -> 4064.3583 | O5: =B5-N5 -> 31808.178 | P5: =Q5/B5 -> 0.27248901 | Q5: =MAX(0,(B5-C5-E5))*0.15+MAX(0,(B5-C5-E5-20000))*0.1+MAX(0,(B5-C5-E5))*0.09+(B5*0.0925) -> 9774.8718 | R5: =B5-Q5 -> 26097.664 | S5: =IF(L5>=MAX(L5,O5,R5),"SIMPLES",IF(O5>=MAX(L5,O5,R5),"LUCRO PRESUMIDO","LUCRO REAL")) -> SIMPLES
A6: May '26 | B6: 44598.288 | C6: 11000 | D6: 0 | E6: =D6*1.288 -> 0 | F6: =IF(ROW()-1<13,SUM($B$2:B6),SUM(INDEX($B:$B,ROW()-11):B6)) -> 135733.92 | G6: =IF(ROW()-1<13,SUM($C$2:C6)+SUM($D$2:D6),SUM(INDEX($C:$C,ROW()-11):C6)+SUM(INDEX($D:$D,ROW()-11):D6)) -> 55000 | H6: =IF(F6=0,0,G6/F6) -> 0.40520454 | I6: =IF(H6>=0.28,"III","V") -> III | J6: =IF(I6="III",IF(F6<=180000,0.06,IF(F6<=360000,(F6*0.112-9360)/F6,IF(F6<=720000,(F6*0.135-17640)/F6,IF(F6<=1800000,(F6*0.16-35640)/F6,IF(F6<=3600000,(F6*0.21-125640)/F6,IF(F6<=4800000,(F6*0.33-648000)/F6,0)))))),IF(F6<=180000,0.155,IF(F6<=360000,(F6*0.18-4500)/F6,IF(F6<=720000,(F6*0.195-9900)/F6,IF(F6<=1800000,(F6*0.205-17100)/F6,IF(F6<=3600000,(F6*0.23-62100)/F6,IF(F6<=4800000,(F6*0.305-540000)/F6,0))))))) -> 0.06 | K6: =B6*J6 -> 2675.8973 | L6: =B6-K6 -> 41922.391 | M6: =N6/B6 -> 0.1133 | N6: =(B6*0.32*0.15)+(MAX(0,(B6*0.32)-20000)*0.1)+(B6*0.32*0.09)+(B6*0.0365) -> 5052.986 | O6: =B6-N6 -> 39545.302 | P6: =Q6/B6 -> 0.30379551 | Q6: =MAX(0,(B6-C6-E6))*0.15+MAX(0,(B6-C6-E6-20000))*0.1+MAX(0,(B6-C6-E6))*0.09+(B6*0.0925) -> 13548.76 | R6: =B6-Q6 -> 31049.528 | S6: =IF(L6>=MAX(L6,O6,R6),"SIMPLES",IF(O6>=MAX(L6,O6,R6),"LUCRO PRESUMIDO","LUCRO REAL")) -> SIMPLES
A7: Jun '26 | B7: 53324.04 | C7: 11000 | D7: 0 | E7: =D7*1.288 -> 0 | F7: =IF(ROW()-1<13,SUM($B$2:B7),SUM(INDEX($B:$B,ROW()-11):B7)) -> 189057.96 | G7: =IF(ROW()-1<13,SUM($C$2:C7)+SUM($D$2:D7),SUM(INDEX($C:$C,ROW()-11):C7)+SUM(INDEX($D:$D,ROW()-11):D7)) -> 66000 | H7: =IF(F7=0,0,G7/F7) -> 0.34909929 | I7: =IF(H7>=0.28,"III","V") -> III | J7: =IF(I7="III",IF(F7<=180000,0.06,IF(F7<=360000,(F7*0.112-9360)/F7,IF(F7<=720000,(F7*0.135-17640)/F7,IF(F7<=1800000,(F7*0.16-35640)/F7,IF(F7<=3600000,(F7*0.21-125640)/F7,IF(F7<=4800000,(F7*0.33-648000)/F7,0)))))),IF(F7<=180000,0.155,IF(F7<=360000,(F7*0.18-4500)/F7,IF(F7<=720000,(F7*0.195-9900)/F7,IF(F7<=1800000,(F7*0.205-17100)/F7,IF(F7<=3600000,(F7*0.23-62100)/F7,IF(F7<=4800000,(F7*0.305-540000)/F7,0))))))) -> 0.062491373 | K7: =B7*J7 -> 3332.2925 | L7: =B7-K7 -> 49991.748 | M7: =N7/B7 -> 0.1133 | N7: =(B7*0.32*0.15)+(MAX(0,(B7*0.32)-20000)*0.1)+(B7*0.32*0.09)+(B7*0.0365) -> 6041.6137 | O7: =B7-N7 -> 47282.426 | P7: =Q7/B7 -> 0.32485624 | Q7: =MAX(0,(B7-C7-E7))*0.15+MAX(0,(B7-C7-E7-20000))*0.1+MAX(0,(B7-C7-E7))*0.09+(B7*0.0925) -> 17322.647 | R7: =B7-Q7 -> 36001.393 | S7: =IF(L7>=MAX(L7,O7,R7),"SIMPLES",IF(O7>=MAX(L7,O7,R7),"LUCRO PRESUMIDO","LUCRO REAL")) -> SIMPLES
A8: Jul '26 | B8: 61080.264 | C8: 11000 | D8: 0 | E8: =D8*1.288 -> 0 | F8: =IF(ROW()-1<13,SUM($B$2:B8),SUM(INDEX($B:$B,ROW()-11):B8)) -> 250138.22 | G8: =IF(ROW()-1<13,SUM($C$2:C8)+SUM($D$2:D8),SUM(INDEX($C:$C,ROW()-11):C8)+SUM(INDEX($D:$D,ROW()-11):D8)) -> 77000 | H8: =IF(F8=0,0,G8/F8) -> 0.3078298 | I8: =IF(H8>=0.28,"III","V") -> III | J8: =IF(I8="III",IF(F8<=180000,0.06,IF(F8<=360000,(F8*0.112-9360)/F8,IF(F8<=720000,(F8*0.135-17640)/F8,IF(F8<=1800000,(F8*0.16-35640)/F8,IF(F8<=3600000,(F8*0.21-125640)/F8,IF(F8<=4800000,(F8*0.33-648000)/F8,0)))))),IF(F8<=180000,0.155,IF(F8<=360000,(F8*0.18-4500)/F8,IF(F8<=720000,(F8*0.195-9900)/F8,IF(F8<=1800000,(F8*0.205-17100)/F8,IF(F8<=3600000,(F8*0.23-62100)/F8,IF(F8<=4800000,(F8*0.305-540000)/F8,0))))))) -> 0.074580689 | K8: =B8*J8 -> 4555.4082 | L8: =B8-K8 -> 56524.856 | M8: =N8/B8 -> 0.1133 | N8: =(B8*0.32*0.15)+(MAX(0,(B8*0.32)-20000)*0.1)+(B8*0.32*0.09)+(B8*0.0365) -> 6920.3939 | O8: =B8-N8 -> 54159.87 | P8: =Q8/B8 -> 0.33852529 | Q8: =MAX(0,(B8-C8-E8))*0.15+MAX(0,(B8-C8-E8-20000))*0.1+MAX(0,(B8-C8-E8))*0.09+(B8*0.0925) -> 20677.214 | R8: =B8-Q8 -> 40403.05 | S8: =IF(L8>=MAX(L8,O8,R8),"SIMPLES",IF(O8>=MAX(L8,O8,R8),"LUCRO PRESUMIDO","LUCRO REAL")) -> SIMPLES
A9: Aug '26 | B9: 68836.488 | C9: 11000 | D9: 0 | E9: =D9*1.288 -> 0 | F9: =IF(ROW()-1<13,SUM($B$2:B9),SUM(INDEX($B:$B,ROW()-11):B9)) -> 318974.71 | G9: =IF(ROW()-1<13,SUM($C$2:C9)+SUM($D$2:D9),SUM(INDEX($C:$C,ROW()-11):C9)+SUM(INDEX($D:$D,ROW()-11):D9)) -> 88000 | H9: =IF(F9=0,0,G9/F9) -> 0.27588394 | I9: =IF(H9>=0.28,"III","V") -> V | J9: =IF(I9="III",IF(F9<=180000,0.06,IF(F9<=360000,(F9*0.112-9360)/F9,IF(F9<=720000,(F9*0.135-17640)/F9,IF(F9<=1800000,(F9*0.16-35640)/F9,IF(F9<=3600000,(F9*0.21-125640)/F9,IF(F9<=4800000,(F9*0.33-648000)/F9,0)))))),IF(F9<=180000,0.155,IF(F9<=360000,(F9*0.18-4500)/F9,IF(F9<=720000,(F9*0.195-9900)/F9,IF(F9<=1800000,(F9*0.205-17100)/F9,IF(F9<=3600000,(F9*0.23-62100)/F9,IF(F9<=4800000,(F9*0.305-540000)/F9,0))))))) -> 0.1658923 | K9: =B9*J9 -> 11419.443 | L9: =B9-K9 -> 57417.045 | M9: =N9/B9 -> 0.11624564 | N9: =(B9*0.32*0.15)+(MAX(0,(B9*0.32)-20000)*0.1)+(B9*0.32*0.09)+(B9*0.0365) -> 8001.9417 | O9: =B9-N9 -> 60834.546 | P9: =Q9/B9 -> 0.34911399 | Q9: =MAX(0,(B9-C9-E9))*0.15+MAX(0,(B9-C9-E9-20000))*0.1+MAX(0,(B9-C9-E9))*0.09+(B9*0.0925) -> 24031.781 | R9: =B9-Q9 -> 44804.707 | S9: =IF(L9>=MAX(L9,O9,R9),"SIMPLES",IF(O9>=MAX(L9,O9,R9),"LUCRO PRESUMIDO","LUCRO REAL")) -> LUCRO PRESUMIDO
A10: Sep '26 | B10: 76592.712 | C10: 11000 | D10: 0 | E10: =D10*1.288 -> 0 | F10: =IF(ROW()-1<13,SUM($B$2:B10),SUM(INDEX($B:$B,ROW()-11):B10)) -> 395567.42 | G10: =IF(ROW()-1<13,SUM($C$2:C10)+SUM($D$2:D10),SUM(INDEX($C:$C,ROW()-11):C10)+SUM(INDEX($D:$D,ROW()-11):D10)) -> 99000 | H10: =IF(F10=0,0,G10/F10) -> 0.25027339 | I10: =IF(H10>=0.28,"III","V") -> V | J10: =IF(I10="III",IF(F10<=180000,0.06,IF(F10<=360000,(F10*0.112-9360)/F10,IF(F10<=720000,(F10*0.135-17640)/F10,IF(F10<=1800000,(F10*0.16-35640)/F10,IF(F10<=3600000,(F10*0.21-125640)/F10,IF(F10<=4800000,(F10*0.33-648000)/F10,0)))))),IF(F10<=180000,0.155,IF(F10<=360000,(F10*0.18-4500)/F10,IF(F10<=720000,(F10*0.195-9900)/F10,IF(F10<=1800000,(F10*0.205-17100)/F10,IF(F10<=3600000,(F10*0.23-62100)/F10,IF(F10<=4800000,(F10*0.305-540000)/F10,0))))))) -> 0.16997266 | K10: =B10*J10 -> 13018.667 | L10: =B10-K10 -> 63574.045 | M10: =N10/B10 -> 0.11918786 | N10: =(B10*0.32*0.15)+(MAX(0,(B10*0.32)-20000)*0.1)+(B10*0.32*0.09)+(B10*0.0365) -> 9128.9211 | O10: =B10-N10 -> 67463.791 | P10: =Q10/B10 -> 0.35755814 | Q10: =MAX(0,(B10-C10-E10))*0.15+MAX(0,(B10-C10-E10-20000))*0.1+MAX(0,(B10-C10-E10))*0.09+(B10*0.0925) -> 27386.348 | R10: =B10-Q10 -> 49206.364 | S10: =IF(L10>=MAX(L10,O10,R10),"SIMPLES",IF(O10>=MAX(L10,O10,R10),"LUCRO PRESUMIDO","LUCRO REAL")) -> LUCRO PRESUMIDO
A11: Oct '26 | B11: 84348.936 | C11: 11000 | D11: 0 | E11: =D11*1.288 -> 0 | F11: =IF(ROW()-1<13,SUM($B$2:B11),SUM(INDEX($B:$B,ROW()-11):B11)) -> 479916.36 | G11: =IF(ROW()-1<13,SUM($C$2:C11)+SUM($D$2:D11),SUM(INDEX($C:$C,ROW()-11):C11)+SUM(INDEX($D:$D,ROW()-11):D11)) -> 110000 | H11: =IF(F11=0,0,G11/F11) -> 0.22920661 | I11: =IF(H11>=0.28,"III","V") -> V | J11: =IF(I11="III",IF(F11<=180000,0.06,IF(F11<=360000,(F11*0.112-9360)/F11,IF(F11<=720000,(F11*0.135-17640)/F11,IF(F11<=1800000,(F11*0.16-35640)/F11,IF(F11<=3600000,(F11*0.21-125640)/F11,IF(F11<=4800000,(F11*0.33-648000)/F11,0)))))),IF(F11<=180000,0.155,IF(F11<=360000,(F11*0.18-4500)/F11,IF(F11<=720000,(F11*0.195-9900)/F11,IF(F11<=1800000,(F11*0.205-17100)/F11,IF(F11<=3600000,(F11*0.23-62100)/F11,IF(F11<=4800000,(F11*0.305-540000)/F11,0))))))) -> 0.17437141 | K11: =B11*J11 -> 14708.043 | L11: =B11-K11 -> 69640.893 | M11: =N11/B11 -> 0.12158897 | N11: =(B11*0.32*0.15)+(MAX(0,(B11*0.32)-20000)*0.1)+(B11*0.32*0.09)+(B11*0.0365) -> 10255.9 | O11: =B11-N11 -> 74093.036 | P11: =Q11/B11 -> 0.36444935 | Q11: =MAX(0,(B11-C11-E11))*0.15+MAX(0,(B11-C11-E11-20000))*0.1+MAX(0,(B11-C11-E11))*0.09+(B11*0.0925) -> 30740.915 | R11: =B11-Q11 -> 53608.021 | S11: =IF(L11>=MAX(L11,O11,R11),"SIMPLES",IF(O11>=MAX(L11,O11,R11),"LUCRO PRESUMIDO","LUCRO REAL")) -> LUCRO PRESUMIDO
A12: Nov '26 | B12: 92105.16 | C12: 11000 | D12: 0 | E12: =D12*1.288 -> 0 | F12: =IF(ROW()-1<13,SUM($B$2:B12),SUM(INDEX($B:$B,ROW()-11):B12)) -> 572021.52 | G12: =IF(ROW()-1<13,SUM($C$2:C12)+SUM($D$2:D12),SUM(INDEX($C:$C,ROW()-11):C12)+SUM(INDEX($D:$D,ROW()-11):D12)) -> 121000 | H12: =IF(F12=0,0,G12/F12) -> 0.2115305 | I12: =IF(H12>=0.28,"III","V") -> V | J12: =IF(I12="III",IF(F12<=180000,0.06,IF(F12<=360000,(F12*0.112-9360)/F12,IF(F12<=720000,(F12*0.135-17640)/F12,IF(F12<=1800000,(F12*0.16-35640)/F12,IF(F12<=3600000,(F12*0.21-125640)/F12,IF(F12<=4800000,(F12*0.33-648000)/F12,0)))))),IF(F12<=180000,0.155,IF(F12<=360000,(F12*0.18-4500)/F12,IF(F12<=720000,(F12*0.195-9900)/F12,IF(F12<=1800000,(F12*0.205-17100)/F12,IF(F12<=3600000,(F12*0.23-62100)/F12,IF(F12<=4800000,(F12*0.305-540000)/F12,0))))))) -> 0.17769296 | K12: =B12*J12 -> 16366.438 | L12: =B12-K12 -> 75738.722 | M12: =N12/B12 -> 0.12358569 | N12: =(B12*0.32*0.15)+(MAX(0,(B12*0.32)-20000)*0.1)+(B12*0.32*0.09)+(B12*0.0365) -> 11382.88 | O12: =B12-N12 -> 80722.28 | P12: =Q12/B12 -> 0.37017993 | Q12: =MAX(0,(B12-C12-E12))*0.15+MAX(0,(B12-C12-E12-20000))*0.1+MAX(0,(B12-C12-E12))*0.09+(B12*0.0925) -> 34095.482 | R12: =B12-Q12 -> 58009.678 | S12: =IF(L12>=MAX(L12,O12,R12),"SIMPLES",IF(O12>=MAX(L12,O12,R12),"LUCRO PRESUMIDO","LUCRO REAL")) -> LUCRO PRESUMIDO
A13: Dec '26 | B13: 99861.384 | C13: 11000 | D13: 0 | E13: =D13*1.288 -> 0 | F13: =IF(ROW()-1<13,SUM($B$2:B13),SUM(INDEX($B:$B,ROW()-11):B13)) -> 671882.9 | G13: =IF(ROW()-1<13,SUM($C$2:C13)+SUM($D$2:D13),SUM(INDEX($C:$C,ROW()-11):C13)+SUM(INDEX($D:$D,ROW()-11):D13)) -> 132000 | H13: =IF(F13=0,0,G13/F13) -> 0.19646281 | I13: =IF(H13>=0.28,"III","V") -> V | J13: =IF(I13="III",IF(F13<=180000,0.06,IF(F13<=360000,(F13*0.112-9360)/F13,IF(F13<=720000,(F13*0.135-17640)/F13,IF(F13<=1800000,(F13*0.16-35640)/F13,IF(F13<=3600000,(F13*0.21-125640)/F13,IF(F13<=4800000,(F13*0.33-648000)/F13,0)))))),IF(F13<=180000,0.155,IF(F13<=360000,(F13*0.18-4500)/F13,IF(F13<=720000,(F13*0.195-9900)/F13,IF(F13<=1800000,(F13*0.205-17100)/F13,IF(F13<=3600000,(F13*0.23-62100)/F13,IF(F13<=4800000,(F13*0.305-540000)/F13,0))))))) -> 0.18026529 | K13: =B13*J13 -> 18001.541 | L13: =B13-K13 -> 81859.843 | M13: =N13/B13 -> 0.12527224 | N13: =(B13*0.32*0.15)+(MAX(0,(B13*0.32)-20000)*0.1)+(B13*0.32*0.09)+(B13*0.0365) -> 12509.859 | O13: =B13-N13 -> 87351.525 | P13: =Q13/B13 -> 0.37502032 | Q13: =MAX(0,(B13-C13-E13))*0.15+MAX(0,(B13-C13-E13-20000))*0.1+MAX(0,(B13-C13-E13))*0.09+(B13*0.0925) -> 37450.049 | R13: =B13-Q13 -> 62411.335 | S13: =IF(L13>=MAX(L13,O13,R13),"SIMPLES",IF(O13>=MAX(L13,O13,R13),"LUCRO PRESUMIDO","LUCRO REAL")) -> LUCRO PRESUMIDO
... A85: Dec '32 | B85: 375207.34 | C85: 55500 | D85: 0 | E85: =D85*1.288 -> 0 | F85: =IF(ROW()-1<13,SUM($B$2:B85),SUM(INDEX($B:$B,ROW()-11):B85)) -> 4374510.3 | G85: =IF(ROW()-1<13,SUM($C$2:C85)+SUM($D$2:D85),SUM(INDEX($C:$C,ROW()-11):C85)+SUM(INDEX($D:$D,ROW()-11):D85)) -> 666000 | H85: =IF(F85=0,0,G85/F85) -> 0.15224561 | I85: =IF(H85>=0.28,"III","V") -> V | J85: =IF(I85="III",IF(F85<=180000,0.06,IF(F85<=360000,(F85*0.112-9360)/F85,IF(F85<=720000,(F85*0.135-17640)/F85,IF(F85<=1800000,(F85*0.16-35640)/F85,IF(F85<=3600000,(F85*0.21-125640)/F85,IF(F85<=4800000,(F85*0.33-648000)/F85,0)))))),IF(F85<=180000,0.155,IF(F85<=360000,(F85*0.18-4500)/F85,IF(F85<=720000,(F85*0.195-9900)/F85,IF(F85<=1800000,(F85*0.205-17100)/F85,IF(F85<=3600000,(F85*0.23-62100)/F85,IF(F85<=4800000,(F85*0.305-540000)/F85,0))))))) -> 0.18155761 | K85: =B85*J85 -> 68121.748 | L85: =B85-K85 -> 307085.59 | M85: =N85/B85 -> 0.13996961 | N85: =(B85*0.32*0.15)+(MAX(0,(B85*0.32)-20000)*0.1)+(B85*0.32*0.09)+(B85*0.0365) -> 52517.626 | O85: =B85-N85 -> 322689.71 | P85: =Q85/B85 -> 0.37687742 | Q85: =MAX(0,(B85-C85-E85))*0.15+MAX(0,(B85-C85-E85-20000))*0.1+MAX(0,(B85-C85-E85))*0.09+(B85*0.0925) -> 141407.17 | R85: =B85-Q85 -> 233800.16 | S85: =IF(L85>=MAX(L85,O85,R85),"SIMPLES",IF(O85>=MAX(L85,O85,R85),"LUCRO PRESUMIDO","LUCRO REAL")) -> LUCRO PRESUMIDO

Sheet Valores - Balanço Patrimonial
B1: Jan '26 | C1: Feb '26 | D1: Mar '26 | E1: Apr '26 | F1: May '26 | G1: Jun '26 | H1: Jul '26 | I1: Aug '26 | J1: Sep '26 | K1: Oct '26 | L1: Nov '26 | M1: Dec '26 | N1: 2026 | O1: Jan '27 | P1: Feb '27 | Q1: Mar '27 | R1: Apr '27 | S1: May '27 | T1: Jun '27 | U1: Jul '27 | V1: Aug '27 | W1: Sep '27 | X1: Oct '27 | Y1: Nov '27 | Z1: Dec '27 | AA1: 2027 | AB1: Jan '28 | AC1: Feb '28 | AD1: Mar '28 | AE1: Apr '28 | AF1: May '28 | AG1: Jun '28 | AH1: Jul '28 | AI1: Aug '28 | AJ1: Sep '28 | AK1: Oct '28 | AL1: Nov '28 | AM1: Dec '28 | AN1: 2028 | AO1: Jan '29 | AP1: Feb '29 | AQ1: Mar '29 | AR1: Apr '29 | AS1: May '29 | AT1: Jun '29 | AU1: Jul '29 | AV1: Aug '29 | AW1: Sep '29 | AX1: Oct '29 | AY1: Nov '29 | AZ1: Dec '29 | BA1: 2029 | BB1: Jan '30 | BC1: Feb '30 | BD1: Mar '30 | BE1: Apr '30 | BF1: May '30 | BG1: Jun '30 | BH1: Jul '30 | BI1: Aug '30 | BJ1: Sep '30 | BK1: Oct '30 | BL1: Nov '30 | BM1: Dec '30 | BN1: 2030 | BO1: Jan '31 | BP1: Feb '31 | BQ1: Mar '31 | BR1: Apr '31 | BS1: May '31 | BT1: Jun '31 | BU1: Jul '31 | BV1: Aug '31 | BW1: Sep '31 | BX1: Oct '31 | BY1: Nov '31 | BZ1: Dec '31 | CA1: 2031 | CB1: Jan '32 | CC1: Feb '32 | CD1: Mar '32 | CE1: Apr '32 | CF1: May '32 | CG1: Jun '32 | CH1: Jul '32 | CI1: Aug '32 | CJ1: Sep '32 | CK1: Oct '32 | CL1: Nov '32 | CM1: Dec '32 | CN1: 2032 | CO1: total
A2: Ativos | B2: 7291.33 | C2: 13003.46 | D2: 23857.83 | E2: 39747.66 | F2: 60044.1 | G2: 84087.16 | H2: 110727.89 | I2: 140890.27 | J2: 174500.68 | K2: 211463.18 | L2: 251688.55 | M2: 295103.06 | N2: 295103.06 | O2: 328895.66 | P2: 357266.92 | Q2: 386954.62 | R2: 417895.89 | S2: 450090.91 | T2: 483481.45 | U2: 518012.58 | V2: 553703.33 | W2: 565507.04 | X2: 578367.19 | Y2: 592235.58 | Z2: 607153.61 | AA2: 607153.61 | AB2: 617600.55 | AC2: 629836.63 | AD2: 640517.7 | AE2: 651664.93 | AF2: 663667.06 | AG2: 676482.64 | AH2: 690184.91 | AI2: 704745.46 | AJ2: 720122.84 | AK2: 736279.67 | AL2: 753183.24 | AM2: 770796.33 | AN2: 770796.33 | AO2: 785475.74 | AP2: 801993.97 | AQ2: 817161.9 | AR2: 832755.82 | AS2: 848727.48 | AT2: 865028.44 | AU2: 881608.91 | AV2: 898418.23 | AW2: 915409.08 | AX2: 932531.28 | AY2: 948233.12 | AZ2: 963646.21 | BA2: 963646.21 | BB2: 996062.53 | BC2: 1034020.1 | BD2: 1066207 | BE2: 1099175.8 | BF2: 1132910.8 | BG2: 1167396.2 | BH2: 1202616.5 | BI2: 1238555.6 | BJ2: 1275203.1 | BK2: 1312540.1 | BL2: 1348682.5 | BM2: 1385487.7 | BN2: 1385487.7 | BO2: 1426852.4 | BP2: 1469761.2 | BQ2: 1513362 | BR2: 1557640.2 | BS2: 1602581.2 | BT2: 1648175.1 | BU2: 1694409.6 | BV2: 1741266.8 | BW2: 1788737.5 | BX2: 1836809.1 | BY2: 1885469.1 | BZ2: 1934705.3 | CA2: 1934705.3 | CB2: 1980066.6 | CC2: 2026790.3 | CD2: 2074060.4 | CE2: 2121869.1 | CF2: 2170201.8 | CG2: 2219050.9 | CH2: 2268406.7 | CI2: 2318258.5 | CJ2: 2367097.8 | CK2: 2415100.1 | CL2: 2463444.9 | CM2: 2512246 | CN2: 2512246 | CO2: 2512246
A3: Ativos Circulantes | B3: 7291.33 | C3: 13003.46 | D3: 23857.83 | E3: 39747.66 | F3: 60044.1 | G3: 84087.16 | H3: 110727.89 | I3: 140890.27 | J3: 174500.68 | K3: 211463.18 | L3: 251688.55 | M3: 295103.06 | N3: 295103.06 | O3: 328895.66 | P3: 357266.92 | Q3: 386954.62 | R3: 417895.89 | S3: 450090.91 | T3: 483481.45 | U3: 518012.58 | V3: 553703.33 | W3: 565507.04 | X3: 578367.19 | Y3: 592235.58 | Z3: 607153.61 | AA3: 607153.61 | AB3: 617600.55 | AC3: 629836.63 | AD3: 640517.7 | AE3: 651664.93 | AF3: 663667.06 | AG3: 676482.64 | AH3: 690184.91 | AI3: 704745.46 | AJ3: 720122.84 | AK3: 736279.67 | AL3: 753183.24 | AM3: 770796.33 | AN3: 770796.33 | AO3: 785475.74 | AP3: 801993.97 | AQ3: 817161.9 | AR3: 832755.82 | AS3: 848727.48 | AT3: 865028.44 | AU3: 881608.91 | AV3: 898418.23 | AW3: 915409.08 | AX3: 932531.28 | AY3: 948233.12 | AZ3: 963646.21 | BA3: 963646.21 | BB3: 996062.53 | BC3: 1034020.1 | BD3: 1066207 | BE3: 1099175.8 | BF3: 1132910.8 | BG3: 1167396.2 | BH3: 1202616.5 | BI3: 1238555.6 | BJ3: 1275203.1 | BK3: 1312540.1 | BL3: 1348682.5 | BM3: 1385487.7 | BN3: 1385487.7 | BO3: 1426852.4 | BP3: 1469761.2 | BQ3: 1513362 | BR3: 1557640.2 | BS3: 1602581.2 | BT3: 1648175.1 | BU3: 1694409.6 | BV3: 1741266.8 | BW3: 1788737.5 | BX3: 1836809.1 | BY3: 1885469.1 | BZ3: 1934705.3 | CA3: 1934705.3 | CB3: 1980066.6 | CC3: 2026790.3 | CD3: 2074060.4 | CE3: 2121869.1 | CF3: 2170201.8 | CG3: 2219050.9 | CH3: 2268406.7 | CI3: 2318258.5 | CJ3: 2367097.8 | CK3: 2415100.1 | CL3: 2463444.9 | CM3: 2512246 | CN3: 2512246 | CO3: 2512246
A4: Dinheiro | B4: 7291.33 | C4: 13003.46 | D4: 23857.83 | E4: 39747.66 | F4: 60044.1 | G4: 84087.16 | H4: 110727.89 | I4: 140890.27 | J4: 174500.68 | K4: 211463.18 | L4: 251688.55 | M4: 295103.06 | N4: 295103.06 | O4: 328895.66 | P4: 357266.92 | Q4: 386954.62 | R4: 417895.89 | S4: 450090.91 | T4: 483481.45 | U4: 518012.58 | V4: 553703.33 | W4: 565507.04 | X4: 578367.19 | Y4: 592235.58 | Z4: 607153.61 | AA4: 607153.61 | AB4: 617600.55 | AC4: 629836.63 | AD4: 640517.7 | AE4: 651664.93 | AF4: 663667.06 | AG4: 676482.64 | AH4: 690184.91 | AI4: 704745.46 | AJ4: 720122.84 | AK4: 736279.67 | AL4: 753183.24 | AM4: 770796.33 | AN4: 770796.33 | AO4: 785475.74 | AP4: 801993.97 | AQ4: 817161.9 | AR4: 832755.82 | AS4: 848727.48 | AT4: 865028.44 | AU4: 881608.91 | AV4: 898418.23 | AW4: 915409.08 | AX4: 932531.28 | AY4: 948233.12 | AZ4: 963646.21 | BA4: 963646.21 | BB4: 996062.53 | BC4: 1034020.1 | BD4: 1066207 | BE4: 1099175.8 | BF4: 1132910.8 | BG4: 1167396.2 | BH4: 1202616.5 | BI4: 1238555.6 | BJ4: 1275203.1 | BK4: 1312540.1 | BL4: 1348682.5 | BM4: 1385487.7 | BN4: 1385487.7 | BO4: 1426852.4 | BP4: 1469761.2 | BQ4: 1513362 | BR4: 1557640.2 | BS4: 1602581.2 | BT4: 1648175.1 | BU4: 1694409.6 | BV4: 1741266.8 | BW4: 1788737.5 | BX4: 1836809.1 | BY4: 1885469.1 | BZ4: 1934705.3 | CA4: 1934705.3 | CB4: 1980066.6 | CC4: 2026790.3 | CD4: 2074060.4 | CE4: 2121869.1 | CF4: 2170201.8 | CG4: 2219050.9 | CH4: 2268406.7 | CI4: 2318258.5 | CJ4: 2367097.8 | CK4: 2415100.1 | CL4: 2463444.9 | CM4: 2512246 | CN4: 2512246 | CO4: 2512246
A5: Contas a receber | B5: 0 | C5: 0 | D5: 0 | E5: 0 | F5: 0 | G5: 0 | H5: 0 | I5: 0 | J5: 0 | K5: 0 | L5: 0 | M5: 0 | N5: 0 | O5: 0 | P5: 0 | Q5: 0 | R5: 0 | S5: 0 | T5: 0 | U5: 0 | V5: 0 | W5: 0 | X5: 0 | Y5: 0 | Z5: 0 | AA5: 0 | AB5: 0 | AC5: 0 | AD5: 0 | AE5: 0 | AF5: 0 | AG5: 0 | AH5: 0 | AI5: 0 | AJ5: 0 | AK5: 0 | AL5: 0 | AM5: 0 | AN5: 0 | AO5: 0 | AP5: 0 | AQ5: 0 | AR5: 0 | AS5: 0 | AT5: 0 | AU5: 0 | AV5: 0 | AW5: 0 | AX5: 0 | AY5: 0 | AZ5: 0 | BA5: 0 | BB5: 0 | BC5: 0 | BD5: 0 | BE5: 0 | BF5: 0 | BG5: 0 | BH5: 0 | BI5: 0 | BJ5: 0 | BK5: 0 | BL5: 0 | BM5: 0 | BN5: 0 | BO5: 0 | BP5: 0 | BQ5: 0 | BR5: 0 | BS5: 0 | BT5: 0 | BU5: 0 | BV5: 0 | BW5: 0 | BX5: 0 | BY5: 0 | BZ5: 0 | CA5: 0 | CB5: 0 | CC5: 0 | CD5: 0 | CE5: 0 | CF5: 0 | CG5: 0 | CH5: 0 | CI5: 0 | CJ5: 0 | CK5: 0 | CL5: 0 | CM5: 0 | CN5: 0 | CO5: 0
A6: Inventário | B6: 0 | C6: 0 | D6: 0 | E6: 0 | F6: 0 | G6: 0 | H6: 0 | I6: 0 | J6: 0 | K6: 0 | L6: 0 | M6: 0 | N6: 0 | O6: 0 | P6: 0 | Q6: 0 | R6: 0 | S6: 0 | T6: 0 | U6: 0 | V6: 0 | W6: 0 | X6: 0 | Y6: 0 | Z6: 0 | AA6: 0 | AB6: 0 | AC6: 0 | AD6: 0 | AE6: 0 | AF6: 0 | AG6: 0 | AH6: 0 | AI6: 0 | AJ6: 0 | AK6: 0 | AL6: 0 | AM6: 0 | AN6: 0 | AO6: 0 | AP6: 0 | AQ6: 0 | AR6: 0 | AS6: 0 | AT6: 0 | AU6: 0 | AV6: 0 | AW6: 0 | AX6: 0 | AY6: 0 | AZ6: 0 | BA6: 0 | BB6: 0 | BC6: 0 | BD6: 0 | BE6: 0 | BF6: 0 | BG6: 0 | BH6: 0 | BI6: 0 | BJ6: 0 | BK6: 0 | BL6: 0 | BM6: 0 | BN6: 0 | BO6: 0 | BP6: 0 | BQ6: 0 | BR6: 0 | BS6: 0 | BT6: 0 | BU6: 0 | BV6: 0 | BW6: 0 | BX6: 0 | BY6: 0 | BZ6: 0 | CA6: 0 | CB6: 0 | CC6: 0 | CD6: 0 | CE6: 0 | CF6: 0 | CG6: 0 | CH6: 0 | CI6: 0 | CJ6: 0 | CK6: 0 | CL6: 0 | CM6: 0 | CN6: 0 | CO6: 0
A7: Outros ativos circulantes | B7: 0 | C7: 0 | D7: 0 | E7: 0 | F7: 0 | G7: 0 | H7: 0 | I7: 0 | J7: 0 | K7: 0 | L7: 0 | M7: 0 | N7: 0 | O7: 0 | P7: 0 | Q7: 0 | R7: 0 | S7: 0 | T7: 0 | U7: 0 | V7: 0 | W7: 0 | X7: 0 | Y7: 0 | Z7: 0 | AA7: 0 | AB7: 0 | AC7: 0 | AD7: 0 | AE7: 0 | AF7: 0 | AG7: 0 | AH7: 0 | AI7: 0 | AJ7: 0 | AK7: 0 | AL7: 0 | AM7: 0 | AN7: 0 | AO7: 0 | AP7: 0 | AQ7: 0 | AR7: 0 | AS7: 0 | AT7: 0 | AU7: 0 | AV7: 0 | AW7: 0 | AX7: 0 | AY7: 0 | AZ7: 0 | BA7: 0 | BB7: 0 | BC7: 0 | BD7: 0 | BE7: 0 | BF7: 0 | BG7: 0 | BH7: 0 | BI7: 0 | BJ7: 0 | BK7: 0 | BL7: 0 | BM7: 0 | BN7: 0 | BO7: 0 | BP7: 0 | BQ7: 0 | BR7: 0 | BS7: 0 | BT7: 0 | BU7: 0 | BV7: 0 | BW7: 0 | BX7: 0 | BY7: 0 | BZ7: 0 | CA7: 0 | CB7: 0 | CC7: 0 | CD7: 0 | CE7: 0 | CF7: 0 | CG7: 0 | CH7: 0 | CI7: 0 | CJ7: 0 | CK7: 0 | CL7: 0 | CM7: 0 | CN7: 0 | CO7: 0
A8: Ativos de Longo Prazo | B8: 0 | C8: 0 | D8: 0 | E8: 0 | F8: 0 | G8: 0 | H8: 0 | I8: 0 | J8: 0 | K8: 0 | L8: 0 | M8: 0 | N8: 0 | O8: 0 | P8: 0 | Q8: 0 | R8: 0 | S8: 0 | T8: 0 | U8: 0 | V8: 0 | W8: 0 | X8: 0 | Y8: 0 | Z8: 0 | AA8: 0 | AB8: 0 | AC8: 0 | AD8: 0 | AE8: 0 | AF8: 0 | AG8: 0 | AH8: 0 | AI8: 0 | AJ8: 0 | AK8: 0 | AL8: 0 | AM8: 0 | AN8: 0 | AO8: 0 | AP8: 0 | AQ8: 0 | AR8: 0 | AS8: 0 | AT8: 0 | AU8: 0 | AV8: 0 | AW8: 0 | AX8: 0 | AY8: 0 | AZ8: 0 | BA8: 0 | BB8: 0 | BC8: 0 | BD8: 0 | BE8: 0 | BF8: 0 | BG8: 0 | BH8: 0 | BI8: 0 | BJ8: 0 | BK8: 0 | BL8: 0 | BM8: 0 | BN8: 0 | BO8: 0 | BP8: 0 | BQ8: 0 | BR8: 0 | BS8: 0 | BT8: 0 | BU8: 0 | BV8: 0 | BW8: 0 | BX8: 0 | BY8: 0 | BZ8: 0 | CA8: 0 | CB8: 0 | CC8: 0 | CD8: 0 | CE8: 0 | CF8: 0 | CG8: 0 | CH8: 0 | CI8: 0 | CJ8: 0 | CK8: 0 | CL8: 0 | CM8: 0 | CN8: 0 | CO8: 0
A9: Ativos Brutos de Longo Prazo | B9: 0 | C9: 0 | D9: 0 | E9: 0 | F9: 0 | G9: 0 | H9: 0 | I9: 0 | J9: 0 | K9: 0 | L9: 0 | M9: 0 | N9: 0 | O9: 0 | P9: 0 | Q9: 0 | R9: 0 | S9: 0 | T9: 0 | U9: 0 | V9: 0 | W9: 0 | X9: 0 | Y9: 0 | Z9: 0 | AA9: 0 | AB9: 0 | AC9: 0 | AD9: 0 | AE9: 0 | AF9: 0 | AG9: 0 | AH9: 0 | AI9: 0 | AJ9: 0 | AK9: 0 | AL9: 0 | AM9: 0 | AN9: 0 | AO9: 0 | AP9: 0 | AQ9: 0 | AR9: 0 | AS9: 0 | AT9: 0 | AU9: 0 | AV9: 0 | AW9: 0 | AX9: 0 | AY9: 0 | AZ9: 0 | BA9: 0 | BB9: 0 | BC9: 0 | BD9: 0 | BE9: 0 | BF9: 0 | BG9: 0 | BH9: 0 | BI9: 0 | BJ9: 0 | BK9: 0 | BL9: 0 | BM9: 0 | BN9: 0 | BO9: 0 | BP9: 0 | BQ9: 0 | BR9: 0 | BS9: 0 | BT9: 0 | BU9: 0 | BV9: 0 | BW9: 0 | BX9: 0 | BY9: 0 | BZ9: 0 | CA9: 0 | CB9: 0 | CC9: 0 | CD9: 0 | CE9: 0 | CF9: 0 | CG9: 0 | CH9: 0 | CI9: 0 | CJ9: 0 | CK9: 0 | CL9: 0 | CM9: 0 | CN9: 0 | CO9: 0
A10: Depreciação acumulada | B10: 0 | C10: 0 | D10: 0 | E10: 0 | F10: 0 | G10: 0 | H10: 0 | I10: 0 | J10: 0 | K10: 0 | L10: 0 | M10: 0 | N10: 0 | O10: 0 | P10: 0 | Q10: 0 | R10: 0 | S10: 0 | T10: 0 | U10: 0 | V10: 0 | W10: 0 | X10: 0 | Y10: 0 | Z10: 0 | AA10: 0 | AB10: 0 | AC10: 0 | AD10: 0 | AE10: 0 | AF10: 0 | AG10: 0 | AH10: 0 | AI10: 0 | AJ10: 0 | AK10: 0 | AL10: 0 | AM10: 0 | AN10: 0 | AO10: 0 | AP10: 0 | AQ10: 0 | AR10: 0 | AS10: 0 | AT10: 0 | AU10: 0 | AV10: 0 | AW10: 0 | AX10: 0 | AY10: 0 | AZ10: 0 | BA10: 0 | BB10: 0 | BC10: 0 | BD10: 0 | BE10: 0 | BF10: 0 | BG10: 0 | BH10: 0 | BI10: 0 | BJ10: 0 | BK10: 0 | BL10: 0 | BM10: 0 | BN10: 0 | BO10: 0 | BP10: 0 | BQ10: 0 | BR10: 0 | BS10: 0 | BT10: 0 | BU10: 0 | BV10: 0 | BW10: 0 | BX10: 0 | BY10: 0 | BZ10: 0 | CA10: 0 | CB10: 0 | CC10: 0 | CD10: 0 | CE10: 0 | CF10: 0 | CG10: 0 | CH10: 0 | CI10: 0 | CJ10: 0 | CK10: 0 | CL10: 0 | CM10: 0 | CN10: 0 | CO10: 0
A12: Passivo e Patrimônio Líquido | B12: 7291.33 | C12: 13003.46 | D12: 23857.83 | E12: 39747.66 | F12: 60044.1 | G12: 84087.16 | H12: 110727.89 | I12: 140890.27 | J12: 174500.68 | K12: 211463.18 | L12: 251688.55 | M12: 295103.06 | N12: 295103.06 | O12: 328895.66 | P12: 357266.92 | Q12: 386954.62 | R12: 417895.89 | S12: 450090.91 | T12: 483481.45 | U12: 518012.58 | V12: 553703.33 | W12: 565507.04 | X12: 578367.19 | Y12: 592235.58 | Z12: 607153.61 | AA12: 607153.61 | AB12: 617600.55 | AC12: 629836.63 | AD12: 640517.7 | AE12: 651664.93 | AF12: 663667.06 | AG12: 676482.64 | AH12: 690184.91 | AI12: 704745.46 | AJ12: 720122.84 | AK12: 736279.67 | AL12: 753183.24 | AM12: 770796.33 | AN12: 770796.33 | AO12: 785475.74 | AP12: 801993.97 | AQ12: 817161.9 | AR12: 832755.82 | AS12: 848727.48 | AT12: 865028.44 | AU12: 881608.91 | AV12: 898418.23 | AW12: 915409.08 | AX12: 932531.28 | AY12: 948233.12 | AZ12: 963646.21 | BA12: 963646.21 | BB12: 996062.53 | BC12: 1034020.1 | BD12: 1066207 | BE12: 1099175.8 | BF12: 1132910.8 | BG12: 1167396.2 | BH12: 1202616.5 | BI12: 1238555.6 | BJ12: 1275203.1 | BK12: 1312540.1 | BL12: 1348682.5 | BM12: 1385487.7 | BN12: 1385487.7 | BO12: 1426852.4 | BP12: 1469761.2 | BQ12: 1513362 | BR12: 1557640.2 | BS12: 1602581.2 | BT12: 1648175.1 | BU12: 1694409.6 | BV12: 1741266.8 | BW12: 1788737.5 | BX12: 1836809.1 | BY12: 1885469.1 | BZ12: 1934705.3 | CA12: 1934705.3 | CB12: 1980066.6 | CC12: 2026790.3 | CD12: 2074060.4 | CE12: 2121869.1 | CF12: 2170201.8 | CG12: 2219050.9 | CH12: 2268406.7 | CI12: 2318258.5 | CJ12: 2367097.8 | CK12: 2415100.1 | CL12: 2463444.9 | CM12: 2512246 | CN12: 2512246 | CO12: 2512246
A13: Passivos | B13: 34223.33 | C13: 61137.42 | D13: 87578.67 | E13: 113552.41 | F13: 139562.91 | G13: 165166.43 | H13: 190297.3 | I13: 214961.75 | J13: 239164.58 | K13: 262888.27 | L13: 286121.02 | M13: 308862.66 | N13: 308862.66 | O13: 330948.86 | P13: 352698.43 | Q13: 374001.45 | R13: 394830.41 | S13: 415220.31 | T13: 435148.29 | U13: 454591.83 | V13: 473602.86 | W13: 467165.25 | X13: 460254.91 | Y13: 452854.11 | Z13: 445034.76 | AA13: 445034.76 | AB13: 435955.88 | AC13: 427231.52 | AD13: 418482.47 | AE13: 408819.19 | AF13: 398659.02 | AG13: 387986.69 | AH13: 376903.97 | AI13: 365406.71 | AJ13: 353479.1 | AK13: 341109.92 | AL13: 328290.68 | AM13: 315007.9 | AN13: 315007.9 | AO13: 300051.54 | AP13: 285883.04 | AQ13: 271114.7 | AR13: 255670.87 | AS13: 239524.63 | AT13: 222649.31 | AU13: 205016.95 | AV13: 186599.18 | AW13: 167367.59 | AX13: 147291.35 | AY13: 126651.43 | AZ13: 104785.57 | BA13: 104785.57 | BB13: 101298.69 | BC13: 109076.97 | BD13: 110264.11 | BE13: 111428.17 | BF13: 112569.59 | BG13: 113687.91 | BH13: 114783.62 | BI13: 115856.72 | BJ13: 116910.01 | BK13: 117940.2 | BL13: 118951.09 | BM13: 112706.25 | BN13: 112706.25 | BO13: 112772.5 | BP13: 113657.94 | BQ13: 114524.84 | BR13: 115373.18 | BS13: 116203.96 | BT13: 117019.28 | BU13: 117819.63 | BV13: 118601.43 | BW13: 119368.27 | BX13: 120120.16 | BY13: 120856.58 | BZ13: 121578.04 | CA13: 121578.04 | CB13: 121478.54 | CC13: 122167.67 | CD13: 122842.34 | CE13: 123504.13 | CF13: 124151.48 | CG13: 124786.45 | CH13: 125410.04 | CI13: 126020.78 | CJ13: 126933.64 | CK13: 127644.63 | CL13: 128219.75 | CM13: 128782.5 | CN13: 128782.5 | CO13: 128782.5
A14: Passivo Circulante | B14: 9432.28 | C14: 11973.22 | D14: 14461.31 | E14: 16900.63 | F14: 19801.71 | G14: 22711.62 | H14: 25563.86 | I14: 28357.96 | J14: 31097.48 | K14: 33782.44 | L14: 36412.33 | M14: 38990.74 | N14: 38990.74 | O14: 41349.17 | P14: 43792.63 | Q14: 46188.21 | R14: 48536.41 | S14: 50836.7 | T14: 53089.63 | U14: 55297.75 | V14: 57461.59 | W14: 59584.24 | X14: 61662.09 | Y14: 63698.73 | Z14: 65694.18 | AA14: 65694.18 | AB14: 66822.51 | AC14: 68713.65 | AD14: 71004.68 | AE14: 72823.2 | AF14: 74604.1 | AG14: 76350.5 | AH14: 78059.28 | AI14: 79737.15 | AJ14: 81380.01 | AK14: 82988.33 | AL14: 84565.75 | AM14: 86111.73 | AN14: 86111.73 | AO14: 86429.2 | AP14: 87992.55 | AQ14: 89427.86 | AR14: 90835.85 | AS14: 92215.5 | AT14: 93567.31 | AU14: 94891.31 | AV14: 96187.97 | AW14: 97459.39 | AX14: 98706.08 | AY14: 100242.02 | AZ14: 101439.23 | BA14: 101439.23 | BB14: 101298.69 | BC14: 109076.97 | BD14: 110264.11 | BE14: 111428.17 | BF14: 112569.59 | BG14: 113687.91 | BH14: 114783.62 | BI14: 115856.72 | BJ14: 116910.01 | BK14: 117940.2 | BL14: 118951.09 | BM14: 112706.25 | BN14: 112706.25 | BO14: 112772.5 | BP14: 113657.94 | BQ14: 114524.84 | BR14: 115373.18 | BS14: 116203.96 | BT14: 117019.28 | BU14: 117819.63 | BV14: 118601.43 | BW14: 119368.27 | BX14: 120120.16 | BY14: 120856.58 | BZ14: 121578.04 | CA14: 121578.04 | CB14: 121478.54 | CC14: 122167.67 | CD14: 122842.34 | CE14: 123504.13 | CF14: 124151.48 | CG14: 124786.45 | CH14: 125410.04 | CI14: 126020.78 | CJ14: 126933.64 | CK14: 127644.63 | CL14: 128219.75 | CM14: 128782.5 | CN14: 128782.5 | CO14: 128782.5
... A28: Verificar | B28: 0 | C28: 0 | D28: 0 | E28: 0 | F28: 0 | G28: 0 | H28: 0 | I28: 0 | J28: 0 | K28: 0 | L28: 0 | M28: 0 | N28: 0 | O28: 0 | P28: 0 | Q28: 0 | R28: 0 | S28: 0 | T28: 0 | U28: 0 | V28: 0 | W28: 0 | X28: 0 | Y28: 0 | Z28: 0 | AA28: 0 | AB28: 0 | AC28: 0 | AD28: 0 | AE28: 0 | AF28: 0 | AG28: 0 | AH28: 0 | AI28: 0 | AJ28: 0 | AK28: 0 | AL28: 0 | AM28: 0 | AN28: 0 | AO28: 0 | AP28: 0 | AQ28: 0 | AR28: 0 | AS28: 0 | AT28: 0 | AU28: 0 | AV28: 0 | AW28: 0 | AX28: 0 | AY28: 0 | AZ28: 0 | BA28: 0 | BB28: 0 | BC28: 0 | BD28: 0 | BE28: 0 | BF28: 0 | BG28: 0 | BH28: 0 | BI28: 0 | BJ28: 0 | BK28: 0 | BL28: 0 | BM28: 0 | BN28: 0 | BO28: 0 | BP28: 0 | BQ28: 0 | BR28: 0 | BS28: 0 | BT28: 0 | BU28: 0 | BV28: 0 | BW28: 0 | BX28: 0 | BY28: 0 | BZ28: 0 | CA28: 0 | CB28: 0 | CC28: 0 | CD28: 0 | CE28: 0 | CF28: 0 | CG28: 0 | CH28: 0 | CI28: 0 | CJ28: 0 | CK28: 0 | CL28: 0 | CM28: 0 | CN28: 0 | CO28: 0

Sheet Valores - Fluxo de caixa
B1: Jan '26 | C1: Feb '26 | D1: Mar '26 | E1: Apr '26 | F1: May '26 | G1: Jun '26 | H1: Jul '26 | I1: Aug '26 | J1: Sep '26 | K1: Oct '26 | L1: Nov '26 | M1: Dec '26 | N1: 2026 | O1: Jan '27 | P1: Feb '27 | Q1: Mar '27 | R1: Apr '27 | S1: May '27 | T1: Jun '27 | U1: Jul '27 | V1: Aug '27 | W1: Sep '27 | X1: Oct '27 | Y1: Nov '27 | Z1: Dec '27 | AA1: 2027 | AB1: Jan '28 | AC1: Feb '28 | AD1: Mar '28 | AE1: Apr '28 | AF1: May '28 | AG1: Jun '28 | AH1: Jul '28 | AI1: Aug '28 | AJ1: Sep '28 | AK1: Oct '28 | AL1: Nov '28 | AM1: Dec '28 | AN1: 2028 | AO1: Jan '29 | AP1: Feb '29 | AQ1: Mar '29 | AR1: Apr '29 | AS1: May '29 | AT1: Jun '29 | AU1: Jul '29 | AV1: Aug '29 | AW1: Sep '29 | AX1: Oct '29 | AY1: Nov '29 | AZ1: Dec '29 | BA1: 2029 | BB1: Jan '30 | BC1: Feb '30 | BD1: Mar '30 | BE1: Apr '30 | BF1: May '30 | BG1: Jun '30 | BH1: Jul '30 | BI1: Aug '30 | BJ1: Sep '30 | BK1: Oct '30 | BL1: Nov '30 | BM1: Dec '30 | BN1: 2030 | BO1: Jan '31 | BP1: Feb '31 | BQ1: Mar '31 | BR1: Apr '31 | BS1: May '31 | BT1: Jun '31 | BU1: Jul '31 | BV1: Aug '31 | BW1: Sep '31 | BX1: Oct '31 | BY1: Nov '31 | BZ1: Dec '31 | CA1: 2031 | CB1: Jan '32 | CC1: Feb '32 | CD1: Mar '32 | CE1: Apr '32 | CF1: May '32 | CG1: Jun '32 | CH1: Jul '32 | CI1: Aug '32 | CJ1: Sep '32 | CK1: Oct '32 | CL1: Nov '32 | CM1: Dec '32 | CN1: 2032 | CO1: total
A2: Dinheiro recebido | B2: 9695.28 | C2: 19196.66 | D2: 28504.13 | E2: 37627.38 | F2: 46566.43 | G2: 55330.97 | H2: 63920.97 | I2: 72336.49 | J2: 80587.17 | K2: 88673.03 | L2: 96594.07 | M2: 104359.99 | N2: 703392.57 | O2: 111970.78 | P2: 119426.45 | Q2: 126736.7 | R2: 133901.52 | S2: 140920.89 | T2: 147794.85 | U2: 154533.06 | V2: 161135.55 | W2: 167612 | X2: 173952.72 | Y2: 180167.38 | Z2: 186256.03 | AA2: 1804407.9 | AB2: 192228.32 | AC2: 198074.57 | AD2: 203804.48 | AE2: 209427.75 | AF2: 214934.66 | AG2: 220334.94 | AH2: 225618.86 | AI2: 230805.84 | AJ2: 235886.17 | AK2: 240859.83 | AL2: 245736.57 | AM2: 250516.33 | AN2: 2668228.3 | AO2: 255199.16 | AP2: 259794.73 | AQ2: 264293.33 | AR2: 268704.69 | AS2: 273028.79 | AT2: 277265.61 | AU2: 281415.2 | AV2: 285477.52 | AW2: 289462.28 | AX2: 293369.48 | AY2: 297199.11 | AZ2: 300951.19 | BA2: 3346161.1 | BB2: 304625.69 | BC2: 308232.35 | BD2: 311761.42 | BE2: 315222.64 | BF2: 318615.98 | BG2: 321941.47 | BH2: 325199.09 | BI2: 328388.83 | BJ2: 331520.4 | BK2: 334584.11 | BL2: 337589.65 | BM2: 340537.01 | BN2: 3878218.6 | BO2: 343426.21 | BP2: 346257.22 | BQ2: 349030.08 | BR2: 351744.76 | BS2: 354401.26 | BT2: 357009.29 | BU2: 359568.85 | BV2: 362070.23 | BW2: 364523.13 | BX2: 366927.57 | BY2: 369283.51 | BZ2: 371591 | CA2: 4295833.1 | CB2: 373849.99 | CC2: 376070.21 | CD2: 378241.96 | CE2: 380374.91 | CF2: 382459.4 | CG2: 384505.11 | CH2: 386512.03 | CI2: 388480.17 | CJ2: 390409.53 | CK2: 392300.11 | CL2: 394151.91 | CM2: 395964.93 | CN2: 4623320.3 | CO2: 21319562
A3: Dinheiro pago | B3: 27195 | C3: 37857.68 | D3: 41602.92 | E3: 45271.97 | F3: 49379.41 | G3: 53981.52 | H3: 59558.87 | I3: 64044.46 | J3: 68440.07 | K3: 72749.26 | L3: 76971.56 | M3: 81108.71 | N3: 678161.43 | O3: 99960.8 | P3: 103734.33 | Q3: 107565.06 | R3: 111320.59 | S3: 115000.92 | T3: 118606.01 | U3: 122137.67 | V3: 125598.95 | W3: 128992.13 | X3: 132318.05 | Y3: 135575.36 | Z3: 138767.65 | AA3: 1439577.5 | AB3: 152032.69 | AC3: 154245.79 | AD3: 162637.64 | AE3: 165971.58 | AF3: 168811.45 | AG3: 171593.89 | AH3: 174320.27 | AI3: 176991.48 | AJ3: 179611.47 | AK3: 182176.65 | AL3: 184689.74 | AM3: 187153.88 | AN3: 2060236.5 | AO3: 195586.43 | AP3: 196833.37 | AQ3: 202961.54 | AR3: 205196.38 | AS3: 207387.61 | AT3: 209534.7 | AU3: 211638.15 | AV3: 213698.5 | AW3: 215716.97 | AX3: 217696.16 | AY3: 222950.58 | AZ3: 225166.21 | BA3: 2524366.6 | BB3: 232931.07 | BC3: 240071.33 | BD3: 248549.98 | BE3: 250423.74 | BF3: 252261.19 | BG3: 254062.25 | BH3: 255826.96 | BI3: 257555.81 | BJ3: 259250.27 | BK3: 260911.17 | BL3: 266287.68 | BM3: 260647.2 | BN3: 3038778.6 | BO3: 260730.1 | BP3: 261291.31 | BQ3: 262661.18 | BR3: 264001.98 | BS3: 265314.69 | BT3: 266601.07 | BU3: 267863.72 | BV3: 269100.87 | BW3: 270311.19 | BX3: 271498.27 | BY3: 272661.62 | BZ3: 273801.24 | CA3: 3205837.2 | CB3: 282991.61 | CC3: 283275.01 | CD3: 284339.27 | CE3: 285381.54 | CF3: 286403.15 | CG3: 287403.31 | CH3: 288385.07 | CI3: 289347.92 | CJ3: 293605.41 | CK3: 296968.5 | CL3: 297999.2 | CM3: 298887.01 | CN3: 3474987 | CO3: 16421945
A4: COS e Despesas Gerais | B4: 8095 | C4: 17420.4 | D4: 19855.1 | E4: 22240.36 | F4: 25089.43 | G4: 28458.56 | H4: 31827.01 | I4: 35127.78 | J4: 38362.62 | K4: 41533.79 | L4: 44640.8 | M4: 47685.39 | N4: 360336.24 | O4: 50501.32 | P4: 53225.09 | Q4: 56027.45 | R4: 58774.67 | S4: 61466.74 | T4: 64103.65 | U4: 66687.17 | V4: 69219.05 | W4: 71701.54 | X4: 74134.15 | Y4: 76516.88 | Z4: 78851.98 | AA4: 781209.69 | AB4: 80312.2 | AC4: 81701.54 | AD4: 84287.01 | AE4: 86830.62 | AF4: 88894.86 | AG4: 90917.73 | AH4: 92899.24 | AI4: 94841.64 | AJ4: 96746.18 | AK4: 98610.62 | AL4: 100437.7 | AM4: 102229.18 | AN4: 1098708.5 | AO4: 102787.46 | AP4: 103388.49 | AQ4: 105132.78 | AR4: 106747.13 | AS4: 108329.89 | AT4: 109880.55 | AU4: 111399.62 | AV4: 112887.61 | AW4: 114345.76 | AX4: 115775.33 | AY4: 117490.82 | AZ4: 119178.23 | BA4: 1327343.7 | BB4: 119210.56 | BC4: 125844 | BD4: 133825.17 | BE4: 135212.17 | BF4: 136572.2 | BG4: 137905.22 | BH4: 139211.24 | BI4: 140490.76 | BJ4: 141745.26 | BK4: 142974.22 | BL4: 144178.15 | BM4: 138123.11 | BN4: 1635292.1 | BO4: 131139.48 | BP4: 131302.18 | BQ4: 132281.57 | BR4: 133239.9 | BS4: 134178.17 | BT4: 135098.14 | BU4: 136001.06 | BV4: 136885.17 | BW4: 137750.47 | BX4: 138599.22 | BY4: 139430.92 | BZ4: 140245.59 | CA4: 1626151.9 | CB4: 140237.68 | CC4: 140209.5 | CD4: 140967.52 | CE4: 141710.23 | CF4: 142437.65 | CG4: 143150.29 | CH4: 143849.88 | CI4: 144535.92 | CJ4: 145521.94 | CK4: 146618.91 | CL4: 147388.84 | CM4: 148021.23 | CN4: 1724649.6 | CO4: 8553691.6
A5: Salário e vencimentos | B5: 19100 | C5: 19100 | D5: 19100 | E5: 19100 | F5: 19100 | G5: 19100 | H5: 20100 | I5: 20100 | J5: 20100 | K5: 20100 | L5: 20100 | M5: 20100 | N5: 235200 | O5: 35065 | P5: 35065 | Q5: 35065 | R5: 35065 | S5: 35065 | T5: 35065 | U5: 35065 | V5: 35065 | W5: 35065 | X5: 35065 | Y5: 35065 | Z5: 35065 | AA5: 420780 | AB5: 46030 | AC5: 46030 | AD5: 51030 | AE5: 51030 | AF5: 51030 | AG5: 51030 | AH5: 51030 | AI5: 51030 | AJ5: 51030 | AK5: 51030 | AL5: 51030 | AM5: 51030 | AN5: 602360 | AO5: 58245 | AP5: 58245 | AQ5: 61995 | AR5: 61995 | AS5: 61995 | AT5: 61995 | AU5: 61995 | AV5: 61995 | AW5: 61995 | AX5: 61995 | AY5: 64995 | AZ5: 64995 | BA5: 742440 | BB5: 72210 | BC5: 72210 | BD5: 72210 | BE5: 72210 | BF5: 72210 | BG5: 72210 | BH5: 72210 | BI5: 72210 | BJ5: 72210 | BK5: 72210 | BL5: 75960 | BM5: 75960 | BN5: 874020 | BO5: 82620 | BP5: 82620 | BQ5: 82620 | BR5: 82620 | BS5: 82620 | BT5: 82620 | BU5: 82620 | BV5: 82620 | BW5: 82620 | BX5: 82620 | BY5: 82620 | BZ5: 82620 | CA5: 991440 | CB5: 91500 | CC5: 91500 | CD5: 91500 | CE5: 91500 | CF5: 91500 | CG5: 91500 | CH5: 91500 | CI5: 91500 | CJ5: 94500 | CK5: 96500 | CL5: 96500 | CM5: 96500 | CN5: 1116000 | CO5: 4982240
A6: Interesse | B6: 0 | C6: 0 | D6: 0 | E6: 0 | F6: 0 | G6: 0 | H6: 0 | I6: 0 | J6: 0 | K6: 0 | L6: 0 | M6: 0 | N6: 0 | O6: 0 | P6: 0 | Q6: 0 | R6: 0 | S6: 0 | T6: 0 | U6: 0 | V6: 0 | W6: 0 | X6: 0 | Y6: 0 | Z6: 0 | AA6: 0 | AB6: 0 | AC6: 0 | AD6: 0 | AE6: 0 | AF6: 0 | AG6: 0 | AH6: 0 | AI6: 0 | AJ6: 0 | AK6: 0 | AL6: 0 | AM6: 0 | AN6: 0 | AO6: 0 | AP6: 0 | AQ6: 0 | AR6: 0 | AS6: 0 | AT6: 0 | AU6: 0 | AV6: 0 | AW6: 0 | AX6: 0 | AY6: 0 | AZ6: 0 | BA6: 0 | BB6: 0 | BC6: 0 | BD6: 0 | BE6: 0 | BF6: 0 | BG6: 0 | BH6: 0 | BI6: 0 | BJ6: 0 | BK6: 0 | BL6: 0 | BM6: 0 | BN6: 0 | BO6: 0 | BP6: 0 | BQ6: 0 | BR6: 0 | BS6: 0 | BT6: 0 | BU6: 0 | BV6: 0 | BW6: 0 | BX6: 0 | BY6: 0 | BZ6: 0 | CA6: 0 | CB6: 0 | CC6: 0 | CD6: 0 | CE6: 0 | CF6: 0 | CG6: 0 | CH6: 0 | CI6: 0 | CJ6: 0 | CK6: 0 | CL6: 0 | CM6: 0 | CN6: 0 | CO6: 0
A7: Sales Tax | B7: 0 | C7: 1337.28 | D7: 2647.82 | E7: 3931.61 | F7: 5189.98 | G7: 6422.96 | H7: 7631.86 | I7: 8816.68 | J7: 9977.45 | K7: 11115.47 | L7: 12230.76 | M7: 13323.32 | N7: 82625.19 | O7: 14394.48 | P7: 15444.24 | Q7: 16472.61 | R7: 17480.92 | S7: 18469.18 | T7: 19437.36 | U7: 20385.5 | V7: 21314.9 | W7: 22225.59 | X7: 23118.9 | Y7: 23993.48 | Z7: 24850.67 | AA7: 237587.83 | AB7: 25690.49 | AC7: 26514.25 | AD7: 27320.63 | AE7: 28110.96 | AF7: 28886.59 | AG7: 29646.16 | AH7: 30391.03 | AI7: 31119.84 | AJ7: 31835.29 | AK7: 32536.03 | AL7: 33222.04 | AM7: 33894.7 | AN7: 359168.01 | AO7: 34553.97 | AP7: 35199.88 | AQ7: 35833.76 | AR7: 36454.25 | AS7: 37062.72 | AT7: 37659.15 | AU7: 38243.53 | AV7: 38815.89 | AW7: 39376.21 | AX7: 39925.83 | AY7: 40464.76 | AZ7: 40992.98 | BA7: 454582.93 | BB7: 41510.51 | BC7: 42017.33 | BD7: 42514.81 | BE7: 43001.57 | BF7: 43478.99 | BG7: 43947.03 | BH7: 44405.72 | BI7: 44855.05 | BJ7: 45295.01 | BK7: 45726.95 | BL7: 46149.53 | BM7: 46564.09 | BN7: 529466.59 | BO7: 46970.62 | BP7: 47369.13 | BQ7: 47759.61 | BR7: 48142.08 | BS7: 48516.52 | BT7: 48882.93 | BU7: 49242.66 | BV7: 49595.7 | BW7: 49940.72 | BX7: 50279.05 | BY7: 50610.7 | BZ7: 50935.65 | CA7: 588245.37 | CB7: 51253.93 | CC7: 51565.51 | CD7: 51871.75 | CE7: 52171.31 | CF7: 52465.5 | CG7: 52753.02 | CH7: 53035.19 | CI7: 53312 | CJ7: 53583.47 | CK7: 53849.59 | CL7: 54110.36 | CM7: 54365.78 | CN7: 634337.41 | CO7: 2886013.3
A8: Imposto de Renda | B8: 0 | C8: 0 | D8: 0 | E8: 0 | F8: 0 | G8: 0 | H8: 0 | I8: 0 | J8: 0 | K8: 0 | L8: 0 | M8: 0 | N8: 0 | O8: 0 | P8: 0 | Q8: 0 | R8: 0 | S8: 0 | T8: 0 | U8: 0 | V8: 0 | W8: 0 | X8: 0 | Y8: 0 | Z8: 0 | AA8: 0 | AB8: 0 | AC8: 0 | AD8: 0 | AE8: 0 | AF8: 0 | AG8: 0 | AH8: 0 | AI8: 0 | AJ8: 0 | AK8: 0 | AL8: 0 | AM8: 0 | AN8: 0 | AO8: 0 | AP8: 0 | AQ8: 0 | AR8: 0 | AS8: 0 | AT8: 0 | AU8: 0 | AV8: 0 | AW8: 0 | AX8: 0 | AY8: 0 | AZ8: 0 | BA8: 0 | BB8: 0 | BC8: 0 | BD8: 0 | BE8: 0 | BF8: 0 | BG8: 0 | BH8: 0 | BI8: 0 | BJ8: 0 | BK8: 0 | BL8: 0 | BM8: 0 | BN8: 0 | BO8: 0 | BP8: 0 | BQ8: 0 | BR8: 0 | BS8: 0 | BT8: 0 | BU8: 0 | BV8: 0 | BW8: 0 | BX8: 0 | BY8: 0 | BZ8: 0 | CA8: 0 | CB8: 0 | CC8: 0 | CD8: 0 | CE8: 0 | CF8: 0 | CG8: 0 | CH8: 0 | CI8: 0 | CJ8: 0 | CK8: 0 | CL8: 0 | CM8: 0 | CN8: 0 | CO8: 0
A9: Caixa Líquido das Operações | B9: -17499.72 | C9: -18661.02 | D9: -13098.79 | E9: -7644.59 | F9: -2812.98 | G9: 1349.45 | H9: 4362.1 | I9: 8292.03 | J9: 12147.1 | K9: 15923.77 | L9: 19622.51 | M9: 23251.28 | N9: 25231.14 | O9: 12009.98 | P9: 15692.12 | Q9: 19171.64 | R9: 22580.93 | S9: 25919.97 | T9: 29188.84 | U9: 32395.39 | V9: 35536.6 | W9: 38619.87 | X9: 41634.67 | Y9: 44592.02 | Z9: 47488.38 | AA9: 364830.41 | AB9: 40195.63 | AC9: 43828.78 | AD9: 41166.84 | AE9: 43456.17 | AF9: 46123.21 | AG9: 48741.05 | AH9: 51298.59 | AI9: 53814.36 | AJ9: 56274.7 | AK9: 58683.18 | AL9: 61046.83 | AM9: 63362.45 | AN9: 607991.79 | AO9: 59612.73 | AP9: 62961.36 | AQ9: 61331.79 | AR9: 63508.31 | AS9: 65641.18 | AT9: 67730.91 | AU9: 69777.05 | AV9: 71779.02 | AW9: 73745.31 | AX9: 75673.32 | AY9: 74248.53 | AZ9: 75784.98 | BA9: 821794.49 | BB9: 71694.62 | BC9: 68161.02 | BD9: 63211.44 | BE9: 64798.9 | BF9: 66354.79 | BG9: 67879.22 | BH9: 69372.13 | BI9: 70833.02 | BJ9: 72270.13 | BK9: 73672.94 | BL9: 71301.97 | BM9: 79889.81 | BN9: 839439.99 | BO9: 82696.11 | BP9: 84965.91 | BQ9: 86368.9 | BR9: 87742.78 | BS9: 89086.57 | BT9: 90408.22 | BU9: 91705.13 | BV9: 92969.36 | BW9: 94211.94 | BX9: 95429.3 | BY9: 96621.89 | BZ9: 97789.76 | CA9: 1089995.9 | CB9: 90858.38 | CC9: 92795.2 | CD9: 93902.69 | CE9: 94993.37 | CF9: 96056.25 | CG9: 97101.8 | CH9: 98126.96 | CI9: 99132.25 | CJ9: 96804.12 | CK9: 95331.61 | CL9: 96152.71 | CM9: 97077.92 | CN9: 1148333.3 | CO9: 4897617
A11: Venda de ativos | B11: 0 | C11: 0 | D11: 0 | E11: 0 | F11: 0 | G11: 0 | H11: 0 | I11: 0 | J11: 0 | K11: 0 | L11: 0 | M11: 0 | N11: 0 | O11: 0 | P11: 0 | Q11: 0 | R11: 0 | S11: 0 | T11: 0 | U11: 0 | V11: 0 | W11: 0 | X11: 0 | Y11: 0 | Z11: 0 | AA11: 0 | AB11: 0 | AC11: 0 | AD11: 0 | AE11: 0 | AF11: 0 | AG11: 0 | AH11: 0 | AI11: 0 | AJ11: 0 | AK11: 0 | AL11: 0 | AM11: 0 | AN11: 0 | AO11: 0 | AP11: 0 | AQ11: 0 | AR11: 0 | AS11: 0 | AT11: 0 | AU11: 0 | AV11: 0 | AW11: 0 | AX11: 0 | AY11: 0 | AZ11: 0 | BA11: 0 | BB11: 0 | BC11: 0 | BD11: 0 | BE11: 0 | BF11: 0 | BG11: 0 | BH11: 0 | BI11: 0 | BJ11: 0 | BK11: 0 | BL11: 0 | BM11: 0 | BN11: 0 | BO11: 0 | BP11: 0 | BQ11: 0 | BR11: 0 | BS11: 0 | BT11: 0 | BU11: 0 | BV11: 0 | BW11: 0 | BX11: 0 | BY11: 0 | BZ11: 0 | CA11: 0 | CB11: 0 | CC11: 0 | CD11: 0 | CE11: 0 | CF11: 0 | CG11: 0 | CH11: 0 | CI11: 0 | CJ11: 0 | CK11: 0 | CL11: 0 | CM11: 0 | CN11: 0 | CO11: 0
A12: Compra de Ativos | B12: 0 | C12: 0 | D12: 0 | E12: 0 | F12: 0 | G12: 0 | H12: 0 | I12: 0 | J12: 0 | K12: 0 | L12: 0 | M12: 0 | N12: 0 | O12: 0 | P12: 0 | Q12: 0 | R12: 0 | S12: 0 | T12: 0 | U12: 0 | V12: 0 | W12: 0 | X12: 0 | Y12: 0 | Z12: 0 | AA12: 0 | AB12: 0 | AC12: 0 | AD12: 0 | AE12: 0 | AF12: 0 | AG12: 0 | AH12: 0 | AI12: 0 | AJ12: 0 | AK12: 0 | AL12: 0 | AM12: 0 | AN12: 0 | AO12: 0 | AP12: 0 | AQ12: 0 | AR12: 0 | AS12: 0 | AT12: 0 | AU12: 0 | AV12: 0 | AW12: 0 | AX12: 0 | AY12: 0 | AZ12: 0 | BA12: 0 | BB12: 0 | BC12: 0 | BD12: 0 | BE12: 0 | BF12: 0 | BG12: 0 | BH12: 0 | BI12: 0 | BJ12: 0 | BK12: 0 | BL12: 0 | BM12: 0 | BN12: 0 | BO12: 0 | BP12: 0 | BQ12: 0 | BR12: 0 | BS12: 0 | BT12: 0 | BU12: 0 | BV12: 0 | BW12: 0 | BX12: 0 | BY12: 0 | BZ12: 0 | CA12: 0 | CB12: 0 | CC12: 0 | CD12: 0 | CE12: 0 | CF12: 0 | CG12: 0 | CH12: 0 | CI12: 0 | CJ12: 0 | CK12: 0 | CL12: 0 | CM12: 0 | CN12: 0 | CO12: 0
A13: Caixa Líquido de Investimentos | B13: 0 | C13: 0 | D13: 0 | E13: 0 | F13: 0 | G13: 0 | H13: 0 | I13: 0 | J13: 0 | K13: 0 | L13: 0 | M13: 0 | N13: 0 | O13: 0 | P13: 0 | Q13: 0 | R13: 0 | S13: 0 | T13: 0 | U13: 0 | V13: 0 | W13: 0 | X13: 0 | Y13: 0 | Z13: 0 | AA13: 0 | AB13: 0 | AC13: 0 | AD13: 0 | AE13: 0 | AF13: 0 | AG13: 0 | AH13: 0 | AI13: 0 | AJ13: 0 | AK13: 0 | AL13: 0 | AM13: 0 | AN13: 0 | AO13: 0 | AP13: 0 | AQ13: 0 | AR13: 0 | AS13: 0 | AT13: 0 | AU13: 0 | AV13: 0 | AW13: 0 | AX13: 0 | AY13: 0 | AZ13: 0 | BA13: 0 | BB13: 0 | BC13: 0 | BD13: 0 | BE13: 0 | BF13: 0 | BG13: 0 | BH13: 0 | BI13: 0 | BJ13: 0 | BK13: 0 | BL13: 0 | BM13: 0 | BN13: 0 | BO13: 0 | BP13: 0 | BQ13: 0 | BR13: 0 | BS13: 0 | BT13: 0 | BU13: 0 | BV13: 0 | BW13: 0 | BX13: 0 | BY13: 0 | BZ13: 0 | CA13: 0 | CB13: 0 | CC13: 0 | CD13: 0 | CE13: 0 | CF13: 0 | CG13: 0 | CH13: 0 | CI13: 0 | CJ13: 0 | CK13: 0 | CL13: 0 | CM13: 0 | CN13: 0 | CO13: 0
A15: Valor recebido | B15: 25000 | C15: 25000 | D15: 25000 | E15: 25000 | F15: 25000 | G15: 25000 | H15: 25000 | I15: 25000 | J15: 25000 | K15: 25000 | L15: 25000 | M15: 25000 | N15: 300000 | O15: 25000 | P15: 25000 | Q15: 25000 | R15: 25000 | S15: 25000 | T15: 25000 | U15: 25000 | V15: 25000 | W15: 0 | X15: 0 | Y15: 0 | Z15: 0 | AA15: 200000 | AB15: 0 | AC15: 0 | AD15: 0 | AE15: 0 | AF15: 0 | AG15: 0 | AH15: 0 | AI15: 0 | AJ15: 0 | AK15: 0 | AL15: 0 | AM15: 0 | AN15: 0 | AO15: 0 | AP15: 0 | AQ15: 0 | AR15: 0 | AS15: 0 | AT15: 0 | AU15: 0 | AV15: 0 | AW15: 0 | AX15: 0 | AY15: 0 | AZ15: 0 | BA15: 0 | BB15: 0 | BC15: 0 | BD15: 0 | BE15: 0 | BF15: 0 | BG15: 0 | BH15: 0 | BI15: 0 | BJ15: 0 | BK15: 0 | BL15: 0 | BM15: 0 | BN15: 0 | BO15: 0 | BP15: 0 | BQ15: 0 | BR15: 0 | BS15: 0 | BT15: 0 | BU15: 0 | BV15: 0 | BW15: 0 | BX15: 0 | BY15: 0 | BZ15: 0 | CA15: 0 | CB15: 0 | CC15: 0 | CD15: 0 | CE15: 0 | CF15: 0 | CG15: 0 | CH15: 0 | CI15: 0 | CJ15: 0 | CK15: 0 | CL15: 0 | CM15: 0 | CN15: 0 | CO15: 500000
A16: Empréstimo recebido | B16: 25000 | C16: 25000 | D16: 25000 | E16: 25000 | F16: 25000 | G16: 25000 | H16: 25000 | I16: 25000 | J16: 25000 | K16: 25000 | L16: 25000 | M16: 25000 | N16: 300000 | O16: 25000 | P16: 25000 | Q16: 25000 | R16: 25000 | S16: 25000 | T16: 25000 | U16: 25000 | V16: 25000 | W16: 0 | X16: 0 | Y16: 0 | Z16: 0 | AA16: 200000 | AB16: 0 | AC16: 0 | AD16: 0 | AE16: 0 | AF16: 0 | AG16: 0 | AH16: 0 | AI16: 0 | AJ16: 0 | AK16: 0 | AL16: 0 | AM16: 0 | AN16: 0 | AO16: 0 | AP16: 0 | AQ16: 0 | AR16: 0 | AS16: 0 | AT16: 0 | AU16: 0 | AV16: 0 | AW16: 0 | AX16: 0 | AY16: 0 | AZ16: 0 | BA16: 0 | BB16: 0 | BC16: 0 | BD16: 0 | BE16: 0 | BF16: 0 | BG16: 0 | BH16: 0 | BI16: 0 | BJ16: 0 | BK16: 0 | BL16: 0 | BM16: 0 | BN16: 0 | BO16: 0 | BP16: 0 | BQ16: 0 | BR16: 0 | BS16: 0 | BT16: 0 | BU16: 0 | BV16: 0 | BW16: 0 | BX16: 0 | BY16: 0 | BZ16: 0 | CA16: 0 | CB16: 0 | CC16: 0 | CD16: 0 | CE16: 0 | CF16: 0 | CG16: 0 | CH16: 0 | CI16: 0 | CJ16: 0 | CK16: 0 | CL16: 0 | CM16: 0 | CN16: 0 | CO16: 500000
A17: Ações ordinárias
A18: Ações preferenciais | B18: 0 | C18: 0 | D18: 0 | E18: 0 | F18: 0 | G18: 0 | H18: 0 | I18: 0 | J18: 0 | K18: 0 | L18: 0 | M18: 0 | N18: 0 | O18: 0 | P18: 0 | Q18: 0 | R18: 0 | S18: 0 | T18: 0 | U18: 0 | V18: 0 | W18: 0 | X18: 0 | Y18: 0 | Z18: 0 | AA18: 0 | AB18: 0 | AC18: 0 | AD18: 0 | AE18: 0 | AF18: 0 | AG18: 0 | AH18: 0 | AI18: 0 | AJ18: 0 | AK18: 0 | AL18: 0 | AM18: 0 | AN18: 0 | AO18: 0 | AP18: 0 | AQ18: 0 | AR18: 0 | AS18: 0 | AT18: 0 | AU18: 0 | AV18: 0 | AW18: 0 | AX18: 0 | AY18: 0 | AZ18: 0 | BA18: 0 | BB18: 0 | BC18: 0 | BD18: 0 | BE18: 0 | BF18: 0 | BG18: 0 | BH18: 0 | BI18: 0 | BJ18: 0 | BK18: 0 | BL18: 0 | BM18: 0 | BN18: 0 | BO18: 0 | BP18: 0 | BQ18: 0 | BR18: 0 | BS18: 0 | BT18: 0 | BU18: 0 | BV18: 0 | BW18: 0 | BX18: 0 | BY18: 0 | BZ18: 0 | CA18: 0 | CB18: 0 | CC18: 0 | CD18: 0 | CE18: 0 | CF18: 0 | CG18: 0 | CH18: 0 | CI18: 0 | CJ18: 0 | CK18: 0 | CL18: 0 | CM18: 0 | CN18: 0 | CO18: 0
A19: Contribuição do Proprietário | B19: 0 | C19: 0 | D19: 0 | E19: 0 | F19: 0 | G19: 0 | H19: 0 | I19: 0 | J19: 0 | K19: 0 | L19: 0 | M19: 0 | N19: 0 | O19: 0 | P19: 0 | Q19: 0 | R19: 0 | S19: 0 | T19: 0 | U19: 0 | V19: 0 | W19: 0 | X19: 0 | Y19: 0 | Z19: 0 | AA19: 0 | AB19: 0 | AC19: 0 | AD19: 0 | AE19: 0 | AF19: 0 | AG19: 0 | AH19: 0 | AI19: 0 | AJ19: 0 | AK19: 0 | AL19: 0 | AM19: 0 | AN19: 0 | AO19: 0 | AP19: 0 | AQ19: 0 | AR19: 0 | AS19: 0 | AT19: 0 | AU19: 0 | AV19: 0 | AW19: 0 | AX19: 0 | AY19: 0 | AZ19: 0 | BA19: 0 | BB19: 0 | BC19: 0 | BD19: 0 | BE19: 0 | BF19: 0 | BG19: 0 | BH19: 0 | BI19: 0 | BJ19: 0 | BK19: 0 | BL19: 0 | BM19: 0 | BN19: 0 | BO19: 0 | BP19: 0 | BQ19: 0 | BR19: 0 | BS19: 0 | BT19: 0 | BU19: 0 | BV19: 0 | BW19: 0 | BX19: 0 | BY19: 0 | BZ19: 0 | CA19: 0 | CB19: 0 | CC19: 0 | CD19: 0 | CE19: 0 | CF19: 0 | CG19: 0 | CH19: 0 | CI19: 0 | CJ19: 0 | CK19: 0 | CL19: 0 | CM19: 0 | CN19: 0 | CO19: 0
A20: Valor pago | B20: 208.95 | C20: 626.85 | D20: 1046.84 | E20: 1465.58 | F20: 1890.58 | G20: 2306.39 | H20: 2721.37 | I20: 3129.65 | J20: 3536.69 | K20: 3961.27 | L20: 4397.14 | M20: 4836.77 | N20: 30128.08 | O20: 3217.38 | P20: 12320.86 | Q20: 14483.94 | R20: 16639.66 | S20: 18724.95 | T20: 20798.3 | U20: 22864.26 | V20: 24845.85 | W20: 26816.16 | X20: 28774.52 | Y20: 30723.63 | Z20: 32570.35 | AA20: 252779.86 | AB20: 29748.69 | AC20: 31592.7 | AD20: 30485.77 | AE20: 32308.94 | AF20: 34121.08 | AG20: 35925.47 | AH20: 37596.32 | AI20: 39253.81 | AJ20: 40897.32 | AK20: 42526.35 | AL20: 44143.26 | AM20: 45749.36 | AN20: 444349.07 | AO20: 44933.32 | AP20: 46443.13 | AQ20: 46163.86 | AR20: 47914.39 | AS20: 49669.52 | AT20: 51429.95 | AU20: 53196.58 | AV20: 54969.7 | AW20: 56754.46 | AX20: 58551.12 | AY20: 58546.69 | AZ20: 60371.89 | BA20: 628944.61 | BB20: 39278.3 | BC20: 30203.43 | BD20: 31024.56 | BE20: 31830.14 | BF20: 32619.73 | BG20: 33393.8 | BH20: 34151.87 | BI20: 34893.92 | BJ20: 35622.67 | BK20: 36335.89 | BL20: 35159.59 | BM20: 43084.56 | BN20: 417598.46 | BO20: 41331.46 | BP20: 42057.06 | BQ20: 42768.1 | BR20: 43464.61 | BS20: 44145.55 | BT20: 44814.37 | BU20: 45470.58 | BV20: 46112.23 | BW20: 46741.23 | BX20: 47357.63 | BY20: 47961.9 | BZ20: 48553.56 | CA20: 540778.28 | CB20: 45497.13 | CC20: 46071.45 | CD20: 46632.65 | CE20: 47184.65 | CF20: 47723.52 | CG20: 48252.7 | CH20: 48771.2 | CI20: 49280.46 | CJ20: 47964.82 | CK20: 47329.23 | CL20: 47807.92 | CM20: 48276.88 | CN20: 570792.61 | CO20: 2885371
A21: Capital de empréstimo | B21: 208.95 | C21: 626.85 | D21: 1046.84 | E21: 1465.58 | F21: 1890.58 | G21: 2306.39 | H21: 2721.37 | I21: 3129.65 | J21: 3536.69 | K21: 3961.27 | L21: 4397.14 | M21: 4836.77 | N21: 30128.08 | O21: 5272.23 | P21: 5693.89 | Q21: 6092.56 | R21: 6519.24 | S21: 6910.39 | T21: 7324.95 | U21: 7764.58 | V21: 8152.81 | W21: 8560.26 | X21: 8988.19 | Y21: 9437.44 | Z21: 9814.8 | AA21: 90531.34 | AB21: 10207.21 | AC21: 10615.5 | AD21: 11040.08 | AE21: 11481.8 | AF21: 11941.07 | AG21: 12418.73 | AH21: 12791.5 | AI21: 13175.13 | AJ21: 13570.47 | AK21: 13977.5 | AL21: 14396.66 | AM21: 14828.76 | AN21: 150444.41 | AO21: 15273.83 | AP21: 15731.85 | AQ21: 16203.65 | AR21: 16851.82 | AS21: 17525.89 | AT21: 18227.13 | AU21: 18956.36 | AV21: 19714.43 | AW21: 20503.01 | AX21: 21322.93 | AY21: 22175.86 | AZ21: 23063.07 | BA21: 225549.83 | BB21: 3346.34 | BC21: 0 | BD21: 0 | BE21: 0 | BF21: 0 | BG21: 0 | BH21: 0 | BI21: 0 | BJ21: 0 | BK21: 0 | BL21: 0 | BM21: 0 | BN21: 3346.34 | BO21: 0 | BP21: 0 | BQ21: 0 | BR21: 0 | BS21: 0 | BT21: 0 | BU21: 0 | BV21: 0 | BW21: 0 | BX21: 0 | BY21: 0 | BZ21: 0 | CA21: 0 | CB21: 0 | CC21: 0 | CD21: 0 | CE21: 0 | CF21: 0 | CG21: 0 | CH21: 0 | CI21: 0 | CJ21: 0 | CK21: 0 | CL21: 0 | CM21: 0 | CN21: 0 | CO21: 500000
A22: Dividendos e Distribuições | B22: 0 | C22: 0 | D22: 0 | E22: 0 | F22: 0 | G22: 0 | H22: 0 | I22: 0 | J22: 0 | K22: 0 | L22: 0 | M22: 0 | N22: 0 | O22: -2054.85 | P22: 6626.97 | Q22: 8391.38 | R22: 10120.42 | S22: 11814.56 | T22: 13473.35 | U22: 15099.68 | V22: 16693.04 | W22: 18255.9 | X22: 19786.33 | Y22: 21286.19 | Z22: 22755.55 | AA22: 162248.52 | AB22: 19541.48 | AC22: 20977.2 | AD22: 19445.69 | AE22: 20827.14 | AF22: 22180.01 | AG22: 23506.74 | AH22: 24804.82 | AI22: 26078.68 | AJ22: 27326.85 | AK22: 28548.85 | AL22: 29746.6 | AM22: 30920.6 | AN22: 293904.66 | AO22: 29659.49 | AP22: 30711.28 | AQ22: 29960.21 | AR22: 31062.57 | AS22: 32143.63 | AT22: 33202.82 | AU22: 34240.22 | AV22: 35255.27 | AW22: 36251.45 | AX22: 37228.19 | AY22: 36370.83 | AZ22: 37308.82 | BA22: 403394.78 | BB22: 35931.96 | BC22: 30203.43 | BD22: 31024.56 | BE22: 31830.14 | BF22: 32619.73 | BG22: 33393.8 | BH22: 34151.87 | BI22: 34893.92 | BJ22: 35622.67 | BK22: 36335.89 | BL22: 35159.59 | BM22: 43084.56 | BN22: 414252.12 | BO22: 41331.46 | BP22: 42057.06 | BQ22: 42768.1 | BR22: 43464.61 | BS22: 44145.55 | BT22: 44814.37 | BU22: 45470.58 | BV22: 46112.23 | BW22: 46741.23 | BX22: 47357.63 | BY22: 47961.9 | BZ22: 48553.56 | CA22: 540778.28 | CB22: 45497.13 | CC22: 46071.45 | CD22: 46632.65 | CE22: 47184.65 | CF22: 47723.52 | CG22: 48252.7 | CH22: 48771.2 | CI22: 49280.46 | CJ22: 47964.82 | CK22: 47329.23 | CL22: 47807.92 | CM22: 48276.88 | CN22: 570792.61 | CO22: 2385371
A23: Caixa Líquido de Financiamento | B23: 24791.05 | C23: 24373.15 | D23: 23953.16 | E23: 23534.42 | F23: 23109.42 | G23: 22693.61 | H23: 22278.63 | I23: 21870.35 | J23: 21463.31 | K23: 21038.73 | L23: 20602.86 | M23: 20163.23 | N23: 269871.92 | O23: 21782.62 | P23: 12679.14 | Q23: 10516.06 | R23: 8360.34 | S23: 6275.05 | T23: 4201.7 | U23: 2135.74 | V23: 154.15 | W23: -26816.16 | X23: -28774.52 | Y23: -30723.63 | Z23: -32570.35 | AA23: -52779.86 | AB23: -29748.69 | AC23: -31592.7 | AD23: -30485.77 | AE23: -32308.94 | AF23: -34121.08 | AG23: -35925.47 | AH23: -37596.32 | AI23: -39253.81 | AJ23: -40897.32 | AK23: -42526.35 | AL23: -44143.26 | AM23: -45749.36 | AN23: -444349.07 | AO23: -44933.32 | AP23: -46443.13 | AQ23: -46163.86 | AR23: -47914.39 | AS23: -49669.52 | AT23: -51429.95 | AU23: -53196.58 | AV23: -54969.7 | AW23: -56754.46 | AX23: -58551.12 | AY23: -58546.69 | AZ23: -60371.89 | BA23: -628944.61 | BB23: -39278.3 | BC23: -30203.43 | BD23: -31024.56 | BE23: -31830.14 | BF23: -32619.73 | BG23: -33393.8 | BH23: -34151.87 | BI23: -34893.92 | BJ23: -35622.67 | BK23: -36335.89 | BL23: -35159.59 | BM23: -43084.56 | BN23: -417598.46 | BO23: -41331.46 | BP23: -42057.06 | BQ23: -42768.1 | BR23: -43464.61 | BS23: -44145.55 | BT23: -44814.37 | BU23: -45470.58 | BV23: -46112.23 | BW23: -46741.23 | BX23: -47357.63 | BY23: -47961.9 | BZ23: -48553.56 | CA23: -540778.28 | CB23: -45497.13 | CC23: -46071.45 | CD23: -46632.65 | CE23: -47184.65 | CF23: -47723.52 | CG23: -48252.7 | CH23: -48771.2 | CI23: -49280.46 | CJ23: -47964.82 | CK23: -47329.23 | CL23: -47807.92 | CM23: -48276.88 | CN23: -570792.61 | CO23: -2385371
A25: Resumo
A26: Dinheiro inicial | B26: 0 | C26: 7291.33 | D26: 13003.46 | E26: 23857.83 | F26: 39747.66 | G26: 60044.1 | H26: 84087.16 | I26: 110727.89 | J26: 140890.27 | K26: 174500.68 | L26: 211463.18 | M26: 251688.55 | N26: 0 | O26: 295103.06 | P26: 328895.66 | Q26: 357266.92 | R26: 386954.62 | S26: 417895.89 | T26: 450090.91 | U26: 483481.45 | V26: 518012.58 | W26: 553703.33 | X26: 565507.04 | Y26: 578367.19 | Z26: 592235.58 | AA26: 295103.06 | AB26: 607153.61 | AC26: 617600.55 | AD26: 629836.63 | AE26: 640517.7 | AF26: 651664.93 | AG26: 663667.06 | AH26: 676482.64 | AI26: 690184.91 | AJ26: 704745.46 | AK26: 720122.84 | AL26: 736279.67 | AM26: 753183.24 | AN26: 607153.61 | AO26: 770796.33 | AP26: 785475.74 | AQ26: 801993.97 | AR26: 817161.9 | AS26: 832755.82 | AT26: 848727.48 | AU26: 865028.44 | AV26: 881608.91 | AW26: 898418.23 | AX26: 915409.08 | AY26: 932531.28 | AZ26: 948233.12 | BA26: 770796.33 | BB26: 963646.21 | BC26: 996062.53 | BD26: 1034020.1 | BE26: 1066207 | BF26: 1099175.8 | BG26: 1132910.8 | BH26: 1167396.2 | BI26: 1202616.5 | BJ26: 1238555.6 | BK26: 1275203.1 | BL26: 1312540.1 | BM26: 1348682.5 | BN26: 963646.21 | BO26: 1385487.7 | BP26: 1426852.4 | BQ26: 1469761.2 | BR26: 1513362 | BS26: 1557640.2 | BT26: 1602581.2 | BU26: 1648175.1 | BV26: 1694409.6 | BW26: 1741266.8 | BX26: 1788737.5 | BY26: 1836809.1 | BZ26: 1885469.1 | CA26: 1385487.7 | CB26: 1934705.3 | CC26: 1980066.6 | CD26: 2026790.3 | CE26: 2074060.4 | CF26: 2121869.1 | CG26: 2170201.8 | CH26: 2219050.9 | CI26: 2268406.7 | CJ26: 2318258.5 | CK26: 2367097.8 | CL26: 2415100.1 | CM26: 2463444.9 | CN26: 1934705.3 | CO26: 0
A27: Dinheiro em caixa | B27: 34695.28 | C27: 44196.66 | D27: 53504.13 | E27: 62627.38 | F27: 71566.43 | G27: 80330.97 | H27: 88920.97 | I27: 97336.49 | J27: 105587.17 | K27: 113673.03 | L27: 121594.07 | M27: 129359.99 | N27: 1003392.6 | O27: 136970.78 | P27: 144426.45 | Q27: 151736.7 | R27: 158901.52 | S27: 165920.89 | T27: 172794.85 | U27: 179533.06 | V27: 186135.55 | W27: 167612 | X27: 173952.72 | Y27: 180167.38 | Z27: 186256.03 | AA27: 2004407.9 | AB27: 192228.32 | AC27: 198074.57 | AD27: 203804.48 | AE27: 209427.75 | AF27: 214934.66 | AG27: 220334.94 | AH27: 225618.86 | AI27: 230805.84 | AJ27: 235886.17 | AK27: 240859.83 | AL27: 245736.57 | AM27: 250516.33 | AN27: 2668228.3 | AO27: 255199.16 | AP27: 259794.73 | AQ27: 264293.33 | AR27: 268704.69 | AS27: 273028.79 | AT27: 277265.61 | AU27: 281415.2 | AV27: 285477.52 | AW27: 289462.28 | AX27: 293369.48 | AY27: 297199.11 | AZ27: 300951.19 | BA27: 3346161.1 | BB27: 304625.69 | BC27: 308232.35 | BD27: 311761.42 | BE27: 315222.64 | BF27: 318615.98 | BG27: 321941.47 | BH27: 325199.09 | BI27: 328388.83 | BJ27: 331520.4 | BK27: 334584.11 | BL27: 337589.65 | BM27: 340537.01 | BN27: 3878218.6 | BO27: 343426.21 | BP27: 346257.22 | BQ27: 349030.08 | BR27: 351744.76 | BS27: 354401.26 | BT27: 357009.29 | BU27: 359568.85 | BV27: 362070.23 | BW27: 364523.13 | BX27: 366927.57 | BY27: 369283.51 | BZ27: 371591 | CA27: 4295833.1 | CB27: 373849.99 | CC27: 376070.21 | CD27: 378241.96 | CE27: 380374.91 | CF27: 382459.4 | CG27: 384505.11 | CH27: 386512.03 | CI27: 388480.17 | CJ27: 390409.53 | CK27: 392300.11 | CL27: 394151.91 | CM27: 395964.93 | CN27: 4623320.3 | CO27: 21819562
A28: Saque | B28: 27403.95 | C28: 38484.53 | D28: 42649.76 | E28: 46737.55 | F28: 51269.99 | G28: 56287.91 | H28: 62280.24 | I28: 67174.11 | J28: 71976.76 | K28: 76710.53 | L28: 81368.7 | M28: 85945.48 | N28: 708289.51 | O28: 103178.18 | P28: 116055.19 | Q28: 122049 | R28: 127960.25 | S28: 133725.87 | T28: 139404.31 | U28: 145001.93 | V28: 150444.8 | W28: 155808.29 | X28: 161092.57 | Y28: 166298.99 | Z28: 171338 | AA28: 1692357.4 | AB28: 181781.38 | AC28: 185838.49 | AD28: 193123.41 | AE28: 198280.52 | AF28: 202932.53 | AG28: 207519.36 | AH28: 211916.59 | AI28: 216245.29 | AJ28: 220508.79 | AK28: 224703 | AL28: 228833 | AM28: 232903.24 | AN28: 2504585.6 | AO28: 240519.75 | AP28: 243276.5 | AQ28: 249125.4 | AR28: 253110.77 | AS28: 257057.13 | AT28: 260964.65 | AU28: 264834.73 | AV28: 268668.2 | AW28: 272471.43 | AX28: 276247.28 | AY28: 281497.27 | AZ28: 285538.1 | BA28: 3153311.2 | BB28: 272209.37 | BC28: 270274.76 | BD28: 279574.54 | BE28: 282253.88 | BF28: 284880.92 | BG28: 287456.05 | BH28: 289978.83 | BI28: 292449.73 | BJ28: 294872.94 | BK28: 297247.06 | BL28: 301447.27 | BM28: 303731.76 | BN28: 3456377.1 | BO28: 302061.56 | BP28: 303348.37 | BQ28: 305429.28 | BR28: 307466.59 | BS28: 309460.24 | BT28: 311415.44 | BU28: 313334.3 | BV28: 315213.1 | BW28: 317052.42 | BX28: 318855.9 | BY28: 320623.52 | BZ28: 322354.8 | CA28: 3746615.5 | CB28: 328488.74 | CC28: 329346.46 | CD28: 330971.92 | CE28: 332566.19 | CF28: 334126.67 | CG28: 335656.01 | CH28: 337156.27 | CI28: 338628.38 | CJ28: 341570.23 | CK28: 344297.73 | CL28: 345807.12 | CM28: 347163.89 | CN28: 4045779.6 | CO28: 19307316
A29: Troco em dinheiro | B29: 7291.33 | C29: 5712.13 | D29: 10854.37 | E29: 15889.83 | F29: 20296.44 | G29: 24043.06 | H29: 26640.73 | I29: 30162.38 | J29: 33610.41 | K29: 36962.5 | L29: 40225.37 | M29: 43414.51 | N29: 295103.06 | O29: 33792.6 | P29: 28371.26 | Q29: 29687.7 | R29: 30941.27 | S29: 32195.02 | T29: 33390.54 | U29: 34531.13 | V29: 35690.75 | W29: 11803.71 | X29: 12860.15 | Y29: 13868.39 | Z29: 14918.03 | AA29: 312050.55 | AB29: 10446.94 | AC29: 12236.08 | AD29: 10681.07 | AE29: 11147.23 | AF29: 12002.13 | AG29: 12815.58 | AH29: 13702.27 | AI29: 14560.55 | AJ29: 15377.38 | AK29: 16156.83 | AL29: 16903.57 | AM29: 17613.09 | AN29: 163642.72 | AO29: 14679.41 | AP29: 16518.23 | AQ29: 15167.93 | AR29: 15593.92 | AS29: 15971.66 | AT29: 16300.96 | AU29: 16580.47 | AV29: 16809.32 | AW29: 16990.85 | AX29: 17122.2 | AY29: 15701.84 | AZ29: 15413.09 | BA29: 192849.88 | BB29: 32416.32 | BC29: 37957.59 | BD29: 32186.88 | BE29: 32968.76 | BF29: 33735.06 | BG29: 34485.42 | BH29: 35220.26 | BI29: 35939.1 | BJ29: 36647.46 | BK29: 37337.05 | BL29: 36142.38 | BM29: 36805.25 | BN29: 421841.53 | BO29: 41364.65 | BP29: 42908.85 | BQ29: 43600.8 | BR29: 44278.17 | BS29: 44941.02 | BT29: 45593.85 | BU29: 46234.55 | BV29: 46857.13 | BW29: 47470.71 | BX29: 48071.67 | BY29: 48659.99 | BZ29: 49236.2 | CA29: 549217.59 | CB29: 45361.25 | CC29: 46723.75 | CD29: 47270.04 | CE29: 47808.72 | CF29: 48332.73 | CG29: 48849.1 | CH29: 49355.76 | CI29: 49851.79 | CJ29: 48839.3 | CK29: 48002.38 | CL29: 48344.79 | CM29: 48801.04 | CN29: 577540.65 | CO29: 2512246
A30: Fim do dinheiro | B30: 7291.33 | C30: 13003.46 | D30: 23857.83 | E30: 39747.66 | F30: 60044.1 | G30: 84087.16 | H30: 110727.89 | I30: 140890.27 | J30: 174500.68 | K30: 211463.18 | L30: 251688.55 | M30: 295103.06 | N30: 295103.06 | O30: 328895.66 | P30: 357266.92 | Q30: 386954.62 | R30: 417895.89 | S30: 450090.91 | T30: 483481.45 | U30: 518012.58 | V30: 553703.33 | W30: 565507.04 | X30: 578367.19 | Y30: 592235.58 | Z30: 607153.61 | AA30: 607153.61 | AB30: 617600.55 | AC30: 629836.63 | AD30: 640517.7 | AE30: 651664.93 | AF30: 663667.06 | AG30: 676482.64 | AH30: 690184.91 | AI30: 704745.46 | AJ30: 720122.84 | AK30: 736279.67 | AL30: 753183.24 | AM30: 770796.33 | AN30: 770796.33 | AO30: 785475.74 | AP30: 801993.97 | AQ30: 817161.9 | AR30: 832755.82 | AS30: 848727.48 | AT30: 865028.44 | AU30: 881608.91 | AV30: 898418.23 | AW30: 915409.08 | AX30: 932531.28 | AY30: 948233.12 | AZ30: 963646.21 | BA30: 963646.21 | BB30: 996062.53 | BC30: 1034020.1 | BD30: 1066207 | BE30: 1099175.8 | BF30: 1132910.8 | BG30: 1167396.2 | BH30: 1202616.5 | BI30: 1238555.6 | BJ30: 1275203.1 | BK30: 1312540.1 | BL30: 1348682.5 | BM30: 1385487.7 | BN30: 1385487.7 | BO30: 1426852.4 | BP30: 1469761.2 | BQ30: 1513362 | BR30: 1557640.2 | BS30: 1602581.2 | BT30: 1648175.1 | BU30: 1694409.6 | BV30: 1741266.8 | BW30: 1788737.5 | BX30: 1836809.1 | BY30: 1885469.1 | BZ30: 1934705.3 | CA30: 1934705.3 | CB30: 1980066.6 | CC30: 2026790.3 | CD30: 2074060.4 | CE30: 2121869.1 | CF30: 2170201.8 | CG30: 2219050.9 | CH30: 2268406.7 | CI30: 2318258.5 | CJ30: 2367097.8 | CK30: 2415100.1 | CL30: 2463444.9 | CM30: 2512246 | CN30: 2512246 | CO30: 2512246

Sheet Valores - Empatar
B1: Jan '26 | C1: Feb '26 | D1: Mar '26 | E1: Apr '26 | F1: May '26 | G1: Jun '26 | H1: Jul '26 | I1: Aug '26 | J1: Sep '26 | K1: Oct '26 | L1: Nov '26 | M1: Dec '26 | N1: 2026 | O1: Jan '27 | P1: Feb '27 | Q1: Mar '27 | R1: Apr '27 | S1: May '27 | T1: Jun '27 | U1: Jul '27 | V1: Aug '27 | W1: Sep '27 | X1: Oct '27 | Y1: Nov '27 | Z1: Dec '27 | AA1: 2027 | AB1: Jan '28 | AC1: Feb '28 | AD1: Mar '28 | AE1: Apr '28 | AF1: May '28 | AG1: Jun '28 | AH1: Jul '28 | AI1: Aug '28 | AJ1: Sep '28 | AK1: Oct '28 | AL1: Nov '28 | AM1: Dec '28 | AN1: 2028 | AO1: Jan '29 | AP1: Feb '29 | AQ1: Mar '29 | AR1: Apr '29 | AS1: May '29 | AT1: Jun '29 | AU1: Jul '29 | AV1: Aug '29 | AW1: Sep '29 | AX1: Oct '29 | AY1: Nov '29 | AZ1: Dec '29 | BA1: 2029 | BB1: Jan '30 | BC1: Feb '30 | BD1: Mar '30 | BE1: Apr '30 | BF1: May '30 | BG1: Jun '30 | BH1: Jul '30 | BI1: Aug '30 | BJ1: Sep '30 | BK1: Oct '30 | BL1: Nov '30 | BM1: Dec '30 | BN1: 2030 | BO1: Jan '31 | BP1: Feb '31 | BQ1: Mar '31 | BR1: Apr '31 | BS1: May '31 | BT1: Jun '31 | BU1: Jul '31 | BV1: Aug '31 | BW1: Sep '31 | BX1: Oct '31 | BY1: Nov '31 | BZ1: Dec '31 | CA1: 2031 | CB1: Jan '32 | CC1: Feb '32 | CD1: Mar '32 | CE1: Apr '32 | CF1: May '32 | CG1: Jun '32 | CH1: Jul '32 | CI1: Aug '32 | CJ1: Sep '32 | CK1: Oct '32 | CL1: Nov '32 | CM1: Dec '32 | CN1: 2032 | CO1: total
A2: Receita Inicial | B2: 0 | C2: 8358 | D2: 24906.84 | E2: 49479.36 | F2: 81916.76 | G2: 122060.23 | H2: 169759.34 | I2: 224863.63 | J2: 287222.67 | K2: 356694.37 | L2: 433136.64 | M2: 516407.39 | N2: 0 | O2: 606372.9 | P2: 702899.44 | Q2: 805853.28 | R2: 915109.06 | S2: 1030541.4 | T2: 1152024.9 | U2: 1279434.3 | V2: 1412652.4 | W2: 1551562.4 | X2: 1696055.5 | Y2: 1846014.7 | Z2: 2001331.4 | AA2: 606372.9 | AB2: 2161897 | AC2: 2327611.1 | AD2: 2498365 | AE2: 2674058.5 | AF2: 2854599.7 | AG2: 3039888.2 | AH2: 3229832.1 | AI2: 3424331.1 | AJ2: 3623301.7 | AK2: 3826651.8 | AL2: 4034289.6 | AM2: 4246131.5 | AN2: 2161897 | AO2: 4462093.8 | AP2: 4682093.1 | AQ2: 4906054.1 | AR2: 5133893.2 | AS2: 5365535.1 | AT2: 5600904.8 | AU2: 5839926.8 | AV2: 6082526.2 | AW2: 6328627.5 | AX2: 6578163.9 | AY2: 6831068.6 | AZ2: 7087274.8 | BA2: 4462093.8 | BB2: 7346715.4 | BC2: 7609323.8 | BD2: 7875041.3 | BE2: 8143801.2 | BF2: 8415544.8 | BG2: 8690213.8 | BH2: 8967749.5 | BI2: 9248093.6 | BJ2: 9531187.4 | BK2: 9816980.8 | BL2: 10105415 | BM2: 10396441 | BN2: 7346715.4 | BO2: 10690007 | BP2: 10986064 | BQ2: 11284562 | BR2: 11585450 | BS2: 11888678 | BT2: 12194197 | BU2: 12501963 | BV2: 12811936 | BW2: 13124066 | BX2: 13438310 | BY2: 13754627 | BZ2: 14072975 | CA2: 10690007 | CB2: 14393312 | CC2: 14715596 | CD2: 15039795 | CE2: 15365865 | CF2: 15693775 | CG2: 16023481 | CH2: 16354951 | CI2: 16688151 | CJ2: 17023048 | CK2: 17359608 | CL2: 17697798 | CM2: 18037584 | CN2: 14393312 | CO2: 0
A3: Receita Líquida | B3: 8358 | C3: 16548.84 | D3: 24572.52 | E3: 32437.4 | F3: 40143.47 | G3: 47699.11 | H3: 55104.29 | I3: 62359.04 | J3: 69471.7 | K3: 76442.27 | L3: 83270.75 | M3: 89965.51 | N3: 606372.9 | O3: 96526.54 | P3: 102953.84 | Q3: 109255.78 | R3: 115432.34 | S3: 121483.53 | T3: 127409.35 | U3: 133218.16 | V3: 138909.96 | W3: 144493.1 | X3: 149959.24 | Y3: 155316.71 | Z3: 160565.54 | AA3: 1555524.1 | AB3: 165714.07 | AC3: 170753.94 | AD3: 175693.52 | AE3: 180541.16 | AF3: 185288.5 | AG3: 189943.91 | AH3: 194499.02 | AI3: 198970.55 | AJ3: 203350.14 | AK3: 207637.79 | AL3: 211841.87 | AM3: 215962.36 | AN3: 2300196.8 | AO3: 219999.28 | AP3: 223960.97 | AQ3: 227839.08 | AR3: 231641.97 | AS3: 235369.64 | AT3: 239022.08 | AU3: 242599.31 | AV3: 246101.31 | AW3: 249536.45 | AX3: 252904.72 | AY3: 256206.13 | AZ3: 259440.68 | BA3: 2884621.6 | BB3: 262608.36 | BC3: 265717.54 | BD3: 268759.85 | BE3: 271743.65 | BF3: 274668.95 | BG3: 277535.75 | BH3: 280344.04 | BI3: 283093.82 | BJ3: 285793.45 | BK3: 288434.58 | BL3: 291025.56 | BM3: 293566.39 | BN3: 3343291.9 | BO3: 296057.08 | BP3: 298497.61 | BQ3: 300888 | BR3: 303228.24 | BS3: 305518.33 | BT3: 307766.63 | BU3: 309973.15 | BV3: 312129.51 | BW3: 314244.08 | BX3: 316316.87 | BY3: 318347.86 | BZ3: 320337.07 | CA3: 3703304.4 | CB3: 322284.48 | CC3: 324198.46 | CD3: 326070.65 | CE3: 327909.41 | CF3: 329706.38 | CG3: 331469.92 | CH3: 333200.03 | CI3: 334896.7 | CJ3: 336559.94 | CK3: 338189.75 | CL3: 339786.13 | CM3: 341349.08 | CN3: 3985620.9 | CO3: 18378933
A4: Receita de fechamento | B4: 8358 | C4: 24906.84 | D4: 49479.36 | E4: 81916.76 | F4: 122060.23 | G4: 169759.34 | H4: 224863.63 | I4: 287222.67 | J4: 356694.37 | K4: 433136.64 | L4: 516407.39 | M4: 606372.9 | N4: 606372.9 | O4: 702899.44 | P4: 805853.28 | Q4: 915109.06 | R4: 1030541.4 | S4: 1152024.9 | T4: 1279434.3 | U4: 1412652.4 | V4: 1551562.4 | W4: 1696055.5 | X4: 1846014.7 | Y4: 2001331.4 | Z4: 2161897 | AA4: 2161897 | AB4: 2327611.1 | AC4: 2498365 | AD4: 2674058.5 | AE4: 2854599.7 | AF4: 3039888.2 | AG4: 3229832.1 | AH4: 3424331.1 | AI4: 3623301.7 | AJ4: 3826651.8 | AK4: 4034289.6 | AL4: 4246131.5 | AM4: 4462093.8 | AN4: 4462093.8 | AO4: 4682093.1 | AP4: 4906054.1 | AQ4: 5133893.2 | AR4: 5365535.1 | AS4: 5600904.8 | AT4: 5839926.8 | AU4: 6082526.2 | AV4: 6328627.5 | AW4: 6578163.9 | AX4: 6831068.6 | AY4: 7087274.8 | AZ4: 7346715.4 | BA4: 7346715.4 | BB4: 7609323.8 | BC4: 7875041.3 | BD4: 8143801.2 | BE4: 8415544.8 | BF4: 8690213.8 | BG4: 8967749.5 | BH4: 9248093.6 | BI4: 9531187.4 | BJ4: 9816980.8 | BK4: 10105415 | BL4: 10396441 | BM4: 10690007 | BN4: 10690007 | BO4: 10986064 | BP4: 11284562 | BQ4: 11585450 | BR4: 11888678 | BS4: 12194197 | BT4: 12501963 | BU4: 12811936 | BV4: 13124066 | BW4: 13438310 | BX4: 13754627 | BY4: 14072975 | BZ4: 14393312 | CA4: 14393312 | CB4: 14715596 | CC4: 15039795 | CD4: 15365865 | CE4: 15693775 | CF4: 16023481 | CG4: 16354951 | CH4: 16688151 | CI4: 17023048 | CJ4: 17359608 | CK4: 17697798 | CL4: 18037584 | CM4: 18378933 | CN4: 18378933 | CO4: 18378933
A6: Despesa Inicial | B6: 0 | C6: 35290 | D6: 73040.8 | E6: 113200.2 | F6: 155721.51 | G6: 201579.04 | H6: 250838.61 | I6: 304433.04 | J6: 361294.15 | K6: 421358.27 | L6: 484561.73 | M6: 550839.86 | N6: 0 | O6: 620132.5 | P6: 707007.49 | Q6: 796712.67 | R6: 889192.39 | S6: 984392 | T6: 1082255.9 | U6: 1182729.3 | V6: 1285760.2 | W6: 1391297.4 | X6: 1499293.3 | Y6: 1609695.7 | Z6: 1722457 | AA6: 620132.5 | AB6: 1837529.6 | AC6: 1964176.4 | AD6: 2092992.7 | AE6: 2229810.4 | AF6: 2368713.9 | AG6: 2509660.1 | AH6: 2652609.4 | AI6: 2797518.6 | AJ6: 2944352.6 | AK6: 3093070.9 | AL6: 3243633.9 | AM6: 3396006.3 | AN6: 1837529.6 | AO6: 3550152.2 | AP6: 3710856.2 | AQ6: 3873419.2 | AR6: 4041361.8 | AS6: 4210903.4 | AT6: 4382011.5 | AU6: 4554654.5 | AV6: 4728800.8 | AW6: 4904419.7 | AX6: 5081482.3 | AY6: 5259960.4 | AZ6: 5443453.9 | BA6: 3550152.2 | BB6: 5628306.8 | BC6: 5819080 | BD6: 6024414.8 | BE6: 6231150.4 | BF6: 6439259.2 | BG6: 6648714.8 | BH6: 6859489.6 | BI6: 7071557.2 | BJ6: 7284891.2 | BK6: 7499467.8 | BL6: 7715259.6 | BM6: 7935994.1 | BN6: 5628306.8 | BO6: 8143425.8 | BP6: 8356853 | BQ6: 8571270.2 | BR6: 8786656.2 | BS6: 9002990 | BT6: 9220252.5 | BU6: 9438426.2 | BV6: 9657494.6 | BW6: 9877436.6 | BX6: 10098236 | BY6: 10319875 | BZ6: 10542337 | CA6: 8143425.8 | CB6: 10765606 | CC6: 10996933 | CD6: 11229025 | CE6: 11461868 | CF6: 11695446 | CG6: 11929743 | CH6: 12164746 | CI6: 12400443 | CJ6: 12636818 | CK6: 12877487 | CL6: 13121056 | CM6: 13365264 | CN6: 10765606 | CO6: 0
A7: Despesa Líquida | B7: 35290 | C7: 37750.8 | D7: 40159.4 | E7: 42521.31 | F7: 45857.53 | G7: 49259.57 | H7: 53594.43 | I7: 56861.11 | J7: 60064.12 | K7: 63203.46 | L7: 66278.13 | M7: 69292.64 | N7: 620132.5 | O7: 86874.99 | P7: 89705.18 | Q7: 92479.72 | R7: 95199.61 | S7: 97863.85 | T7: 100473.44 | U7: 103030.89 | V7: 105537.2 | W7: 107995.88 | X7: 110402.42 | Y7: 112761.33 | Z7: 115072.61 | AA7: 1217397.1 | AB7: 126646.77 | AC7: 128816.3 | AD7: 136817.71 | AE7: 138903.51 | AF7: 140946.19 | AG7: 142949.26 | AH7: 144909.21 | AI7: 146834.06 | AJ7: 148718.3 | AK7: 150562.93 | AL7: 152372.46 | AM7: 154145.89 | AN7: 1712622.6 | AO7: 160704.02 | AP7: 162562.96 | AQ7: 167942.6 | AR7: 169541.65 | AS7: 171108.11 | AT7: 172642.98 | AU7: 174146.26 | AV7: 175618.95 | AW7: 177062.56 | AX7: 178478.09 | AY7: 183493.54 | AZ7: 184852.91 | BA7: 2078154.6 | BB7: 190773.2 | BC7: 205334.8 | BD7: 206735.55 | BE7: 208108.81 | BF7: 209455.58 | BG7: 210774.85 | BH7: 212067.62 | BI7: 213333.9 | BJ7: 214576.61 | BK7: 215791.83 | BL7: 220734.48 | BM7: 207431.74 | BN7: 2515119 | BO7: 213427.22 | BP7: 214417.14 | BQ7: 215386 | BR7: 216333.8 | BS7: 217262.54 | BT7: 218173.73 | BU7: 219068.37 | BV7: 219941.95 | BW7: 220798.98 | BX7: 221639.46 | BY7: 222462.39 | BZ7: 223268.77 | CA7: 2622180.4 | CB7: 231326.6 | CC7: 232092.39 | CD7: 232842.63 | CE7: 233577.83 | CF7: 234297.48 | CG7: 235003.09 | CH7: 235696.66 | CI7: 236375.19 | CJ7: 240668.68 | CK7: 243569.13 | CL7: 244208.54 | CM7: 244833.91 | CN7: 2844492.1 | CO7: 13610098
A8: Despesa de Fechamento | B8: 35290 | C8: 73040.8 | D8: 113200.2 | E8: 155721.51 | F8: 201579.04 | G8: 250838.61 | H8: 304433.04 | I8: 361294.15 | J8: 421358.27 | K8: 484561.73 | L8: 550839.86 | M8: 620132.5 | N8: 620132.5 | O8: 707007.49 | P8: 796712.67 | Q8: 889192.39 | R8: 984392 | S8: 1082255.9 | T8: 1182729.3 | U8: 1285760.2 | V8: 1391297.4 | W8: 1499293.3 | X8: 1609695.7 | Y8: 1722457 | Z8: 1837529.6 | AA8: 1837529.6 | AB8: 1964176.4 | AC8: 2092992.7 | AD8: 2229810.4 | AE8: 2368713.9 | AF8: 2509660.1 | AG8: 2652609.4 | AH8: 2797518.6 | AI8: 2944352.6 | AJ8: 3093070.9 | AK8: 3243633.9 | AL8: 3396006.3 | AM8: 3550152.2 | AN8: 3550152.2 | AO8: 3710856.2 | AP8: 3873419.2 | AQ8: 4041361.8 | AR8: 4210903.4 | AS8: 4382011.5 | AT8: 4554654.5 | AU8: 4728800.8 | AV8: 4904419.7 | AW8: 5081482.3 | AX8: 5259960.4 | AY8: 5443453.9 | AZ8: 5628306.8 | BA8: 5628306.8 | BB8: 5819080 | BC8: 6024414.8 | BD8: 6231150.4 | BE8: 6439259.2 | BF8: 6648714.8 | BG8: 6859489.6 | BH8: 7071557.2 | BI8: 7284891.2 | BJ8: 7499467.8 | BK8: 7715259.6 | BL8: 7935994.1 | BM8: 8143425.8 | BN8: 8143425.8 | BO8: 8356853 | BP8: 8571270.2 | BQ8: 8786656.2 | BR8: 9002990 | BS8: 9220252.5 | BT8: 9438426.2 | BU8: 9657494.6 | BV8: 9877436.6 | BW8: 10098236 | BX8: 10319875 | BY8: 10542337 | BZ8: 10765606 | CA8: 10765606 | CB8: 10996933 | CC8: 11229025 | CD8: 11461868 | CE8: 11695446 | CF8: 11929743 | CG8: 12164746 | CH8: 12400443 | CI8: 12636818 | CJ8: 12877487 | CK8: 13121056 | CL8: 13365264 | CM8: 13610098 | CN8: 13610098 | CO8: 13610098
A10: O ponto de equilíbrio é? | B10: Não | C10: Não | D10: Não | E10: Não | F10: Não | G10: Não | H10: Não | I10: Não | J10: Não | K10: Não | L10: Não | M10: Não | N10: Não | O10: Não | P10: Sim | Q10: Sim | R10: Sim | S10: Sim | T10: Sim | U10: Sim | V10: Sim | W10: Sim | X10: Sim | Y10: Sim | Z10: Sim | AA10: Sim | AB10: Sim | AC10: Sim | AD10: Sim | AE10: Sim | AF10: Sim | AG10: Sim | AH10: Sim | AI10: Sim | AJ10: Sim | AK10: Sim | AL10: Sim | AM10: Sim | AN10: Sim | AO10: Sim | AP10: Sim | AQ10: Sim | AR10: Sim | AS10: Sim | AT10: Sim | AU10: Sim | AV10: Sim | AW10: Sim | AX10: Sim | AY10: Sim | AZ10: Sim | BA10: Sim | BB10: Sim | BC10: Sim | BD10: Sim | BE10: Sim | BF10: Sim | BG10: Sim | BH10: Sim | BI10: Sim | BJ10: Sim | BK10: Sim | BL10: Sim | BM10: Sim | BN10: Sim | BO10: Sim | BP10: Sim | BQ10: Sim | BR10: Sim | BS10: Sim | BT10: Sim | BU10: Sim | BV10: Sim | BW10: Sim | BX10: Sim | BY10: Sim | BZ10: Sim | CA10: Sim | CB10: Sim | CC10: Sim | CD10: Sim | CE10: Sim | CF10: Sim | CG10: Sim | CH10: Sim | CI10: Sim | CJ10: Sim | CK10: Sim | CL10: Sim | CM10: Sim | CN10: Sim | CO10: Sim
A11: Mês do Ponto de Equilíbrio | B11: 0 | C11: 0 | D11: 0 | E11: 0 | F11: 0 | G11: 0 | H11: 0 | I11: 0 | J11: 0 | K11: 0 | L11: 0 | M11: 0 | N11: 0 | O11: 0 | P11: Feb '27 | Q11: 0 | R11: 0 | S11: 0 | T11: 0 | U11: 0 | V11: 0 | W11: 0 | X11: 0 | Y11: 0 | Z11: 0 | AA11: Feb '27 | AB11: 0 | AC11: 0 | AD11: 0 | AE11: 0 | AF11: 0 | AG11: 0 | AH11: 0 | AI11: 0 | AJ11: 0 | AK11: 0 | AL11: 0 | AM11: 0 | AN11: 0 | AO11: 0 | AP11: 0 | AQ11: 0 | AR11: 0 | AS11: 0 | AT11: 0 | AU11: 0 | AV11: 0 | AW11: 0 | AX11: 0 | AY11: 0 | AZ11: 0 | BA11: 0 | BB11: 0 | BC11: 0 | BD11: 0 | BE11: 0 | BF11: 0 | BG11: 0 | BH11: 0 | BI11: 0 | BJ11: 0 | BK11: 0 | BL11: 0 | BM11: 0 | BN11: 0 | BO11: 0 | BP11: 0 | BQ11: 0 | BR11: 0 | BS11: 0 | BT11: 0 | BU11: 0 | BV11: 0 | BW11: 0 | BX11: 0 | BY11: 0 | BZ11: 0 | CA11: 0 | CB11: 0 | CC11: 0 | CD11: 0 | CE11: 0 | CF11: 0 | CG11: 0 | CH11: 0 | CI11: 0 | CJ11: 0 | CK11: 0 | CL11: 0 | CM11: 0 | CN11: 0 | CO11: Feb '27
A12: Dias necessários | B12: 0 | C12: 0 | D12: 0 | E12: 0 | F12: 0 | G12: 0 | H12: 0 | I12: 0 | J12: 0 | K12: 0 | L12: 0 | M12: 0 | N12: 0 | O12: 0 | P12: 10 Dias | Q12: 0 | R12: 0 | S12: 0 | T12: 0 | U12: 0 | V12: 0 | W12: 0 | X12: 0 | Y12: 0 | Z12: 0 | AA12: 10 Dias | AB12: 0 | AC12: 0 | AD12: 0 | AE12: 0 | AF12: 0 | AG12: 0 | AH12: 0 | AI12: 0 | AJ12: 0 | AK12: 0 | AL12: 0 | AM12: 0 | AN12: 0 | AO12: 0 | AP12: 0 | AQ12: 0 | AR12: 0 | AS12: 0 | AT12: 0 | AU12: 0 | AV12: 0 | AW12: 0 | AX12: 0 | AY12: 0 | AZ12: 0 | BA12: 0 | BB12: 0 | BC12: 0 | BD12: 0 | BE12: 0 | BF12: 0 | BG12: 0 | BH12: 0 | BI12: 0 | BJ12: 0 | BK12: 0 | BL12: 0 | BM12: 0 | BN12: 0 | BO12: 0 | BP12: 0 | BQ12: 0 | BR12: 0 | BS12: 0 | BT12: 0 | BU12: 0 | BV12: 0 | BW12: 0 | BX12: 0 | BY12: 0 | BZ12: 0 | CA12: 0 | CB12: 0 | CC12: 0 | CD12: 0 | CE12: 0 | CF12: 0 | CG12: 0 | CH12: 0 | CI12: 0 | CJ12: 0 | CK12: 0 | CL12: 0 | CM12: 0 | CN12: 0 | CO12: 10 Dias
A13: Receita de equilíbrio | B13: 35290 | C13: 73040.8 | D13: 113200.2 | E13: 155721.51 | F13: 201579.04 | G13: 250838.61 | H13: 304433.04 | I13: 361294.15 | J13: 421358.27 | K13: 484561.73 | L13: 550839.86 | M13: 620132.5 | N13: 620132.5 | O13: 707007.49 | P13: 737217.39 | Q13: 0 | R13: 0 | S13: 0 | T13: 0 | U13: 0 | V13: 0 | W13: 0 | X13: 0 | Y13: 0 | Z13: 0 | AA13: 737217.39 | AB13: 0 | AC13: 0 | AD13: 0 | AE13: 0 | AF13: 0 | AG13: 0 | AH13: 0 | AI13: 0 | AJ13: 0 | AK13: 0 | AL13: 0 | AM13: 0 | AN13: 0 | AO13: 0 | AP13: 0 | AQ13: 0 | AR13: 0 | AS13: 0 | AT13: 0 | AU13: 0 | AV13: 0 | AW13: 0 | AX13: 0 | AY13: 0 | AZ13: 0 | BA13: 0 | BB13: 0 | BC13: 0 | BD13: 0 | BE13: 0 | BF13: 0 | BG13: 0 | BH13: 0 | BI13: 0 | BJ13: 0 | BK13: 0 | BL13: 0 | BM13: 0 | BN13: 0 | BO13: 0 | BP13: 0 | BQ13: 0 | BR13: 0 | BS13: 0 | BT13: 0 | BU13: 0 | BV13: 0 | BW13: 0 | BX13: 0 | BY13: 0 | BZ13: 0 | CA13: 0 | CB13: 0 | CC13: 0 | CD13: 0 | CE13: 0 | CF13: 0 | CG13: 0 | CH13: 0 | CI13: 0 | CJ13: 0 | CK13: 0 | CL13: 0 | CM13: 0 | CN13: 0 | CO13: 737217.39
A14: Receita Fixa
A15: Mensalidade | B15: 0 | C15: 0 | D15: 0 | E15: 0 | F15: 0 | G15: 0 | H15: 0 | I15: 0 | J15: 0 | K15: 0 | L15: 0 | M15: 0 | N15: 0 | O15: 0 | P15: 526583.85 | Q15: 0 | R15: 0 | S15: 0 | T15: 0 | U15: 0 | V15: 0 | W15: 0 | X15: 0 | Y15: 0 | Z15: 0 | AA15: 526583.85 | AB15: 0 | AC15: 0 | AD15: 0 | AE15: 0 | AF15: 0 | AG15: 0 | AH15: 0 | AI15: 0 | AJ15: 0 | AK15: 0 | AL15: 0 | AM15: 0 | AN15: 0 | AO15: 0 | AP15: 0 | AQ15: 0 | AR15: 0 | AS15: 0 | AT15: 0 | AU15: 0 | AV15: 0 | AW15: 0 | AX15: 0 | AY15: 0 | AZ15: 0 | BA15: 0 | BB15: 0 | BC15: 0 | BD15: 0 | BE15: 0 | BF15: 0 | BG15: 0 | BH15: 0 | BI15: 0 | BJ15: 0 | BK15: 0 | BL15: 0 | BM15: 0 | BN15: 0 | BO15: 0 | BP15: 0 | BQ15: 0 | BR15: 0 | BS15: 0 | BT15: 0 | BU15: 0 | BV15: 0 | BW15: 0 | BX15: 0 | BY15: 0 | BZ15: 0 | CA15: 0 | CB15: 0 | CC15: 0 | CD15: 0 | CE15: 0 | CF15: 0 | CG15: 0 | CH15: 0 | CI15: 0 | CJ15: 0 | CK15: 0 | CL15: 0 | CM15: 0 | CN15: 0 | CO15: 526583.85
A16: Receita Variável
A17: Comissão sobre Vendas Recuperadas | B17: 0 | C17: 0 | D17: 0 | E17: 0 | F17: 0 | G17: 0 | H17: 0 | I17: 0 | J17: 0 | K17: 0 | L17: 0 | M17: 0 | N17: 0 | O17: 0 | P17: 210633.54 | Q17: 0 | R17: 0 | S17: 0 | T17: 0 | U17: 0 | V17: 0 | W17: 0 | X17: 0 | Y17: 0 | Z17: 0 | AA17: 210633.54 | AB17: 0 | AC17: 0 | AD17: 0 | AE17: 0 | AF17: 0 | AG17: 0 | AH17: 0 | AI17: 0 | AJ17: 0 | AK17: 0 | AL17: 0 | AM17: 0 | AN17: 0 | AO17: 0 | AP17: 0 | AQ17: 0 | AR17: 0 | AS17: 0 | AT17: 0 | AU17: 0 | AV17: 0 | AW17: 0 | AX17: 0 | AY17: 0 | AZ17: 0 | BA17: 0 | BB17: 0 | BC17: 0 | BD17: 0 | BE17: 0 | BF17: 0 | BG17: 0 | BH17: 0 | BI17: 0 | BJ17: 0 | BK17: 0 | BL17: 0 | BM17: 0 | BN17: 0 | BO17: 0 | BP17: 0 | BQ17: 0 | BR17: 0 | BS17: 0 | BT17: 0 | BU17: 0 | BV17: 0 | BW17: 0 | BX17: 0 | BY17: 0 | BZ17: 0 | CA17: 0 | CB17: 0 | CC17: 0 | CD17: 0 | CE17: 0 | CF17: 0 | CG17: 0 | CH17: 0 | CI17: 0 | CJ17: 0 | CK17: 0 | CL17: 0 | CM17: 0 | CN17: 0 | CO17: 210633.54
A18: Unidades de equilíbrio
A19: Receita Fixa
A20: Mensalidade | B20: 0 | C20: 0 | D20: 0 | E20: 0 | F20: 0 | G20: 0 | H20: 0 | I20: 0 | J20: 0 | K20: 0 | L20: 0 | M20: 0 | N20: 0 | O20: 0 | P20: 118.82 | Q20: 0 | R20: 0 | S20: 0 | T20: 0 | U20: 0 | V20: 0 | W20: 0 | X20: 0 | Y20: 0 | Z20: 0 | AA20: 118.82 | AB20: 0 | AC20: 0 | AD20: 0 | AE20: 0 | AF20: 0 | AG20: 0 | AH20: 0 | AI20: 0 | AJ20: 0 | AK20: 0 | AL20: 0 | AM20: 0 | AN20: 0 | AO20: 0 | AP20: 0 | AQ20: 0 | AR20: 0 | AS20: 0 | AT20: 0 | AU20: 0 | AV20: 0 | AW20: 0 | AX20: 0 | AY20: 0 | AZ20: 0 | BA20: 0 | BB20: 0 | BC20: 0 | BD20: 0 | BE20: 0 | BF20: 0 | BG20: 0 | BH20: 0 | BI20: 0 | BJ20: 0 | BK20: 0 | BL20: 0 | BM20: 0 | BN20: 0 | BO20: 0 | BP20: 0 | BQ20: 0 | BR20: 0 | BS20: 0 | BT20: 0 | BU20: 0 | BV20: 0 | BW20: 0 | BX20: 0 | BY20: 0 | BZ20: 0 | CA20: 0 | CB20: 0 | CC20: 0 | CD20: 0 | CE20: 0 | CF20: 0 | CG20: 0 | CH20: 0 | CI20: 0 | CJ20: 0 | CK20: 0 | CL20: 0 | CM20: 0 | CN20: 0 | CO20: 118.82
A21: Receita Variável
A22: Comissão sobre Vendas Recuperadas | B22: 0 | C22: 0 | D22: 0 | E22: 0 | F22: 0 | G22: 0 | H22: 0 | I22: 0 | J22: 0 | K22: 0 | L22: 0 | M22: 0 | N22: 0 | O22: 0 | P22: 118.82 | Q22: 0 | R22: 0 | S22: 0 | T22: 0 | U22: 0 | V22: 0 | W22: 0 | X22: 0 | Y22: 0 | Z22: 0 | AA22: 118.82 | AB22: 0 | AC22: 0 | AD22: 0 | AE22: 0 | AF22: 0 | AG22: 0 | AH22: 0 | AI22: 0 | AJ22: 0 | AK22: 0 | AL22: 0 | AM22: 0 | AN22: 0 | AO22: 0 | AP22: 0 | AQ22: 0 | AR22: 0 | AS22: 0 | AT22: 0 | AU22: 0 | AV22: 0 | AW22: 0 | AX22: 0 | AY22: 0 | AZ22: 0 | BA22: 0 | BB22: 0 | BC22: 0 | BD22: 0 | BE22: 0 | BF22: 0 | BG22: 0 | BH22: 0 | BI22: 0 | BJ22: 0 | BK22: 0 | BL22: 0 | BM22: 0 | BN22: 0 | BO22: 0 | BP22: 0 | BQ22: 0 | BR22: 0 | BS22: 0 | BT22: 0 | BU22: 0 | BV22: 0 | BW22: 0 | BX22: 0 | BY22: 0 | BZ22: 0 | CA22: 0 | CB22: 0 | CC22: 0 | CD22: 0 | CE22: 0 | CF22: 0 | CG22: 0 | CH22: 0 | CI22: 0 | CJ22: 0 | CK22: 0 | CL22: 0 | CM22: 0 | CN22: 0 | CO22: 118.82

Sheet Valores - Análise de Razão
B1: Jan '26 | C1: Feb '26 | D1: Mar '26 | E1: Apr '26 | F1: May '26 | G1: Jun '26 | H1: Jul '26 | I1: Aug '26 | J1: Sep '26 | K1: Oct '26 | L1: Nov '26 | M1: Dec '26 | N1: 2026 | O1: Jan '27 | P1: Feb '27 | Q1: Mar '27 | R1: Apr '27 | S1: May '27 | T1: Jun '27 | U1: Jul '27 | V1: Aug '27 | W1: Sep '27 | X1: Oct '27 | Y1: Nov '27 | Z1: Dec '27 | AA1: 2027 | AB1: Jan '28 | AC1: Feb '28 | AD1: Mar '28 | AE1: Apr '28 | AF1: May '28 | AG1: Jun '28 | AH1: Jul '28 | AI1: Aug '28 | AJ1: Sep '28 | AK1: Oct '28 | AL1: Nov '28 | AM1: Dec '28 | AN1: 2028 | AO1: Jan '29 | AP1: Feb '29 | AQ1: Mar '29 | AR1: Apr '29 | AS1: May '29 | AT1: Jun '29 | AU1: Jul '29 | AV1: Aug '29 | AW1: Sep '29 | AX1: Oct '29 | AY1: Nov '29 | AZ1: Dec '29 | BA1: 2029 | BB1: Jan '30 | BC1: Feb '30 | BD1: Mar '30 | BE1: Apr '30 | BF1: May '30 | BG1: Jun '30 | BH1: Jul '30 | BI1: Aug '30 | BJ1: Sep '30 | BK1: Oct '30 | BL1: Nov '30 | BM1: Dec '30 | BN1: 2030 | BO1: Jan '31 | BP1: Feb '31 | BQ1: Mar '31 | BR1: Apr '31 | BS1: May '31 | BT1: Jun '31 | BU1: Jul '31 | BV1: Aug '31 | BW1: Sep '31 | BX1: Oct '31 | BY1: Nov '31 | BZ1: Dec '31 | CA1: 2031 | CB1: Jan '32 | CC1: Feb '32 | CD1: Mar '32 | CE1: Apr '32 | CF1: May '32 | CG1: Jun '32 | CH1: Jul '32 | CI1: Aug '32 | CJ1: Sep '32 | CK1: Oct '32 | CL1: Nov '32 | CM1: Dec '32 | CN1: 2032 | CO1: total
A2: Índice de Liquidez
A3: Índice de liquidez corrente | B3: 0.77 | C3: 1.09 | D3: 1.65 | E3: 2.35 | F3: 3.03 | G3: 3.7 | H3: 4.33 | I3: 4.97 | J3: 5.61 | K3: 6.26 | L3: 6.91 | M3: 7.57 | N3: 7.57 | O3: 7.95 | P3: 8.16 | Q3: 8.38 | R3: 8.61 | S3: 8.85 | T3: 9.11 | U3: 9.37 | V3: 9.64 | W3: 9.49 | X3: 9.38 | Y3: 9.3 | Z3: 9.24 | AA3: 9.24 | AB3: 9.24 | AC3: 9.17 | AD3: 9.02 | AE3: 8.95 | AF3: 8.9 | AG3: 8.86 | AH3: 8.84 | AI3: 8.84 | AJ3: 8.85 | AK3: 8.87 | AL3: 8.91 | AM3: 8.95 | AN3: 8.95 | AO3: 9.09 | AP3: 9.11 | AQ3: 9.14 | AR3: 9.17 | AS3: 9.2 | AT3: 9.24 | AU3: 9.29 | AV3: 9.34 | AW3: 9.39 | AX3: 9.45 | AY3: 9.46 | AZ3: 9.5 | BA3: 9.5 | BB3: 9.83 | BC3: 9.48 | BD3: 9.67 | BE3: 9.86 | BF3: 10.06 | BG3: 10.27 | BH3: 10.48 | BI3: 10.69 | BJ3: 10.91 | BK3: 11.13 | BL3: 11.34 | BM3: 12.29 | BN3: 12.29 | BO3: 12.65 | BP3: 12.93 | BQ3: 13.21 | BR3: 13.5 | BS3: 13.79 | BT3: 14.08 | BU3: 14.38 | BV3: 14.68 | BW3: 14.99 | BX3: 15.29 | BY3: 15.6 | BZ3: 15.91 | CA3: 15.91 | CB3: 16.3 | CC3: 16.59 | CD3: 16.88 | CE3: 17.18 | CF3: 17.48 | CG3: 17.78 | CH3: 18.09 | CI3: 18.4 | CJ3: 18.65 | CK3: 18.92 | CL3: 19.21 | CM3: 19.51 | CN3: 19.51 | CO3: 19.51
A4: Razão Rápida | B4: 0.77 | C4: 1.09 | D4: 1.65 | E4: 2.35 | F4: 3.03 | G4: 3.7 | H4: 4.33 | I4: 4.97 | J4: 5.61 | K4: 6.26 | L4: 6.91 | M4: 7.57 | N4: 7.57 | O4: 7.95 | P4: 8.16 | Q4: 8.38 | R4: 8.61 | S4: 8.85 | T4: 9.11 | U4: 9.37 | V4: 9.64 | W4: 9.49 | X4: 9.38 | Y4: 9.3 | Z4: 9.24 | AA4: 9.24 | AB4: 9.24 | AC4: 9.17 | AD4: 9.02 | AE4: 8.95 | AF4: 8.9 | AG4: 8.86 | AH4: 8.84 | AI4: 8.84 | AJ4: 8.85 | AK4: 8.87 | AL4: 8.91 | AM4: 8.95 | AN4: 8.95 | AO4: 9.09 | AP4: 9.11 | AQ4: 9.14 | AR4: 9.17 | AS4: 9.2 | AT4: 9.24 | AU4: 9.29 | AV4: 9.34 | AW4: 9.39 | AX4: 9.45 | AY4: 9.46 | AZ4: 9.5 | BA4: 9.5 | BB4: 9.83 | BC4: 9.48 | BD4: 9.67 | BE4: 9.86 | BF4: 10.06 | BG4: 10.27 | BH4: 10.48 | BI4: 10.69 | BJ4: 10.91 | BK4: 11.13 | BL4: 11.34 | BM4: 12.29 | BN4: 12.29 | BO4: 12.65 | BP4: 12.93 | BQ4: 13.21 | BR4: 13.5 | BS4: 13.79 | BT4: 14.08 | BU4: 14.38 | BV4: 14.68 | BW4: 14.99 | BX4: 15.29 | BY4: 15.6 | BZ4: 15.91 | CA4: 15.91 | CB4: 16.3 | CC4: 16.59 | CD4: 16.88 | CE4: 17.18 | CF4: 17.48 | CG4: 17.78 | CH4: 18.09 | CI4: 18.4 | CJ4: 18.65 | CK4: 18.92 | CL4: 19.21 | CM4: 19.51 | CN4: 19.51 | CO4: 19.51
A5: Proporção de caixa | B5: 0.77 | C5: 1.09 | D5: 1.65 | E5: 2.35 | F5: 3.03 | G5: 3.7 | H5: 4.33 | I5: 4.97 | J5: 5.61 | K5: 6.26 | L5: 6.91 | M5: 7.57 | N5: 7.57 | O5: 7.95 | P5: 8.16 | Q5: 8.38 | R5: 8.61 | S5: 8.85 | T5: 9.11 | U5: 9.37 | V5: 9.64 | W5: 9.49 | X5: 9.38 | Y5: 9.3 | Z5: 9.24 | AA5: 9.24 | AB5: 9.24 | AC5: 9.17 | AD5: 9.02 | AE5: 8.95 | AF5: 8.9 | AG5: 8.86 | AH5: 8.84 | AI5: 8.84 | AJ5: 8.85 | AK5: 8.87 | AL5: 8.91 | AM5: 8.95 | AN5: 8.95 | AO5: 9.09 | AP5: 9.11 | AQ5: 9.14 | AR5: 9.17 | AS5: 9.2 | AT5: 9.24 | AU5: 9.29 | AV5: 9.34 | AW5: 9.39 | AX5: 9.45 | AY5: 9.46 | AZ5: 9.5 | BA5: 9.5 | BB5: 9.83 | BC5: 9.48 | BD5: 9.67 | BE5: 9.86 | BF5: 10.06 | BG5: 10.27 | BH5: 10.48 | BI5: 10.69 | BJ5: 10.91 | BK5: 11.13 | BL5: 11.34 | BM5: 12.29 | BN5: 12.29 | BO5: 12.65 | BP5: 12.93 | BQ5: 13.21 | BR5: 13.5 | BS5: 13.79 | BT5: 14.08 | BU5: 14.38 | BV5: 14.68 | BW5: 14.99 | BX5: 15.29 | BY5: 15.6 | BZ5: 15.91 | CA5: 15.91 | CB5: 16.3 | CC5: 16.59 | CD5: 16.88 | CE5: 17.18 | CF5: 17.48 | CG5: 17.78 | CH5: 18.09 | CI5: 18.4 | CJ5: 18.65 | CK5: 18.92 | CL5: 19.21 | CM5: 19.51 | CN5: 19.51 | CO5: 19.51
A7: Índice de lucratividade
A8: Razão de Margem
A9: Margem Bruta (%) | B9: 0.7 | C9: 0.7 | D9: 0.7 | E9: 0.7 | F9: 0.7 | G9: 0.7 | H9: 0.7 | I9: 0.7 | J9: 0.7 | K9: 0.7 | L9: 0.7 | M9: 0.7 | N9: 0.7 | O9: 0.7 | P9: 0.7 | Q9: 0.7 | R9: 0.7 | S9: 0.7 | T9: 0.7 | U9: 0.7 | V9: 0.7 | W9: 0.7 | X9: 0.7 | Y9: 0.7 | Z9: 0.7 | AA9: 0.7 | AB9: 0.7 | AC9: 0.7 | AD9: 0.7 | AE9: 0.7 | AF9: 0.7 | AG9: 0.7 | AH9: 0.7 | AI9: 0.7 | AJ9: 0.7 | AK9: 0.7 | AL9: 0.7 | AM9: 0.7 | AN9: 0.7 | AO9: 0.7 | AP9: 0.7 | AQ9: 0.7 | AR9: 0.7 | AS9: 0.7 | AT9: 0.7 | AU9: 0.7 | AV9: 0.7 | AW9: 0.7 | AX9: 0.7 | AY9: 0.7 | AZ9: 0.7 | BA9: 0.7 | BB9: 0.7 | BC9: 0.7 | BD9: 0.7 | BE9: 0.7 | BF9: 0.7 | BG9: 0.7 | BH9: 0.7 | BI9: 0.7 | BJ9: 0.7 | BK9: 0.7 | BL9: 0.7 | BM9: 0.7 | BN9: 0.7 | BO9: 0.7 | BP9: 0.7 | BQ9: 0.7 | BR9: 0.7 | BS9: 0.7 | BT9: 0.7 | BU9: 0.7 | BV9: 0.7 | BW9: 0.7 | BX9: 0.7 | BY9: 0.7 | BZ9: 0.7 | CA9: 0.7 | CB9: 0.7 | CC9: 0.7 | CD9: 0.7 | CE9: 0.7 | CF9: 0.7 | CG9: 0.7 | CH9: 0.7 | CI9: 0.7 | CJ9: 0.7 | CK9: 0.7 | CL9: 0.7 | CM9: 0.7 | CN9: 0.7 | CO9: 0.7
A10: Margem Operacional (%) | B10: -3.22 | C10: -1.28 | D10: -0.63 | E10: -0.31 | F10: -0.14 | G10: -0.03 | H10: 0.03 | I10: 0.09 | J10: 0.14 | K10: 0.17 | L10: 0.2 | M10: 0.23 | N10: -0.02 | O10: 0.1 | P10: 0.13 | Q10: 0.15 | R10: 0.18 | S10: 0.19 | T10: 0.21 | U10: 0.23 | V10: 0.24 | W10: 0.25 | X10: 0.26 | Y10: 0.27 | Z10: 0.28 | AA10: 0.22 | AB10: 0.24 | AC10: 0.25 | AD10: 0.22 | AE10: 0.23 | AF10: 0.24 | AG10: 0.25 | AH10: 0.25 | AI10: 0.26 | AJ10: 0.27 | AK10: 0.27 | AL10: 0.28 | AM10: 0.29 | AN10: 0.26 | AO10: 0.27 | AP10: 0.27 | AQ10: 0.26 | AR10: 0.27 | AS10: 0.27 | AT10: 0.28 | AU10: 0.28 | AV10: 0.29 | AW10: 0.29 | AX10: 0.29 | AY10: 0.28 | AZ10: 0.29 | BA10: 0.28 | BB10: 0.27 | BC10: 0.23 | BD10: 0.23 | BE10: 0.23 | BF10: 0.24 | BG10: 0.24 | BH10: 0.24 | BI10: 0.25 | BJ10: 0.25 | BK10: 0.25 | BL10: 0.24 | BM10: 0.29 | BN10: 0.25 | BO10: 0.28 | BP10: 0.28 | BQ10: 0.28 | BR10: 0.29 | BS10: 0.29 | BT10: 0.29 | BU10: 0.29 | BV10: 0.3 | BW10: 0.3 | BX10: 0.3 | BY10: 0.3 | BZ10: 0.3 | CA10: 0.29 | CB10: 0.28 | CC10: 0.28 | CD10: 0.29 | CE10: 0.29 | CF10: 0.29 | CG10: 0.29 | CH10: 0.29 | CI10: 0.29 | CJ10: 0.28 | CK10: 0.28 | CL10: 0.28 | CM10: 0.28 | CN10: 0.29 | CO10: 0.26
A11: Margem antes dos impostos (%) | B11: -3.22 | C11: -1.28 | D11: -0.63 | E11: -0.31 | F11: -0.14 | G11: -0.03 | H11: 0.03 | I11: 0.09 | J11: 0.14 | K11: 0.17 | L11: 0.2 | M11: 0.23 | N11: -0.02 | O11: 0.1 | P11: 0.13 | Q11: 0.15 | R11: 0.18 | S11: 0.19 | T11: 0.21 | U11: 0.23 | V11: 0.24 | W11: 0.25 | X11: 0.26 | Y11: 0.27 | Z11: 0.28 | AA11: 0.22 | AB11: 0.24 | AC11: 0.25 | AD11: 0.22 | AE11: 0.23 | AF11: 0.24 | AG11: 0.25 | AH11: 0.25 | AI11: 0.26 | AJ11: 0.27 | AK11: 0.27 | AL11: 0.28 | AM11: 0.29 | AN11: 0.26 | AO11: 0.27 | AP11: 0.27 | AQ11: 0.26 | AR11: 0.27 | AS11: 0.27 | AT11: 0.28 | AU11: 0.28 | AV11: 0.29 | AW11: 0.29 | AX11: 0.29 | AY11: 0.28 | AZ11: 0.29 | BA11: 0.28 | BB11: 0.27 | BC11: 0.23 | BD11: 0.23 | BE11: 0.23 | BF11: 0.24 | BG11: 0.24 | BH11: 0.24 | BI11: 0.25 | BJ11: 0.25 | BK11: 0.25 | BL11: 0.24 | BM11: 0.29 | BN11: 0.25 | BO11: 0.28 | BP11: 0.28 | BQ11: 0.28 | BR11: 0.29 | BS11: 0.29 | BT11: 0.29 | BU11: 0.29 | BV11: 0.3 | BW11: 0.3 | BX11: 0.3 | BY11: 0.3 | BZ11: 0.3 | CA11: 0.29 | CB11: 0.28 | CC11: 0.28 | CD11: 0.29 | CE11: 0.29 | CF11: 0.29 | CG11: 0.29 | CH11: 0.29 | CI11: 0.29 | CJ11: 0.28 | CK11: 0.28 | CL11: 0.28 | CM11: 0.28 | CN11: 0.29 | CO11: 0.26
A12: Margem de lucro líquido (%) | B12: -3.22 | C12: -1.28 | D12: -0.63 | E12: -0.31 | F12: -0.14 | G12: -0.03 | H12: 0.03 | I12: 0.09 | J12: 0.14 | K12: 0.17 | L12: 0.2 | M12: 0.23 | N12: -0.02 | O12: 0.1 | P12: 0.13 | Q12: 0.15 | R12: 0.18 | S12: 0.19 | T12: 0.21 | U12: 0.23 | V12: 0.24 | W12: 0.25 | X12: 0.26 | Y12: 0.27 | Z12: 0.28 | AA12: 0.22 | AB12: 0.24 | AC12: 0.25 | AD12: 0.22 | AE12: 0.23 | AF12: 0.24 | AG12: 0.25 | AH12: 0.25 | AI12: 0.26 | AJ12: 0.27 | AK12: 0.27 | AL12: 0.28 | AM12: 0.29 | AN12: 0.26 | AO12: 0.27 | AP12: 0.27 | AQ12: 0.26 | AR12: 0.27 | AS12: 0.27 | AT12: 0.28 | AU12: 0.28 | AV12: 0.29 | AW12: 0.29 | AX12: 0.29 | AY12: 0.28 | AZ12: 0.29 | BA12: 0.28 | BB12: 0.27 | BC12: 0.23 | BD12: 0.23 | BE12: 0.23 | BF12: 0.24 | BG12: 0.24 | BH12: 0.24 | BI12: 0.25 | BJ12: 0.25 | BK12: 0.25 | BL12: 0.24 | BM12: 0.29 | BN12: 0.25 | BO12: 0.28 | BP12: 0.28 | BQ12: 0.28 | BR12: 0.29 | BS12: 0.29 | BT12: 0.29 | BU12: 0.29 | BV12: 0.3 | BW12: 0.3 | BX12: 0.3 | BY12: 0.3 | BZ12: 0.3 | CA12: 0.29 | CB12: 0.28 | CC12: 0.28 | CD12: 0.29 | CE12: 0.29 | CF12: 0.29 | CG12: 0.29 | CH12: 0.29 | CI12: 0.29 | CJ12: 0.28 | CK12: 0.28 | CL12: 0.28 | CM12: 0.28 | CN12: 0.29 | CO12: 0.26
A13: Margem de Fluxo de Caixa (%) | B13: -2.09 | C13: -1.13 | D13: -0.53 | E13: -0.24 | F13: -0.07 | G13: 0.03 | H13: 0.08 | I13: 0.13 | J13: 0.17 | K13: 0.21 | L13: 0.24 | M13: 0.26 | N13: 0.04 | O13: 0.12 | P13: 0.15 | Q13: 0.18 | R13: 0.2 | S13: 0.21 | T13: 0.23 | U13: 0.24 | V13: 0.26 | W13: 0.27 | X13: 0.28 | Y13: 0.29 | Z13: 0.3 | AA13: 0.23 | AB13: 0.24 | AC13: 0.26 | AD13: 0.23 | AE13: 0.24 | AF13: 0.25 | AG13: 0.26 | AH13: 0.26 | AI13: 0.27 | AJ13: 0.28 | AK13: 0.28 | AL13: 0.29 | AM13: 0.29 | AN13: 0.26 | AO13: 0.27 | AP13: 0.28 | AQ13: 0.27 | AR13: 0.27 | AS13: 0.28 | AT13: 0.28 | AU13: 0.29 | AV13: 0.29 | AW13: 0.3 | AX13: 0.3 | AY13: 0.29 | AZ13: 0.29 | BA13: 0.28 | BB13: 0.27 | BC13: 0.26 | BD13: 0.24 | BE13: 0.24 | BF13: 0.24 | BG13: 0.24 | BH13: 0.25 | BI13: 0.25 | BJ13: 0.25 | BK13: 0.26 | BL13: 0.25 | BM13: 0.27 | BN13: 0.25 | BO13: 0.28 | BP13: 0.28 | BQ13: 0.29 | BR13: 0.29 | BS13: 0.29 | BT13: 0.29 | BU13: 0.3 | BV13: 0.3 | BW13: 0.3 | BX13: 0.3 | BY13: 0.3 | BZ13: 0.31 | CA13: 0.29 | CB13: 0.28 | CC13: 0.29 | CD13: 0.29 | CE13: 0.29 | CF13: 0.29 | CG13: 0.29 | CH13: 0.29 | CI13: 0.3 | CJ13: 0.29 | CK13: 0.28 | CL13: 0.28 | CM13: 0.28 | CN13: 0.29 | CO13: 0.27
A14: Taxa de retorno
A15: Retorno sobre ativos (%) | B15: -3.69 | C15: -1.63 | D15: -0.65 | E15: -0.25 | F15: -0.1 | G15: -0.02 | H15: 0.01 | I15: 0.04 | J15: 0.05 | K15: 0.06 | L15: 0.07 | M15: 0.07 | N15: -0.05 | O15: 0.03 | P15: 0.04 | Q15: 0.04 | R15: 0.05 | S15: 0.05 | T15: 0.06 | U15: 0.06 | V15: 0.06 | W15: 0.06 | X15: 0.07 | Y15: 0.07 | Z15: 0.07 | AA15: 0.56 | AB15: 0.06 | AC15: 0.07 | AD15: 0.06 | AE15: 0.06 | AF15: 0.07 | AG15: 0.07 | AH15: 0.07 | AI15: 0.07 | AJ15: 0.08 | AK15: 0.08 | AL15: 0.08 | AM15: 0.08 | AN15: 0.76 | AO15: 0.08 | AP15: 0.08 | AQ15: 0.07 | AR15: 0.07 | AS15: 0.08 | AT15: 0.08 | AU15: 0.08 | AV15: 0.08 | AW15: 0.08 | AX15: 0.08 | AY15: 0.08 | AZ15: 0.08 | BA15: 0.84 | BB15: 0.07 | BC15: 0.06 | BD15: 0.06 | BE15: 0.06 | BF15: 0.06 | BG15: 0.06 | BH15: 0.06 | BI15: 0.06 | BJ15: 0.06 | BK15: 0.06 | BL15: 0.05 | BM15: 0.06 | BN15: 0.6 | BO15: 0.06 | BP15: 0.06 | BQ15: 0.06 | BR15: 0.06 | BS15: 0.06 | BT15: 0.05 | BU15: 0.05 | BV15: 0.05 | BW15: 0.05 | BX15: 0.05 | BY15: 0.05 | BZ15: 0.05 | CA15: 0.56 | CB15: 0.05 | CC15: 0.05 | CD15: 0.04 | CE15: 0.04 | CF15: 0.04 | CG15: 0.04 | CH15: 0.04 | CI15: 0.04 | CJ15: 0.04 | CK15: 0.04 | CL15: 0.04 | CM15: 0.04 | CN15: 0.45 | CO15: 1.9
A16: Retorno sobre o Patrimônio Líquido (%) | B16: 1 | C16: 0.56 | D16: 0.28 | E16: 0.15 | F16: 0.07 | G16: 0.02 | H16: -0.02 | I16: -0.07 | J16: -0.14 | K16: -0.23 | L16: -0.4 | M16: -0.86 | N16: 1 | O16: -1.22 | P16: 10.53 | Q16: 1.91 | R16: 1.12 | S16: 0.82 | T16: 0.65 | U16: 0.54 | V16: 0.47 | W16: 0.41 | X16: 0.37 | Y16: 0.33 | Z16: 0.3 | AA16: 4.56 | AB16: 0.23 | AC16: 0.22 | AD16: 0.18 | AE16: 0.18 | AF16: 0.17 | AG16: 0.17 | AH16: 0.16 | AI16: 0.16 | AJ16: 0.15 | AK16: 0.15 | AL16: 0.15 | AM16: 0.14 | AN16: 1.9 | AO16: 0.13 | AP16: 0.12 | AQ16: 0.11 | AR16: 0.11 | AS16: 0.11 | AT16: 0.11 | AU16: 0.1 | AV16: 0.1 | AW16: 0.1 | AX16: 0.1 | AY16: 0.09 | AZ16: 0.09 | BA16: 1.23 | BB16: 0.08 | BC16: 0.07 | BD16: 0.07 | BE16: 0.07 | BF16: 0.06 | BG16: 0.06 | BH16: 0.06 | BI16: 0.06 | BJ16: 0.06 | BK16: 0.06 | BL16: 0.06 | BM16: 0.07 | BN16: 0.78 | BO16: 0.06 | BP16: 0.06 | BQ16: 0.06 | BR16: 0.06 | BS16: 0.06 | BT16: 0.06 | BU16: 0.06 | BV16: 0.06 | BW16: 0.06 | BX16: 0.06 | BY16: 0.06 | BZ16: 0.05 | CA16: 0.7 | CB16: 0.05 | CC16: 0.05 | CD16: 0.05 | CE16: 0.05 | CF16: 0.05 | CG16: 0.05 | CH16: 0.05 | CI16: 0.05 | CJ16: 0.04 | CK16: 0.04 | CL16: 0.04 | CM16: 0.04 | CN16: 0.54 | CO16: 2
A17: Retorno sobre o capital empregado (%) | B17: 12.58 | C17: -20.58 | D17: -1.66 | E17: -0.44 | F17: -0.14 | G17: -0.03 | H17: 0.02 | I17: 0.05 | J17: 0.07 | K17: 0.07 | L17: 0.08 | M17: 0.08 | N17: -0.05 | O17: 0.03 | P17: 0.04 | Q17: 0.05 | R17: 0.05 | S17: 0.06 | T17: 0.06 | U17: 0.07 | V17: 0.07 | W17: 0.07 | X17: 0.08 | Y17: 0.08 | Z17: 0.08 | AA17: 0.62 | AB17: 0.07 | AC17: 0.07 | AD17: 0.07 | AE17: 0.07 | AF17: 0.08 | AG17: 0.08 | AH17: 0.08 | AI17: 0.08 | AJ17: 0.09 | AK17: 0.09 | AL17: 0.09 | AM17: 0.09 | AN17: 0.86 | AO17: 0.08 | AP17: 0.09 | AQ17: 0.08 | AR17: 0.08 | AS17: 0.08 | AT17: 0.09 | AU17: 0.09 | AV17: 0.09 | AW17: 0.09 | AX17: 0.09 | AY17: 0.09 | AZ17: 0.09 | BA17: 0.94 | BB17: 0.08 | BC17: 0.07 | BD17: 0.06 | BE17: 0.06 | BF17: 0.06 | BG17: 0.06 | BH17: 0.06 | BI17: 0.06 | BJ17: 0.06 | BK17: 0.06 | BL17: 0.06 | BM17: 0.07 | BN17: 0.65 | BO17: 0.06 | BP17: 0.06 | BQ17: 0.06 | BR17: 0.06 | BS17: 0.06 | BT17: 0.06 | BU17: 0.06 | BV17: 0.06 | BW17: 0.06 | BX17: 0.06 | BY17: 0.05 | BZ17: 0.05 | CA17: 0.6 | CB17: 0.05 | CC17: 0.05 | CD17: 0.05 | CE17: 0.05 | CF17: 0.05 | CG17: 0.05 | CH17: 0.05 | CI17: 0.04 | CJ17: 0.04 | CK17: 0.04 | CL17: 0.04 | CM17: 0.04 | CN17: 0.48 | CO17: 2
A19: Índice de Eficiência
A20: Índice de Rotatividade de Ativos | B20: 0 | C20: 0 | D20: 0 | E20: 0 | F20: 0 | G20: 0 | H20: 0 | I20: 0 | J20: 0 | K20: 0 | L20: 0 | M20: 0 | N20: 0 | O20: 0 | P20: 0 | Q20: 0 | R20: 0 | S20: 0 | T20: 0 | U20: 0 | V20: 0 | W20: 0 | X20: 0 | Y20: 0 | Z20: 0 | AA20: 0 | AB20: 0 | AC20: 0 | AD20: 0 | AE20: 0 | AF20: 0 | AG20: 0 | AH20: 0 | AI20: 0 | AJ20: 0 | AK20: 0 | AL20: 0 | AM20: 0 | AN20: 0 | AO20: 0 | AP20: 0 | AQ20: 0 | AR20: 0 | AS20: 0 | AT20: 0 | AU20: 0 | AV20: 0 | AW20: 0 | AX20: 0 | AY20: 0 | AZ20: 0 | BA20: 0 | BB20: 0 | BC20: 0 | BD20: 0 | BE20: 0 | BF20: 0 | BG20: 0 | BH20: 0 | BI20: 0 | BJ20: 0 | BK20: 0 | BL20: 0 | BM20: 0 | BN20: 0 | BO20: 0 | BP20: 0 | BQ20: 0 | BR20: 0 | BS20: 0 | BT20: 0 | BU20: 0 | BV20: 0 | BW20: 0 | BX20: 0 | BY20: 0 | BZ20: 0 | CA20: 0 | CB20: 0 | CC20: 0 | CD20: 0 | CE20: 0 | CF20: 0 | CG20: 0 | CH20: 0 | CI20: 0 | CJ20: 0 | CK20: 0 | CL20: 0 | CM20: 0 | CN20: 0 | CO20: 0
A21: Taxa de rotatividade de estoque | B21: 0 | C21: 0 | D21: 0 | E21: 0 | F21: 0 | G21: 0 | H21: 0 | I21: 0 | J21: 0 | K21: 0 | L21: 0 | M21: 0 | N21: 0 | O21: 0 | P21: 0 | Q21: 0 | R21: 0 | S21: 0 | T21: 0 | U21: 0 | V21: 0 | W21: 0 | X21: 0 | Y21: 0 | Z21: 0 | AA21: 0 | AB21: 0 | AC21: 0 | AD21: 0 | AE21: 0 | AF21: 0 | AG21: 0 | AH21: 0 | AI21: 0 | AJ21: 0 | AK21: 0 | AL21: 0 | AM21: 0 | AN21: 0 | AO21: 0 | AP21: 0 | AQ21: 0 | AR21: 0 | AS21: 0 | AT21: 0 | AU21: 0 | AV21: 0 | AW21: 0 | AX21: 0 | AY21: 0 | AZ21: 0 | BA21: 0 | BB21: 0 | BC21: 0 | BD21: 0 | BE21: 0 | BF21: 0 | BG21: 0 | BH21: 0 | BI21: 0 | BJ21: 0 | BK21: 0 | BL21: 0 | BM21: 0 | BN21: 0 | BO21: 0 | BP21: 0 | BQ21: 0 | BR21: 0 | BS21: 0 | BT21: 0 | BU21: 0 | BV21: 0 | BW21: 0 | BX21: 0 | BY21: 0 | BZ21: 0 | CA21: 0 | CB21: 0 | CC21: 0 | CD21: 0 | CE21: 0 | CF21: 0 | CG21: 0 | CH21: 0 | CI21: 0 | CJ21: 0 | CK21: 0 | CL21: 0 | CM21: 0 | CN21: 0 | CO21: 0
A22: Índice de rotatividade de contas a receber | B22: 0 | C22: 0 | D22: 0 | E22: 0 | F22: 0 | G22: 0 | H22: 0 | I22: 0 | J22: 0 | K22: 0 | L22: 0 | M22: 0 | N22: 0 | O22: 0 | P22: 0 | Q22: 0 | R22: 0 | S22: 0 | T22: 0 | U22: 0 | V22: 0 | W22: 0 | X22: 0 | Y22: 0 | Z22: 0 | AA22: 0 | AB22: 0 | AC22: 0 | AD22: 0 | AE22: 0 | AF22: 0 | AG22: 0 | AH22: 0 | AI22: 0 | AJ22: 0 | AK22: 0 | AL22: 0 | AM22: 0 | AN22: 0 | AO22: 0 | AP22: 0 | AQ22: 0 | AR22: 0 | AS22: 0 | AT22: 0 | AU22: 0 | AV22: 0 | AW22: 0 | AX22: 0 | AY22: 0 | AZ22: 0 | BA22: 0 | BB22: 0 | BC22: 0 | BD22: 0 | BE22: 0 | BF22: 0 | BG22: 0 | BH22: 0 | BI22: 0 | BJ22: 0 | BK22: 0 | BL22: 0 | BM22: 0 | BN22: 0 | BO22: 0 | BP22: 0 | BQ22: 0 | BR22: 0 | BS22: 0 | BT22: 0 | BU22: 0 | BV22: 0 | BW22: 0 | BX22: 0 | BY22: 0 | BZ22: 0 | CA22: 0 | CB22: 0 | CC22: 0 | CD22: 0 | CE22: 0 | CF22: 0 | CG22: 0 | CH22: 0 | CI22: 0 | CJ22: 0 | CK22: 0 | CL22: 0 | CM22: 0 | CN22: 0 | CO22: 0
A23: Índice de rotatividade de contas a pagar | B23: 4 | C23: 2.14 | D23: 2.12 | E23: 2.11 | F23: 2.13 | G23: 2.12 | H23: 2.1 | I23: 2.09 | J23: 2.08 | K23: 2.08 | L23: 2.07 | M23: 2.06 | N23: 31.3 | O23: 2.05 | P23: 2.05 | Q23: 2.05 | R23: 2.05 | S23: 2.04 | T23: 2.04 | U23: 2.04 | V23: 2.04 | W23: 2.03 | X23: 2.03 | Y23: 2.03 | Z23: 2.03 | AA23: 24.66 | AB23: 2.01 | AC23: 2.03 | AD23: 2.04 | AE23: 2.02 | AF23: 2.02 | AG23: 2.02 | AH23: 2.02 | AI23: 2.02 | AJ23: 2.02 | AK23: 2.02 | AL23: 2.02 | AM23: 2.02 | AN23: 24.25 | AO23: 1.99 | AP23: 2.02 | AQ23: 2.02 | AR23: 2.01 | AS23: 2.01 | AT23: 2.01 | AU23: 2.01 | AV23: 2.01 | AW23: 2.01 | AX23: 2.01 | AY23: 2.02 | AZ23: 2.01 | BA23: 23.96 | BB23: 1.99 | BC23: 2.12 | BD23: 2.01 | BE23: 2.01 | BF23: 2.01 | BG23: 2.01 | BH23: 2.01 | BI23: 2.01 | BJ23: 2.01 | BK23: 2.01 | BL23: 2.01 | BM23: 1.9 | BN23: 26.12 | BO23: 1.99 | BP23: 2.01 | BQ23: 2.01 | BR23: 2.01 | BS23: 2.01 | BT23: 2.01 | BU23: 2.01 | BV23: 2.01 | BW23: 2.01 | BX23: 2.01 | BY23: 2.01 | BZ23: 2.01 | CA23: 23.97 | CB23: 1.99 | CC23: 2.01 | CD23: 2.01 | CE23: 2.01 | CF23: 2.01 | CG23: 2 | CH23: 2 | CI23: 2 | CJ23: 2.01 | CK23: 2.01 | CL23: 2 | CM23: 2 | CN23: 23.93 | CO23: 232.66
A25: Taxa de cobertura
A26: Taxa de Cobertura de Juros | B26: 0 | C26: 0 | D26: 0 | E26: 0 | F26: 0 | G26: 0 | H26: 0 | I26: 0 | J26: 0 | K26: 0 | L26: 0 | M26: 0 | N26: 0 | O26: 0 | P26: 0 | Q26: 0 | R26: 0 | S26: 0 | T26: 0 | U26: 0 | V26: 0 | W26: 0 | X26: 0 | Y26: 0 | Z26: 0 | AA26: 0 | AB26: 0 | AC26: 0 | AD26: 0 | AE26: 0 | AF26: 0 | AG26: 0 | AH26: 0 | AI26: 0 | AJ26: 0 | AK26: 0 | AL26: 0 | AM26: 0 | AN26: 0 | AO26: 0 | AP26: 0 | AQ26: 0 | AR26: 0 | AS26: 0 | AT26: 0 | AU26: 0 | AV26: 0 | AW26: 0 | AX26: 0 | AY26: 0 | AZ26: 0 | BA26: 0 | BB26: 0 | BC26: 0 | BD26: 0 | BE26: 0 | BF26: 0 | BG26: 0 | BH26: 0 | BI26: 0 | BJ26: 0 | BK26: 0 | BL26: 0 | BM26: 0 | BN26: 0 | BO26: 0 | BP26: 0 | BQ26: 0 | BR26: 0 | BS26: 0 | BT26: 0 | BU26: 0 | BV26: 0 | BW26: 0 | BX26: 0 | BY26: 0 | BZ26: 0 | CA26: 0 | CB26: 0 | CC26: 0 | CD26: 0 | CE26: 0 | CF26: 0 | CG26: 0 | CH26: 0 | CI26: 0 | CJ26: 0 | CK26: 0 | CL26: 0 | CM26: 0 | CN26: 0 | CO26: 0
A27: Índice de cobertura do serviço da dívida | B27: -128.89 | C27: -33.82 | D27: -14.89 | E27: -6.88 | F27: -3.02 | G27: -0.68 | H27: 0.55 | I27: 1.76 | J27: 2.66 | K27: 3.34 | L27: 3.86 | M27: 4.27 | N27: -0.46 | O27: 1.83 | P27: 2.33 | Q27: 2.75 | R27: 3.1 | S27: 3.42 | T27: 3.68 | U27: 3.89 | V27: 4.09 | W27: 4.26 | X27: 4.4 | Y27: 4.51 | Z27: 4.64 | AA27: 3.73 | AB27: 3.83 | AC27: 3.95 | AD27: 3.52 | AE27: 3.63 | AF27: 3.71 | AG27: 3.78 | AH27: 3.88 | AI27: 3.96 | AJ27: 4.03 | AK27: 4.08 | AL27: 4.13 | AM27: 4.17 | AN27: 3.91 | AO27: 3.88 | AP27: 3.9 | AQ27: 3.7 | AR27: 3.69 | AS27: 3.67 | AT27: 3.64 | AU27: 3.61 | AV27: 3.58 | AW27: 3.53 | AX27: 3.49 | AY27: 3.28 | AZ27: 3.23 | BA27: 3.58 | BB27: 21.47 | BC27: 0 | BD27: 0 | BE27: 0 | BF27: 0 | BG27: 0 | BH27: 0 | BI27: 0 | BJ27: 0 | BK27: 0 | BL27: 0 | BM27: 0 | BN27: 247.49 | BO27: 0 | BP27: 0 | BQ27: 0 | BR27: 0 | BS27: 0 | BT27: 0 | BU27: 0 | BV27: 0 | BW27: 0 | BX27: 0 | BY27: 0 | BZ27: 0 | CA27: 0 | CB27: 0 | CC27: 0 | CD27: 0 | CE27: 0 | CF27: 0 | CG27: 0 | CH27: 0 | CI27: 0 | CJ27: 0 | CK27: 0 | CL27: 0 | CM27: 0 | CN27: 0 | CO27: 9.54
A28: Índice de Cobertura de Ativos | B28: -0.09 | C28: 0.02 | D28: 0.13 | E28: 0.24 | F28: 0.34 | G28: 0.43 | H28: 0.52 | I28: 0.6 | J28: 0.69 | K28: 0.78 | L28: 0.86 | M28: 0.95 | N28: 0.95 | O28: 0.99 | P28: 1.01 | Q28: 1.04 | R28: 1.07 | S28: 1.1 | T28: 1.13 | U28: 1.16 | V28: 1.19 | W28: 1.24 | X28: 1.3 | Y28: 1.36 | Z28: 1.43 | AA28: 1.43 | AB28: 1.49 | AC28: 1.57 | AD28: 1.64 | AE28: 1.72 | AF28: 1.82 | AG28: 1.93 | AH28: 2.05 | AI28: 2.19 | AJ28: 2.35 | AK28: 2.53 | AL28: 2.74 | AM28: 2.99 | AN28: 2.99 | AO28: 3.27 | AP28: 3.61 | AQ28: 4.01 | AR28: 4.5 | AS28: 5.14 | AT28: 5.98 | AU28: 7.14 | AV28: 8.87 | AW28: 11.7 | AX28: 17.16 | AY28: 32.11 | AZ28: 257.66 | BA28: 257.66 | BB28: 0 | BC28: 0 | BD28: 0 | BE28: 0 | BF28: 0 | BG28: 0 | BH28: 0 | BI28: 0 | BJ28: 0 | BK28: 0 | BL28: 0 | BM28: 0 | BN28: 0 | BO28: 0 | BP28: 0 | BQ28: 0 | BR28: 0 | BS28: 0 | BT28: 0 | BU28: 0 | BV28: 0 | BW28: 0 | BX28: 0 | BY28: 0 | BZ28: 0 | CA28: 0 | CB28: 0 | CC28: 0 | CD28: 0 | CE28: 0 | CF28: 0 | CG28: 0 | CH28: 0 | CI28: 0 | CJ28: 0 | CK28: 0 | CL28: 0 | CM28: 0 | CN28: 0 | CO28: 0
A30: Índice de Alavancagem
A31: Relação dívida/ativos | B31: 4.69 | C31: 4.7 | D31: 3.67 | E31: 2.86 | F31: 2.32 | G31: 1.96 | H31: 1.72 | I31: 1.53 | J31: 1.37 | K31: 1.24 | L31: 1.14 | M31: 1.05 | N31: 1.05 | O31: 1.01 | P31: 0.99 | Q31: 0.97 | R31: 0.94 | S31: 0.92 | T31: 0.9 | U31: 0.88 | V31: 0.86 | W31: 0.83 | X31: 0.8 | Y31: 0.76 | Z31: 0.73 | AA31: 0.73 | AB31: 0.71 | AC31: 0.68 | AD31: 0.65 | AE31: 0.63 | AF31: 0.6 | AG31: 0.57 | AH31: 0.55 | AI31: 0.52 | AJ31: 0.49 | AK31: 0.46 | AL31: 0.44 | AM31: 0.41 | AN31: 0.41 | AO31: 0.38 | AP31: 0.36 | AQ31: 0.33 | AR31: 0.31 | AS31: 0.28 | AT31: 0.26 | AU31: 0.23 | AV31: 0.21 | AW31: 0.18 | AX31: 0.16 | AY31: 0.13 | AZ31: 0.11 | BA31: 0.11 | BB31: 0.1 | BC31: 0.11 | BD31: 0.1 | BE31: 0.1 | BF31: 0.1 | BG31: 0.1 | BH31: 0.1 | BI31: 0.09 | BJ31: 0.09 | BK31: 0.09 | BL31: 0.09 | BM31: 0.08 | BN31: 0.08 | BO31: 0.08 | BP31: 0.08 | BQ31: 0.08 | BR31: 0.07 | BS31: 0.07 | BT31: 0.07 | BU31: 0.07 | BV31: 0.07 | BW31: 0.07 | BX31: 0.07 | BY31: 0.06 | BZ31: 0.06 | CA31: 0.06 | CB31: 0.06 | CC31: 0.06 | CD31: 0.06 | CE31: 0.06 | CF31: 0.06 | CG31: 0.06 | CH31: 0.06 | CI31: 0.05 | CJ31: 0.05 | CK31: 0.05 | CL31: 0.05 | CM31: 0.05 | CN31: 0.05 | CO31: 0.05
A32: Índice de Dívida/Patrimônio Líquido | B32: -1.27 | C32: -1.27 | D32: -1.37 | E32: -1.54 | F32: -1.76 | G32: -2.04 | H32: -2.39 | I32: -2.9 | J32: -3.7 | K32: -5.11 | L32: -8.31 | M32: -22.45 | N32: -22.45 | O32: -161.19 | P32: 77.2 | Q32: 28.87 | R32: 17.12 | S32: 11.91 | T32: 9 | U32: 7.17 | V32: 5.91 | W32: 4.75 | X32: 3.9 | Y32: 3.25 | Z32: 2.75 | AA32: 2.75 | AB32: 2.4 | AC32: 2.11 | AD32: 1.88 | AE32: 1.68 | AF32: 1.5 | AG32: 1.34 | AH32: 1.2 | AI32: 1.08 | AJ32: 0.96 | AK32: 0.86 | AL32: 0.77 | AM32: 0.69 | AN32: 0.69 | AO32: 0.62 | AP32: 0.55 | AQ32: 0.5 | AR32: 0.44 | AS32: 0.39 | AT32: 0.35 | AU32: 0.3 | AV32: 0.26 | AW32: 0.22 | AX32: 0.19 | AY32: 0.15 | AZ32: 0.12 | BA32: 0.12 | BB32: 0.11 | BC32: 0.12 | BD32: 0.12 | BE32: 0.11 | BF32: 0.11 | BG32: 0.11 | BH32: 0.11 | BI32: 0.1 | BJ32: 0.1 | BK32: 0.1 | BL32: 0.1 | BM32: 0.09 | BN32: 0.09 | BO32: 0.09 | BP32: 0.08 | BQ32: 0.08 | BR32: 0.08 | BS32: 0.08 | BT32: 0.08 | BU32: 0.07 | BV32: 0.07 | BW32: 0.07 | BX32: 0.07 | BY32: 0.07 | BZ32: 0.07 | CA32: 0.07 | CB32: 0.07 | CC32: 0.06 | CD32: 0.06 | CE32: 0.06 | CF32: 0.06 | CG32: 0.06 | CH32: 0.06 | CI32: 0.06 | CJ32: 0.06 | CK32: 0.06 | CL32: 0.05 | CM32: 0.05 | CN32: 0.05 | CO32: 0.05
A33: Relação dívida/capital | B33: 4.69 | C33: 4.7 | D33: 3.67 | E33: 2.86 | F33: 2.32 | G33: 1.96 | H33: 1.72 | I33: 1.53 | J33: 1.37 | K33: 1.24 | L33: 1.14 | M33: 1.05 | N33: 1.05 | O33: 1.01 | P33: 0.99 | Q33: 0.97 | R33: 0.94 | S33: 0.92 | T33: 0.9 | U33: 0.88 | V33: 0.86 | W33: 0.83 | X33: 0.8 | Y33: 0.76 | Z33: 0.73 | AA33: 0.73 | AB33: 0.71 | AC33: 0.68 | AD33: 0.65 | AE33: 0.63 | AF33: 0.6 | AG33: 0.57 | AH33: 0.55 | AI33: 0.52 | AJ33: 0.49 | AK33: 0.46 | AL33: 0.44 | AM33: 0.41 | AN33: 0.41 | AO33: 0.38 | AP33: 0.36 | AQ33: 0.33 | AR33: 0.31 | AS33: 0.28 | AT33: 0.26 | AU33: 0.23 | AV33: 0.21 | AW33: 0.18 | AX33: 0.16 | AY33: 0.13 | AZ33: 0.11 | BA33: 0.11 | BB33: 0.1 | BC33: 0.11 | BD33: 0.1 | BE33: 0.1 | BF33: 0.1 | BG33: 0.1 | BH33: 0.1 | BI33: 0.09 | BJ33: 0.09 | BK33: 0.09 | BL33: 0.09 | BM33: 0.08 | BN33: 0.08 | BO33: 0.08 | BP33: 0.08 | BQ33: 0.08 | BR33: 0.07 | BS33: 0.07 | BT33: 0.07 | BU33: 0.07 | BV33: 0.07 | BW33: 0.07 | BX33: 0.07 | BY33: 0.06 | BZ33: 0.06 | CA33: 0.06 | CB33: 0.06 | CC33: 0.06 | CD33: 0.06 | CE33: 0.06 | CF33: 0.06 | CG33: 0.06 | CH33: 0.06 | CI33: 0.05 | CJ33: 0.05 | CK33: 0.05 | CL33: 0.05 | CM33: 0.05 | CN33: 0.05 | CO33: 0.05
A34: Relação dívida/EBITDA | B34: -1.27 | C34: -2.88 | D34: -5.62 | E34: -11.26 | F34: -24.42 | G34: -105.84 | H34: 126.04 | I34: 39.1 | J34: 25.42 | K34: 19.86 | L34: 16.84 | M34: 14.94 | N34: -22.45 | O34: 34.29 | P34: 26.62 | Q34: 22.29 | R34: 19.51 | S34: 17.58 | T34: 16.15 | U34: 15.06 | V34: 14.19 | W34: 12.8 | X34: 11.64 | Y34: 10.64 | Z34: 9.78 | AA34: 1.32 | AB34: 11.16 | AC34: 10.19 | AD34: 10.76 | AE34: 9.82 | AF34: 8.99 | AG34: 8.26 | AH34: 7.6 | AI34: 7.01 | AJ34: 6.47 | AK34: 5.98 | AL34: 5.52 | AM34: 5.1 | AN34: 0.54 | AO34: 5.06 | AP34: 4.66 | AQ34: 4.53 | AR34: 4.12 | AS34: 3.73 | AT34: 3.35 | AU34: 3 | AV34: 2.65 | AW34: 2.31 | AX34: 1.98 | AY34: 1.74 | AZ34: 1.4 | BA34: 0.13 | BB34: 1.41 | BC34: 1.81 | BD34: 1.78 | BE34: 1.75 | BF34: 1.73 | BG34: 1.7 | BH34: 1.68 | BI34: 1.66 | BJ34: 1.64 | BK34: 1.62 | BL34: 1.69 | BM34: 1.31 | BN34: 0.14 | BO34: 1.36 | BP34: 1.35 | BQ34: 1.34 | BR34: 1.33 | BS34: 1.32 | BT34: 1.31 | BU34: 1.3 | BV34: 1.29 | BW34: 1.28 | BX34: 1.27 | BY34: 1.26 | BZ34: 1.25 | CA34: 0.11 | CB34: 1.34 | CC34: 1.33 | CD34: 1.32 | CE34: 1.31 | CF34: 1.3 | CG34: 1.29 | CH34: 1.29 | CI34: 1.28 | CJ34: 1.32 | CK34: 1.35 | CL34: 1.34 | CM34: 1.33 | CN34: 0.11 | CO34: 0.03
A35: Índice de Ativos para Patrimônio Líquido | B35: -0.27 | C35: -0.27 | D35: -0.37 | E35: -0.54 | F35: -0.76 | G35: -1.04 | H35: -1.39 | I35: -1.9 | J35: -2.7 | K35: -4.11 | L35: -7.31 | M35: -21.45 | N35: -21.45 | O35: -160.19 | P35: 78.2 | Q35: 29.87 | R35: 18.12 | S35: 12.91 | T35: 10 | U35: 8.17 | V35: 6.91 | W35: 5.75 | X35: 4.9 | Y35: 4.25 | Z35: 3.75 | AA35: 3.75 | AB35: 3.4 | AC35: 3.11 | AD35: 2.88 | AE35: 2.68 | AF35: 2.5 | AG35: 2.34 | AH35: 2.2 | AI35: 2.08 | AJ35: 1.96 | AK35: 1.86 | AL35: 1.77 | AM35: 1.69 | AN35: 1.69 | AO35: 1.62 | AP35: 1.55 | AQ35: 1.5 | AR35: 1.44 | AS35: 1.39 | AT35: 1.35 | AU35: 1.3 | AV35: 1.26 | AW35: 1.22 | AX35: 1.19 | AY35: 1.15 | AZ35: 1.12 | BA35: 1.12 | BB35: 1.11 | BC35: 1.12 | BD35: 1.12 | BE35: 1.11 | BF35: 1.11 | BG35: 1.11 | BH35: 1.11 | BI35: 1.1 | BJ35: 1.1 | BK35: 1.1 | BL35: 1.1 | BM35: 1.09 | BN35: 1.09 | BO35: 1.09 | BP35: 1.08 | BQ35: 1.08 | BR35: 1.08 | BS35: 1.08 | BT35: 1.08 | BU35: 1.07 | BV35: 1.07 | BW35: 1.07 | BX35: 1.07 | BY35: 1.07 | BZ35: 1.07 | CA35: 1.07 | CB35: 1.07 | CC35: 1.06 | CD35: 1.06 | CE35: 1.06 | CF35: 1.06 | CG35: 1.06 | CH35: 1.06 | CI35: 1.06 | CJ35: 1.06 | CK35: 1.06 | CL35: 1.05 | CM35: 1.05 | CN35: 1.05 | CO35: 1.05

Sheet Valores - Financiamento
B1: Jan '26 | C1: Feb '26 | D1: Mar '26 | E1: Apr '26 | F1: May '26 | G1: Jun '26 | H1: Jul '26 | I1: Aug '26 | J1: Sep '26 | K1: Oct '26 | L1: Nov '26 | M1: Dec '26 | N1: 2026 | O1: Jan '27 | P1: Feb '27 | Q1: Mar '27 | R1: Apr '27 | S1: May '27 | T1: Jun '27 | U1: Jul '27 | V1: Aug '27 | W1: Sep '27 | X1: Oct '27 | Y1: Nov '27 | Z1: Dec '27 | AA1: 2027 | AB1: Jan '28 | AC1: Feb '28 | AD1: Mar '28 | AE1: Apr '28 | AF1: May '28 | AG1: Jun '28 | AH1: Jul '28 | AI1: Aug '28 | AJ1: Sep '28 | AK1: Oct '28 | AL1: Nov '28 | AM1: Dec '28 | AN1: 2028 | AO1: Jan '29 | AP1: Feb '29 | AQ1: Mar '29 | AR1: Apr '29 | AS1: May '29 | AT1: Jun '29 | AU1: Jul '29 | AV1: Aug '29 | AW1: Sep '29 | AX1: Oct '29 | AY1: Nov '29 | AZ1: Dec '29 | BA1: 2029 | BB1: Jan '30 | BC1: Feb '30 | BD1: Mar '30 | BE1: Apr '30 | BF1: May '30 | BG1: Jun '30 | BH1: Jul '30 | BI1: Aug '30 | BJ1: Sep '30 | BK1: Oct '30 | BL1: Nov '30 | BM1: Dec '30 | BN1: 2030 | BO1: Jan '31 | BP1: Feb '31 | BQ1: Mar '31 | BR1: Apr '31 | BS1: May '31 | BT1: Jun '31 | BU1: Jul '31 | BV1: Aug '31 | BW1: Sep '31 | BX1: Oct '31 | BY1: Nov '31 | BZ1: Dec '31 | CA1: 2031 | CB1: Jan '32 | CC1: Feb '32 | CD1: Mar '32 | CE1: Apr '32 | CF1: May '32 | CG1: Jun '32 | CH1: Jul '32 | CI1: Aug '32 | CJ1: Sep '32 | CK1: Oct '32 | CL1: Nov '32 | CM1: Dec '32 | CN1: 2032 | CO1: total
A2: Valor recebido | B2: 25000 | C2: 25000 | D2: 25000 | E2: 25000 | F2: 25000 | G2: 25000 | H2: 25000 | I2: 25000 | J2: 25000 | K2: 25000 | L2: 25000 | M2: 25000 | N2: 300000 | O2: 25000 | P2: 25000 | Q2: 25000 | R2: 25000 | S2: 25000 | T2: 25000 | U2: 25000 | V2: 25000 | W2: 0 | X2: 0 | Y2: 0 | Z2: 0 | AA2: 200000 | AB2: 0 | AC2: 0 | AD2: 0 | AE2: 0 | AF2: 0 | AG2: 0 | AH2: 0 | AI2: 0 | AJ2: 0 | AK2: 0 | AL2: 0 | AM2: 0 | AN2: 0 | AO2: 0 | AP2: 0 | AQ2: 0 | AR2: 0 | AS2: 0 | AT2: 0 | AU2: 0 | AV2: 0 | AW2: 0 | AX2: 0 | AY2: 0 | AZ2: 0 | BA2: 0 | BB2: 0 | BC2: 0 | BD2: 0 | BE2: 0 | BF2: 0 | BG2: 0 | BH2: 0 | BI2: 0 | BJ2: 0 | BK2: 0 | BL2: 0 | BM2: 0 | BN2: 0 | BO2: 0 | BP2: 0 | BQ2: 0 | BR2: 0 | BS2: 0 | BT2: 0 | BU2: 0 | BV2: 0 | BW2: 0 | BX2: 0 | BY2: 0 | BZ2: 0 | CA2: 0 | CB2: 0 | CC2: 0 | CD2: 0 | CE2: 0 | CF2: 0 | CG2: 0 | CH2: 0 | CI2: 0 | CJ2: 0 | CK2: 0 | CL2: 0 | CM2: 0 | CN2: 0 | CO2: 500000
A3: Funding | B3: 25000 | C3: 25000 | D3: 25000 | E3: 25000 | F3: 25000 | G3: 25000 | H3: 25000 | I3: 25000 | J3: 25000 | K3: 25000 | L3: 25000 | M3: 25000 | N3: 300000 | O3: 25000 | P3: 25000 | Q3: 25000 | R3: 25000 | S3: 25000 | T3: 25000 | U3: 25000 | V3: 25000 | W3: 0 | X3: 0 | Y3: 0 | Z3: 0 | AA3: 200000 | AB3: 0 | AC3: 0 | AD3: 0 | AE3: 0 | AF3: 0 | AG3: 0 | AH3: 0 | AI3: 0 | AJ3: 0 | AK3: 0 | AL3: 0 | AM3: 0 | AN3: 0 | AO3: 0 | AP3: 0 | AQ3: 0 | AR3: 0 | AS3: 0 | AT3: 0 | AU3: 0 | AV3: 0 | AW3: 0 | AX3: 0 | AY3: 0 | AZ3: 0 | BA3: 0 | BB3: 0 | BC3: 0 | BD3: 0 | BE3: 0 | BF3: 0 | BG3: 0 | BH3: 0 | BI3: 0 | BJ3: 0 | BK3: 0 | BL3: 0 | BM3: 0 | BN3: 0 | BO3: 0 | BP3: 0 | BQ3: 0 | BR3: 0 | BS3: 0 | BT3: 0 | BU3: 0 | BV3: 0 | BW3: 0 | BX3: 0 | BY3: 0 | BZ3: 0 | CA3: 0 | CB3: 0 | CC3: 0 | CD3: 0 | CE3: 0 | CF3: 0 | CG3: 0 | CH3: 0 | CI3: 0 | CJ3: 0 | CK3: 0 | CL3: 0 | CM3: 0 | CN3: 0 | CO3: 500000
A4: Aporte Diego AM Engenharia | B4: 25000 | C4: 25000 | D4: 25000 | E4: 25000 | F4: 25000 | G4: 25000 | H4: 25000 | I4: 25000 | J4: 25000 | K4: 25000 | L4: 25000 | M4: 25000 | N4: 300000 | O4: 25000 | P4: 25000 | Q4: 25000 | R4: 25000 | S4: 25000 | T4: 25000 | U4: 25000 | V4: 25000 | W4: 0 | X4: 0 | Y4: 0 | Z4: 0 | AA4: 200000 | AB4: 0 | AC4: 0 | AD4: 0 | AE4: 0 | AF4: 0 | AG4: 0 | AH4: 0 | AI4: 0 | AJ4: 0 | AK4: 0 | AL4: 0 | AM4: 0 | AN4: 0 | AO4: 0 | AP4: 0 | AQ4: 0 | AR4: 0 | AS4: 0 | AT4: 0 | AU4: 0 | AV4: 0 | AW4: 0 | AX4: 0 | AY4: 0 | AZ4: 0 | BA4: 0 | BB4: 0 | BC4: 0 | BD4: 0 | BE4: 0 | BF4: 0 | BG4: 0 | BH4: 0 | BI4: 0 | BJ4: 0 | BK4: 0 | BL4: 0 | BM4: 0 | BN4: 0 | BO4: 0 | BP4: 0 | BQ4: 0 | BR4: 0 | BS4: 0 | BT4: 0 | BU4: 0 | BV4: 0 | BW4: 0 | BX4: 0 | BY4: 0 | BZ4: 0 | CA4: 0 | CB4: 0 | CC4: 0 | CD4: 0 | CE4: 0 | CF4: 0 | CG4: 0 | CH4: 0 | CI4: 0 | CJ4: 0 | CK4: 0 | CL4: 0 | CM4: 0 | CN4: 0 | CO4: 500000
A6: Valor pago | B6: 208.95 | C6: 626.85 | D6: 1046.84 | E6: 1465.58 | F6: 1890.58 | G6: 2306.39 | H6: 2721.37 | I6: 3129.65 | J6: 3536.69 | K6: 3961.27 | L6: 4397.14 | M6: 4836.77 | N6: 30128.08 | O6: 5272.23 | P6: 5693.89 | Q6: 6092.56 | R6: 6519.24 | S6: 6910.39 | T6: 7324.95 | U6: 7764.58 | V6: 8152.81 | W6: 8560.26 | X6: 8988.19 | Y6: 9437.44 | Z6: 9814.8 | AA6: 90531.34 | AB6: 10207.21 | AC6: 10615.5 | AD6: 11040.08 | AE6: 11481.8 | AF6: 11941.07 | AG6: 12418.73 | AH6: 12791.5 | AI6: 13175.13 | AJ6: 13570.47 | AK6: 13977.5 | AL6: 14396.66 | AM6: 14828.76 | AN6: 150444.41 | AO6: 15273.83 | AP6: 15731.85 | AQ6: 16203.65 | AR6: 16851.82 | AS6: 17525.89 | AT6: 18227.13 | AU6: 18956.36 | AV6: 19714.43 | AW6: 20503.01 | AX6: 21322.93 | AY6: 22175.86 | AZ6: 23063.07 | BA6: 225549.83 | BB6: 3346.34 | BC6: 0 | BD6: 0 | BE6: 0 | BF6: 0 | BG6: 0 | BH6: 0 | BI6: 0 | BJ6: 0 | BK6: 0 | BL6: 0 | BM6: 0 | BN6: 3346.34 | BO6: 0 | BP6: 0 | BQ6: 0 | BR6: 0 | BS6: 0 | BT6: 0 | BU6: 0 | BV6: 0 | BW6: 0 | BX6: 0 | BY6: 0 | BZ6: 0 | CA6: 0 | CB6: 0 | CC6: 0 | CD6: 0 | CE6: 0 | CF6: 0 | CG6: 0 | CH6: 0 | CI6: 0 | CJ6: 0 | CK6: 0 | CL6: 0 | CM6: 0 | CN6: 0 | CO6: 500000
A7: Funding | B7: 208.95 | C7: 626.85 | D7: 1046.84 | E7: 1465.58 | F7: 1890.58 | G7: 2306.39 | H7: 2721.37 | I7: 3129.65 | J7: 3536.69 | K7: 3961.27 | L7: 4397.14 | M7: 4836.77 | N7: 30128.08 | O7: 5272.23 | P7: 5693.89 | Q7: 6092.56 | R7: 6519.24 | S7: 6910.39 | T7: 7324.95 | U7: 7764.58 | V7: 8152.81 | W7: 8560.26 | X7: 8988.19 | Y7: 9437.44 | Z7: 9814.8 | AA7: 90531.34 | AB7: 10207.21 | AC7: 10615.5 | AD7: 11040.08 | AE7: 11481.8 | AF7: 11941.07 | AG7: 12418.73 | AH7: 12791.5 | AI7: 13175.13 | AJ7: 13570.47 | AK7: 13977.5 | AL7: 14396.66 | AM7: 14828.76 | AN7: 150444.41 | AO7: 15273.83 | AP7: 15731.85 | AQ7: 16203.65 | AR7: 16851.82 | AS7: 17525.89 | AT7: 18227.13 | AU7: 18956.36 | AV7: 19714.43 | AW7: 20503.01 | AX7: 21322.93 | AY7: 22175.86 | AZ7: 23063.07 | BA7: 225549.83 | BB7: 3346.34 | BC7: 0 | BD7: 0 | BE7: 0 | BF7: 0 | BG7: 0 | BH7: 0 | BI7: 0 | BJ7: 0 | BK7: 0 | BL7: 0 | BM7: 0 | BN7: 3346.34 | BO7: 0 | BP7: 0 | BQ7: 0 | BR7: 0 | BS7: 0 | BT7: 0 | BU7: 0 | BV7: 0 | BW7: 0 | BX7: 0 | BY7: 0 | BZ7: 0 | CA7: 0 | CB7: 0 | CC7: 0 | CD7: 0 | CE7: 0 | CF7: 0 | CG7: 0 | CH7: 0 | CI7: 0 | CJ7: 0 | CK7: 0 | CL7: 0 | CM7: 0 | CN7: 0 | CO7: 500000
A8: Aporte Diego AM Engenharia | B8: 208.95 | C8: 626.85 | D8: 1046.84 | E8: 1465.58 | F8: 1890.58 | G8: 2306.39 | H8: 2721.37 | I8: 3129.65 | J8: 3536.69 | K8: 3961.27 | L8: 4397.14 | M8: 4836.77 | N8: 30128.08 | O8: 5272.23 | P8: 5693.89 | Q8: 6092.56 | R8: 6519.24 | S8: 6910.39 | T8: 7324.95 | U8: 7764.58 | V8: 8152.81 | W8: 8560.26 | X8: 8988.19 | Y8: 9437.44 | Z8: 9814.8 | AA8: 90531.34 | AB8: 10207.21 | AC8: 10615.5 | AD8: 11040.08 | AE8: 11481.8 | AF8: 11941.07 | AG8: 12418.73 | AH8: 12791.5 | AI8: 13175.13 | AJ8: 13570.47 | AK8: 13977.5 | AL8: 14396.66 | AM8: 14828.76 | AN8: 150444.41 | AO8: 15273.83 | AP8: 15731.85 | AQ8: 16203.65 | AR8: 16851.82 | AS8: 17525.89 | AT8: 18227.13 | AU8: 18956.36 | AV8: 19714.43 | AW8: 20503.01 | AX8: 21322.93 | AY8: 22175.86 | AZ8: 23063.07 | BA8: 225549.83 | BB8: 3346.34 | BC8: 0 | BD8: 0 | BE8: 0 | BF8: 0 | BG8: 0 | BH8: 0 | BI8: 0 | BJ8: 0 | BK8: 0 | BL8: 0 | BM8: 0 | BN8: 3346.34 | BO8: 0 | BP8: 0 | BQ8: 0 | BR8: 0 | BS8: 0 | BT8: 0 | BU8: 0 | BV8: 0 | BW8: 0 | BX8: 0 | BY8: 0 | BZ8: 0 | CA8: 0 | CB8: 0 | CC8: 0 | CD8: 0 | CE8: 0 | CF8: 0 | CG8: 0 | CH8: 0 | CI8: 0 | CJ8: 0 | CK8: 0 | CL8: 0 | CM8: 0 | CN8: 0 | CO8: 500000
A9: Principal pago | B9: 208.95 | C9: 626.85 | D9: 1046.84 | E9: 1465.58 | F9: 1890.58 | G9: 2306.39 | H9: 2721.37 | I9: 3129.65 | J9: 3536.69 | K9: 3961.27 | L9: 4397.14 | M9: 4836.77 | N9: 30128.08 | O9: 5272.23 | P9: 5693.89 | Q9: 6092.56 | R9: 6519.24 | S9: 6910.39 | T9: 7324.95 | U9: 7764.58 | V9: 8152.81 | W9: 8560.26 | X9: 8988.19 | Y9: 9437.44 | Z9: 9814.8 | AA9: 90531.34 | AB9: 10207.21 | AC9: 10615.5 | AD9: 11040.08 | AE9: 11481.8 | AF9: 11941.07 | AG9: 12418.73 | AH9: 12791.5 | AI9: 13175.13 | AJ9: 13570.47 | AK9: 13977.5 | AL9: 14396.66 | AM9: 14828.76 | AN9: 150444.41 | AO9: 15273.83 | AP9: 15731.85 | AQ9: 16203.65 | AR9: 16851.82 | AS9: 17525.89 | AT9: 18227.13 | AU9: 18956.36 | AV9: 19714.43 | AW9: 20503.01 | AX9: 21322.93 | AY9: 22175.86 | AZ9: 23063.07 | BA9: 225549.83 | BB9: 3346.34 | BC9: 0 | BD9: 0 | BE9: 0 | BF9: 0 | BG9: 0 | BH9: 0 | BI9: 0 | BJ9: 0 | BK9: 0 | BL9: 0 | BM9: 0 | BN9: 3346.34 | BO9: 0 | BP9: 0 | BQ9: 0 | BR9: 0 | BS9: 0 | BT9: 0 | BU9: 0 | BV9: 0 | BW9: 0 | BX9: 0 | BY9: 0 | BZ9: 0 | CA9: 0 | CB9: 0 | CC9: 0 | CD9: 0 | CE9: 0 | CF9: 0 | CG9: 0 | CH9: 0 | CI9: 0 | CJ9: 0 | CK9: 0 | CL9: 0 | CM9: 0 | CN9: 0 | CO9: 500000
A10: Juros pagos | B10: 0 | C10: 0 | D10: 0 | E10: 0 | F10: 0 | G10: 0 | H10: 0 | I10: 0 | J10: 0 | K10: 0 | L10: 0 | M10: 0 | N10: 0 | O10: 0 | P10: 0 | Q10: 0 | R10: 0 | S10: 0 | T10: 0 | U10: 0 | V10: 0 | W10: 0 | X10: 0 | Y10: 0 | Z10: 0 | AA10: 0 | AB10: 0 | AC10: 0 | AD10: 0 | AE10: 0 | AF10: 0 | AG10: 0 | AH10: 0 | AI10: 0 | AJ10: 0 | AK10: 0 | AL10: 0 | AM10: 0 | AN10: 0 | AO10: 0 | AP10: 0 | AQ10: 0 | AR10: 0 | AS10: 0 | AT10: 0 | AU10: 0 | AV10: 0 | AW10: 0 | AX10: 0 | AY10: 0 | AZ10: 0 | BA10: 0 | BB10: 0 | BC10: 0 | BD10: 0 | BE10: 0 | BF10: 0 | BG10: 0 | BH10: 0 | BI10: 0 | BJ10: 0 | BK10: 0 | BL10: 0 | BM10: 0 | BN10: 0 | BO10: 0 | BP10: 0 | BQ10: 0 | BR10: 0 | BS10: 0 | BT10: 0 | BU10: 0 | BV10: 0 | BW10: 0 | BX10: 0 | BY10: 0 | BZ10: 0 | CA10: 0 | CB10: 0 | CC10: 0 | CD10: 0 | CE10: 0 | CF10: 0 | CG10: 0 | CH10: 0 | CI10: 0 | CJ10: 0 | CK10: 0 | CL10: 0 | CM10: 0 | CN10: 0 | CO10: 0
A12: Dívida Total | B12: 24791.05 | C12: 49164.2 | D12: 73117.36 | E12: 96651.78 | F12: 119761.2 | G12: 142454.81 | H12: 164733.44 | I12: 186603.79 | J12: 208067.1 | K12: 229105.83 | L12: 249708.69 | M12: 269871.92 | N12: 269871.92 | O12: 289599.69 | P12: 308905.8 | Q12: 327813.24 | R12: 346294 | S12: 364383.61 | T12: 382058.66 | U12: 399294.08 | V12: 416141.27 | W12: 407581.01 | X12: 398592.82 | Y12: 389155.38 | Z12: 379340.58 | AA12: 379340.58 | AB12: 369133.37 | AC12: 358517.87 | AD12: 347477.79 | AE12: 335995.99 | AF12: 324054.92 | AG12: 311636.19 | AH12: 298844.69 | AI12: 285669.56 | AJ12: 272099.09 | AK12: 258121.59 | AL12: 243724.93 | AM12: 228896.17 | AN12: 228896.17 | AO12: 213622.34 | AP12: 197890.49 | AQ12: 181686.84 | AR12: 164835.02 | AS12: 147309.13 | AT12: 129082 | AU12: 110125.64 | AV12: 90411.21 | AW12: 69908.2 | AX12: 48585.27 | AY12: 26409.41 | AZ12: 3346.34 | BA12: 3346.34 | BB12: 0 | BC12: 0 | BD12: 0 | BE12: 0 | BF12: 0 | BG12: 0 | BH12: 0 | BI12: 0 | BJ12: 0 | BK12: 0 | BL12: 0 | BM12: 0 | BN12: 0 | BO12: 0 | BP12: 0 | BQ12: 0 | BR12: 0 | BS12: 0 | BT12: 0 | BU12: 0 | BV12: 0 | BW12: 0 | BX12: 0 | BY12: 0 | BZ12: 0 | CA12: 0 | CB12: 0 | CC12: 0 | CD12: 0 | CE12: 0 | CF12: 0 | CG12: 0 | CH12: 0 | CI12: 0 | CJ12: 0 | CK12: 0 | CL12: 0 | CM12: 0 | CN12: 0 | CO12: 0
A13: Dívida de curto prazo | B13: 0 | C13: 0 | D13: 0 | E13: 0 | F13: 0 | G13: 0 | H13: 0 | I13: 0 | J13: 0 | K13: 0 | L13: 0 | M13: 0 | N13: 0 | O13: 0 | P13: 0 | Q13: 0 | R13: 0 | S13: 0 | T13: 0 | U13: 0 | V13: 0 | W13: 0 | X13: 0 | Y13: 0 | Z13: 0 | AA13: 0 | AB13: 0 | AC13: 0 | AD13: 0 | AE13: 0 | AF13: 0 | AG13: 0 | AH13: 0 | AI13: 0 | AJ13: 0 | AK13: 0 | AL13: 0 | AM13: 0 | AN13: 0 | AO13: 0 | AP13: 0 | AQ13: 0 | AR13: 0 | AS13: 0 | AT13: 0 | AU13: 0 | AV13: 0 | AW13: 0 | AX13: 0 | AY13: 0 | AZ13: 0 | BA13: 0 | BB13: 0 | BC13: 0 | BD13: 0 | BE13: 0 | BF13: 0 | BG13: 0 | BH13: 0 | BI13: 0 | BJ13: 0 | BK13: 0 | BL13: 0 | BM13: 0 | BN13: 0 | BO13: 0 | BP13: 0 | BQ13: 0 | BR13: 0 | BS13: 0 | BT13: 0 | BU13: 0 | BV13: 0 | BW13: 0 | BX13: 0 | BY13: 0 | BZ13: 0 | CA13: 0 | CB13: 0 | CC13: 0 | CD13: 0 | CE13: 0 | CF13: 0 | CG13: 0 | CH13: 0 | CI13: 0 | CJ13: 0 | CK13: 0 | CL13: 0 | CM13: 0 | CN13: 0 | CO13: 0
A14: Funding | B14: 0 | C14: 0 | D14: 0 | E14: 0 | F14: 0 | G14: 0 | H14: 0 | I14: 0 | J14: 0 | K14: 0 | L14: 0 | M14: 0 | N14: 0 | O14: 0 | P14: 0 | Q14: 0 | R14: 0 | S14: 0 | T14: 0 | U14: 0 | V14: 0 | W14: 0 | X14: 0 | Y14: 0 | Z14: 0 | AA14: 0 | AB14: 0 | AC14: 0 | AD14: 0 | AE14: 0 | AF14: 0 | AG14: 0 | AH14: 0 | AI14: 0 | AJ14: 0 | AK14: 0 | AL14: 0 | AM14: 0 | AN14: 0 | AO14: 0 | AP14: 0 | AQ14: 0 | AR14: 0 | AS14: 0 | AT14: 0 | AU14: 0 | AV14: 0 | AW14: 0 | AX14: 0 | AY14: 0 | AZ14: 0 | BA14: 0 | BB14: 0 | BC14: 0 | BD14: 0 | BE14: 0 | BF14: 0 | BG14: 0 | BH14: 0 | BI14: 0 | BJ14: 0 | BK14: 0 | BL14: 0 | BM14: 0 | BN14: 0 | BO14: 0 | BP14: 0 | BQ14: 0 | BR14: 0 | BS14: 0 | BT14: 0 | BU14: 0 | BV14: 0 | BW14: 0 | BX14: 0 | BY14: 0 | BZ14: 0 | CA14: 0 | CB14: 0 | CC14: 0 | CD14: 0 | CE14: 0 | CF14: 0 | CG14: 0 | CH14: 0 | CI14: 0 | CJ14: 0 | CK14: 0 | CL14: 0 | CM14: 0 | CN14: 0 | CO14: 0
A15: Aporte Diego AM Engenharia | B15: 0 | C15: 0 | D15: 0 | E15: 0 | F15: 0 | G15: 0 | H15: 0 | I15: 0 | J15: 0 | K15: 0 | L15: 0 | M15: 0 | N15: 0 | O15: 0 | P15: 0 | Q15: 0 | R15: 0 | S15: 0 | T15: 0 | U15: 0 | V15: 0 | W15: 0 | X15: 0 | Y15: 0 | Z15: 0 | AA15: 0 | AB15: 0 | AC15: 0 | AD15: 0 | AE15: 0 | AF15: 0 | AG15: 0 | AH15: 0 | AI15: 0 | AJ15: 0 | AK15: 0 | AL15: 0 | AM15: 0 | AN15: 0 | AO15: 0 | AP15: 0 | AQ15: 0 | AR15: 0 | AS15: 0 | AT15: 0 | AU15: 0 | AV15: 0 | AW15: 0 | AX15: 0 | AY15: 0 | AZ15: 0 | BA15: 0 | BB15: 0 | BC15: 0 | BD15: 0 | BE15: 0 | BF15: 0 | BG15: 0 | BH15: 0 | BI15: 0 | BJ15: 0 | BK15: 0 | BL15: 0 | BM15: 0 | BN15: 0 | BO15: 0 | BP15: 0 | BQ15: 0 | BR15: 0 | BS15: 0 | BT15: 0 | BU15: 0 | BV15: 0 | BW15: 0 | BX15: 0 | BY15: 0 | BZ15: 0 | CA15: 0 | CB15: 0 | CC15: 0 | CD15: 0 | CE15: 0 | CF15: 0 | CG15: 0 | CH15: 0 | CI15: 0 | CJ15: 0 | CK15: 0 | CL15: 0 | CM15: 0 | CN15: 0 | CO15: 0
... A18: Aporte Diego AM Engenharia | B18: 24791.05 | C18: 49164.2 | D18: 73117.36 | E18: 96651.78 | F18: 119761.2 | G18: 142454.81 | H18: 164733.44 | I18: 186603.79 | J18: 208067.1 | K18: 229105.83 | L18: 249708.69 | M18: 269871.92 | N18: 269871.92 | O18: 289599.69 | P18: 308905.8 | Q18: 327813.24 | R18: 346294 | S18: 364383.61 | T18: 382058.66 | U18: 399294.08 | V18: 416141.27 | W18: 407581.01 | X18: 398592.82 | Y18: 389155.38 | Z18: 379340.58 | AA18: 379340.58 | AB18: 369133.37 | AC18: 358517.87 | AD18: 347477.79 | AE18: 335995.99 | AF18: 324054.92 | AG18: 311636.19 | AH18: 298844.69 | AI18: 285669.56 | AJ18: 272099.09 | AK18: 258121.59 | AL18: 243724.93 | AM18: 228896.17 | AN18: 228896.17 | AO18: 213622.34 | AP18: 197890.49 | AQ18: 181686.84 | AR18: 164835.02 | AS18: 147309.13 | AT18: 129082 | AU18: 110125.64 | AV18: 90411.21 | AW18: 69908.2 | AX18: 48585.27 | AY18: 26409.41 | AZ18: 3346.34 | BA18: 3346.34 | BB18: 0 | BC18: 0 | BD18: 0 | BE18: 0 | BF18: 0 | BG18: 0 | BH18: 0 | BI18: 0 | BJ18: 0 | BK18: 0 | BL18: 0 | BM18: 0 | BN18: 0 | BO18: 0 | BP18: 0 | BQ18: 0 | BR18: 0 | BS18: 0 | BT18: 0 | BU18: 0 | BV18: 0 | BW18: 0 | BX18: 0 | BY18: 0 | BZ18: 0 | CA18: 0 | CB18: 0 | CC18: 0 | CD18: 0 | CE18: 0 | CF18: 0 | CG18: 0 | CH18: 0 | CI18: 0 | CJ18: 0 | CK18: 0 | CL18: 0 | CM18: 0 | CN18: 0 | CO18: 0

Sheet Valores - Ativos
